Workbook

Sheet PARTNERS SUMMARY
G1: SEPT 5G Router (ODU) Leads | O1: OCT 5G Router (ODU) Leads | X1: NOV 5G Router (ODU) Leads | AJ1: ENTERPRISE PARTNERS CONVERTED LEADS DOD
A2: EBB PARTNERS FWA LEADS SUMMARY | G2: =SUBTOTAL(9,G4:G1048571) -> 42 | H2: =SUBTOTAL(9,H4:H1048571) -> 25 | I2: =SUBTOTAL(9,I4:I1048571) -> 12 | J2: =SUBTOTAL(9,J4:J1048571) -> 2 | K2: =SUBTOTAL(9,K4:K1048571) -> 3 | L2: =SUBTOTAL(9,L4:L1048571) -> 16 | M2: =IFERROR(L2/G2,0) -> 0.38095238 | O2: =SUBTOTAL(9,O4:O1048571) -> 808 | P2: =SUBTOTAL(9,P4:P1048571) -> 7 | Q2: =SUBTOTAL(9,Q4:Q1048571) -> 513 | R2: =SUBTOTAL(9,R4:R1048571) -> 184 | S2: =SUBTOTAL(9,S4:S1048571) -> 98 | T2: =SUBTOTAL(9,T4:T1048571) -> 6 | U2: =SUBTOTAL(9,U4:U1048571) -> 335 | V2: =IFERROR(U2/O2,0) -> 0.41460396 | X2: =SUBTOTAL(9,X4:X1048571) -> 1269 | Y2: =SUBTOTAL(9,Y4:Y1048571) -> 2 | Z2: =SUBTOTAL(9,Z4:Z1048571) -> 285 | AA2: =SUBTOTAL(9,AA4:AA1048571) -> 107 | AB2: =SUBTOTAL(9,AB4:AB1048571) -> 11 | AC2: =SUBTOTAL(9,AC4:AC1048571) -> 0 | AD2: =SUBTOTAL(9,AD4:AD1048571) -> 613 | AE2: Nov | AF2: =IFERROR(AD2/X2,0) -> 0.48305753 | AH2: =SUM(AH4:AH157) -> 0 | AI2: =SUM(AI4:AI157) -> 0 | AJ2: =SUM(AJ4:AJ157) -> 0 | AK2: =SUM(AK4:AK157) -> 0 | AL2: =SUM(AL4:AL157) -> 0 | AM2: =SUM(AM4:AM157) -> 0 | AN2: =SUM(AN4:AN157) -> 0 | AO2: =SUM(AO4:AO157) -> 0 | ... DI2: =SUM(DI4:DI157) -> 23 | DJ2: =SUBTOTAL(9,DJ4:DJ1048576) -> 34 | DK2: =SUBTOTAL(9,DK4:DK1048576) -> 21 | DL2: =SUBTOTAL(9,DL4:DL1048576) -> 31 | DM2: =SUBTOTAL(9,DM4:DM1048576) -> 24 | DN2: =SUBTOTAL(9,DN4:DN1048576) -> 23 | DO2: =SUBTOTAL(9,DO4:DO1048576) -> 30 | DP2: =SUBTOTAL(9,DP4:DP1048576) -> 0 | DQ2: =SUBTOTAL(9,DQ4:DQ1048576) -> 0 | ... EY2: =SUBTOTAL(9,EY4:EY1048576) -> 0
A3: PAE | B3: Partners Name | C3: KYC_ID | D3: EMAIL ID | E3: Zone | F3: REGION | G3: Leads | H3: Confirmed | I3: Rejected | J3: Unreachable | K3: Postponed(Update W) | L3: Converted/waiting conversion | M3: Conv. Rate (%) | O3: Leads | P3: Prospect | Q3: Confirmed | R3: Rejected | S3: Unreachable | T3: Postponed(Update W) | U3: Converted/waiting conversion | V3: Conv. Rate (%) | X3: Leads | Y3: Prospect | Z3: Confirmed | AA3: Rejected | AB3: Unreachable | AC3: Postponed(Update W) | AD3: Converted/waiting conversion | AE3: Wrongly Leads MTD | AF3: Conv. Rate (%) | AH3: 45901 | AI3: 45902 | AJ3: 45903 | AK3: 45904 | AL3: 45905 | AM3: 45906 | AN3: 45907 | AO3: 45908 | AP3: 45909 | AQ3: 45910 | AR3: 45911 | AS3: 45912 | AT3: 45913 | AU3: 45914 | AV3: 45915 | AW3: 45916 | AX3: 45917 | AY3: 45918 | AZ3: 45919 | BA3: 45920 | BB3: 45921 | BC3: 45922 | BD3: 45923 | BE3: 45924 | BF3: 45925 | BG3: 45926 | BH3: 45927 | BI3: 45928 | BJ3: 45929 | BK3: 45930 | BL3: 45931 | BM3: 45932 | BN3: 45933 | BO3: 45934 | BP3: 45935 | BQ3: 45936 | BR3: 45937 | BS3: 45938 | BT3: 45939 | BU3: 45940 | BV3: 45941 | BW3: 45942 | BX3: 45943 | BY3: 45944 | BZ3: 45945 | CA3: 45946 | CB3: 45947 | CC3: 45948 | CD3: 45949 | CE3: 45950 | CF3: 45951 | CG3: 45952 | CH3: 45953 | CI3: 45954 | CJ3: 45955 | CK3: 45956 | CL3: 45957 | CM3: 45958 | CN3: 45959 | CO3: 45960 | CP3: 45961 | CQ3: 45962 | CR3: 45963 | CS3: 45964 | CT3: 45965 | CU3: 45966 | CV3: 45967 | CW3: 45968 | CX3: 45969 | CY3: 45970 | CZ3: 45971 | DA3: 45972 | DB3: 45973 | DC3: 45974 | DD3: 45975 | DE3: 45976 | DF3: 45977 | DG3: 45978 | DH3: 45979 | DI3: 45980 | DJ3: 45981 | DK3: 45982 | DL3: 45983 | DM3: 45984 | DN3: 45985 | DO3: 45986 | DP3: 45987 | DQ3: 45988 | DR3: 45989 | DS3: 45990 | DT3: 45991 | DU3: 45992 | DV3: 45993 | DW3: 45994 | DX3: 45995 | DY3: 45996 | DZ3: 45997 | EA3: 45998 | EB3: 45999 | EC3: 46000 | ED3: 46001 | EE3: 46002 | EF3: 46003 | EG3: 46004 | EH3: 46005 | EI3: 46006 | EJ3: 46007 | EK3: 46008 | EL3: 46009 | EM3: 46010 | EN3: 46011 | EO3: 46012 | EP3: 46013 | EQ3: 46014 | ER3: 46015 | ES3: 46016 | ET3: 46017 | EU3: 46018 | EV3: 46019 | EW3: 46020 | EX3: 46021 | EY3: 46022
A4: Mariana Hongo | B4: STRATON AND CRAPHT LIMITED | C4: 751785175 | D4: Warierowycliffe@gmail.com | E4: Kisumu | F4: Western | G4: =COUNTIF('SEPT DUMP '!$C:$C,'PARTNERS SUMMARY'!$B4) -> 12 | H4: =COUNTIFS('SEPT DUMP '!$C:$C,'PARTNERS SUMMARY'!$B4,'SEPT DUMP '!$O:$O,"Confirmed") -> 9 | I4: =COUNTIFS('SEPT DUMP '!$C:$C,'PARTNERS SUMMARY'!$B4,'SEPT DUMP '!$O:$O,"Rejected") -> 3 | J4: =COUNTIFS('SEPT DUMP '!$C:$C,'PARTNERS SUMMARY'!$B4,'SEPT DUMP '!$O:$O,"Unreachable") -> 0 | K4: =COUNTIFS('SEPT DUMP '!$C:$C,'PARTNERS SUMMARY'!$B4,'SEPT DUMP '!$O:$O,"Postponed(Update Y)") -> 0 | L4: =SUM(AH4:BK4) -> 3 | M4: =IFERROR(L4/G4,0) -> 0.25 | O4: =COUNTIF('OCT DUMP'!$D:$D,'PARTNERS SUMMARY'!$B4) -> 306 | P4: =COUNTIFS('OCT DUMP'!$D:$D,'PARTNERS SUMMARY'!$B4,'OCT DUMP'!Q:Q,"Prospect") -> 0 | Q4: =COUNTIFS('OCT DUMP'!$D:$D,'PARTNERS SUMMARY'!$B4,'OCT DUMP'!$Q:$Q,"Confirmed") -> 184 | R4: =COUNTIFS('OCT DUMP'!$D:$D,'PARTNERS SUMMARY'!$B4,'OCT DUMP'!$Q:$Q,"Rejected") -> 83 | S4: =COUNTIFS('OCT DUMP'!$D:$D,'PARTNERS SUMMARY'!$B4,'OCT DUMP'!$Q:$Q,"Unreachable") -> 39 | T4: =COUNTIFS('OCT DUMP'!$D:$D,'PARTNERS SUMMARY'!$B4,'OCT DUMP'!$Q:$Q,"Postponed(Update Y)") -> 0 | U4: =SUM(BL4:CP4) -> 159 | V4: =IFERROR(U4/O4,0) -> 0.51960784 | X4: =COUNTIF('NOV DUMP'!C:C,'PARTNERS SUMMARY'!$B4) -> 199 | Y4: =COUNTIFS('NOV DUMP'!$C:$C,'PARTNERS SUMMARY'!$B4,'NOV DUMP'!$S:$S,"Prospect") -> 0 | Z4: =COUNTIFS('NOV DUMP'!$C:$C,'PARTNERS SUMMARY'!$B4,'NOV DUMP'!$S:$S,"Confirmed") -> 50 | AA4: =COUNTIFS('NOV DUMP'!$C:$C,'PARTNERS SUMMARY'!$B4,'NOV DUMP'!$S:$S,"Rejected") -> 16 | AB4: =COUNTIFS('NOV DUMP'!$C:$C,'PARTNERS SUMMARY'!$B4,'NOV DUMP'!$S:$S,"Unreachable") -> 0 | AC4: =COUNTIFS('NOV DUMP'!$C:$C,'PARTNERS SUMMARY'!$B4,'NOV DUMP'!$S:$S,"Postponed(Update Y)") -> 0 | AD4: =SUM(CQ4:DT4) -> 164 | AE4: =COUNTIFS('ACTIVATED LEADS '!$H:$H,'PARTNERS SUMMARY'!$B4,'ACTIVATED LEADS '!$K:$K,'PARTNERS SUMMARY'!$AE$2,'ACTIVATED LEADS '!$C:$C,"16") -> 99 | AF4: =IFERROR(AD4/X4,0) -> 0.8241206 | AH4: =COUNTIFS('ACTIVATED LEADS '!$H:$H,$B4,'ACTIVATED LEADS '!$D:$D,'PARTNERS SUMMARY'!AH$3) -> 0 | AI4: =COUNTIFS('ACTIVATED LEADS '!$H:$H,$B4,'ACTIVATED LEADS '!$D:$D,'PARTNERS SUMMARY'!AI$3) -> 0 | AJ4: =COUNTIFS('ACTIVATED LEADS '!$H:$H,$B4,'ACTIVATED LEADS '!$D:$D,'PARTNERS SUMMARY'!AJ$3) -> 0 | AK4: =COUNTIFS('ACTIVATED LEADS '!$H:$H,$B4,'ACTIVATED LEADS '!$D:$D,'PARTNERS SUMMARY'!AK$3) -> 0 | AL4: =COUNTIFS('ACTIVATED LEADS '!$H:$H,$B4,'ACTIVATED LEADS '!$D:$D,'PARTNERS SUMMARY'!AL$3) -> 0 | AM4: =COUNTIFS('ACTIVATED LEADS '!$H:$H,$B4,'ACTIVATED LEADS '!$D:$D,'PARTNERS SUMMARY'!AM$3) -> 0 | AN4: =COUNTIFS('ACTIVATED LEADS '!$H:$H,$B4,'ACTIVATED LEADS '!$D:$D,'PARTNERS SUMMARY'!AN$3) -> 0 | AO4: =COUNTIFS('ACTIVATED LEADS '!$H:$H,$B4,'ACTIVATED LEADS '!$D:$D,'PARTNERS SUMMARY'!AO$3) -> 0 | ... DO4: =COUNTIFS('ACTIVATED LEADS '!$H:$H,$B4,'ACTIVATED LEADS '!$D:$D,'PARTNERS SUMMARY'!DO$3) -> 2
A5: Brian Odero | B5: SYLVERENE COMMUNICATION | C5: 735820631 | D5: Wanderaclinton2@gmail.com | E5: two rivers | F5: Nairobi | G5: =COUNTIF('SEPT DUMP '!$C:$C,'PARTNERS SUMMARY'!$B5) -> 6 | H5: =COUNTIFS('SEPT DUMP '!$C:$C,'PARTNERS SUMMARY'!$B5,'SEPT DUMP '!$O:$O,"Confirmed") -> 2 | I5: =COUNTIFS('SEPT DUMP '!$C:$C,'PARTNERS SUMMARY'!$B5,'SEPT DUMP '!$O:$O,"Rejected") -> 3 | J5: =COUNTIFS('SEPT DUMP '!$C:$C,'PARTNERS SUMMARY'!$B5,'SEPT DUMP '!$O:$O,"Unreachable") -> 1 | K5: =COUNTIFS('SEPT DUMP '!$C:$C,'PARTNERS SUMMARY'!$B5,'SEPT DUMP '!$O:$O,"Postponed(Update Y)") -> 0 | L5: =SUM(AH5:BK5) -> 2 | M5: =IFERROR(L5/G5,0) -> 0.33333333 | O5: =COUNTIF('OCT DUMP'!$D:$D,'PARTNERS SUMMARY'!$B5) -> 172 | P5: =COUNTIFS('OCT DUMP'!$D:$D,'PARTNERS SUMMARY'!$B5,'OCT DUMP'!Q:Q,"Prospect") -> 1 | Q5: =COUNTIFS('OCT DUMP'!$D:$D,'PARTNERS SUMMARY'!$B5,'OCT DUMP'!$Q:$Q,"Confirmed") -> 108 | R5: =COUNTIFS('OCT DUMP'!$D:$D,'PARTNERS SUMMARY'!$B5,'OCT DUMP'!$Q:$Q,"Rejected") -> 43 | S5: =COUNTIFS('OCT DUMP'!$D:$D,'PARTNERS SUMMARY'!$B5,'OCT DUMP'!$Q:$Q,"Unreachable") -> 19 | T5: =COUNTIFS('OCT DUMP'!$D:$D,'PARTNERS SUMMARY'!$B5,'OCT DUMP'!$Q:$Q,"Postponed(Update Y)") -> 1 | U5: =SUM(BL5:CP5) -> 44 | V5: =IFERROR(U5/O5,0) -> 0.25581395 | X5: =COUNTIF('NOV DUMP'!C:C,'PARTNERS SUMMARY'!$B5) -> 275 | Y5: =COUNTIFS('NOV DUMP'!$C:$C,'PARTNERS SUMMARY'!$B5,'NOV DUMP'!$S:$S,"Prospect") -> 0 | Z5: =COUNTIFS('NOV DUMP'!$C:$C,'PARTNERS SUMMARY'!$B5,'NOV DUMP'!$S:$S,"Confirmed") -> 58 | AA5: =COUNTIFS('NOV DUMP'!$C:$C,'PARTNERS SUMMARY'!$B5,'NOV DUMP'!$S:$S,"Rejected") -> 34 | AB5: =COUNTIFS('NOV DUMP'!$C:$C,'PARTNERS SUMMARY'!$B5,'NOV DUMP'!$S:$S,"Unreachable") -> 2 | AC5: =COUNTIFS('NOV DUMP'!$C:$C,'PARTNERS SUMMARY'!$B5,'NOV DUMP'!$S:$S,"Postponed(Update Y)") -> 0 | AD5: =SUM(CQ5:DT5) -> 113 | AE5: =COUNTIFS('ACTIVATED LEADS '!$H:$H,'PARTNERS SUMMARY'!$B5,'ACTIVATED LEADS '!$K:$K,'PARTNERS SUMMARY'!$AE$2,'ACTIVATED LEADS '!$C:$C,"16") -> 81 | AF5: =IFERROR(AD5/X5,0) -> 0.41090909 | AH5: =COUNTIFS('ACTIVATED LEADS '!$H:$H,$B5,'ACTIVATED LEADS '!$D:$D,'PARTNERS SUMMARY'!AH$3) -> 0 | AI5: =COUNTIFS('ACTIVATED LEADS '!$H:$H,$B5,'ACTIVATED LEADS '!$D:$D,'PARTNERS SUMMARY'!AI$3) -> 0 | AJ5: =COUNTIFS('ACTIVATED LEADS '!$H:$H,$B5,'ACTIVATED LEADS '!$D:$D,'PARTNERS SUMMARY'!AJ$3) -> 0 | AK5: =COUNTIFS('ACTIVATED LEADS '!$H:$H,$B5,'ACTIVATED LEADS '!$D:$D,'PARTNERS SUMMARY'!AK$3) -> 0 | AL5: =COUNTIFS('ACTIVATED LEADS '!$H:$H,$B5,'ACTIVATED LEADS '!$D:$D,'PARTNERS SUMMARY'!AL$3) -> 0 | AM5: =COUNTIFS('ACTIVATED LEADS '!$H:$H,$B5,'ACTIVATED LEADS '!$D:$D,'PARTNERS SUMMARY'!AM$3) -> 0 | AN5: =COUNTIFS('ACTIVATED LEADS '!$H:$H,$B5,'ACTIVATED LEADS '!$D:$D,'PARTNERS SUMMARY'!AN$3) -> 0 | AO5: =COUNTIFS('ACTIVATED LEADS '!$H:$H,$B5,'ACTIVATED LEADS '!$D:$D,'PARTNERS SUMMARY'!AO$3) -> 0 | ... DO5: =COUNTIFS('ACTIVATED LEADS '!$H:$H,$B5,'ACTIVATED LEADS '!$D:$D,'PARTNERS SUMMARY'!DO$3) -> 3
A6: Mariana Hongo | B6: DAVIJO DISTRIBUTORS | C6: 781446693 | D6: beatriceokinyi9@gmail.com | E6: Kisumu | F6: Western | G6: =COUNTIF('SEPT DUMP '!$C:$C,'PARTNERS SUMMARY'!$B6) -> 13 | H6: =COUNTIFS('SEPT DUMP '!$C:$C,'PARTNERS SUMMARY'!$B6,'SEPT DUMP '!$O:$O,"Confirmed") -> 6 | I6: =COUNTIFS('SEPT DUMP '!$C:$C,'PARTNERS SUMMARY'!$B6,'SEPT DUMP '!$O:$O,"Rejected") -> 4 | J6: =COUNTIFS('SEPT DUMP '!$C:$C,'PARTNERS SUMMARY'!$B6,'SEPT DUMP '!$O:$O,"Unreachable") -> 1 | K6: =COUNTIFS('SEPT DUMP '!$C:$C,'PARTNERS SUMMARY'!$B6,'SEPT DUMP '!$O:$O,"Postponed(Update Y)") -> 2 | L6: =SUM(AH6:BK6) -> 5 | M6: =IFERROR(L6/G6,0) -> 0.38461538 | O6: =COUNTIF('OCT DUMP'!$D:$D,'PARTNERS SUMMARY'!$B6) -> 26 | P6: =COUNTIFS('OCT DUMP'!$D:$D,'PARTNERS SUMMARY'!$B6,'OCT DUMP'!Q:Q,"Prospect") -> 0 | Q6: =COUNTIFS('OCT DUMP'!$D:$D,'PARTNERS SUMMARY'!$B6,'OCT DUMP'!$Q:$Q,"Confirmed") -> 14 | R6: =COUNTIFS('OCT DUMP'!$D:$D,'PARTNERS SUMMARY'!$B6,'OCT DUMP'!$Q:$Q,"Rejected") -> 8 | S6: =COUNTIFS('OCT DUMP'!$D:$D,'PARTNERS SUMMARY'!$B6,'OCT DUMP'!$Q:$Q,"Unreachable") -> 3 | T6: =COUNTIFS('OCT DUMP'!$D:$D,'PARTNERS SUMMARY'!$B6,'OCT DUMP'!$Q:$Q,"Postponed(Update Y)") -> 1 | U6: =SUM(BL6:CP6) -> 9 | V6: =IFERROR(U6/O6,0) -> 0.34615385 | X6: =COUNTIF('NOV DUMP'!C:C,'PARTNERS SUMMARY'!$B6) -> 35 | Y6: =COUNTIFS('NOV DUMP'!$C:$C,'PARTNERS SUMMARY'!$B6,'NOV DUMP'!$S:$S,"Prospect") -> 0 | Z6: =COUNTIFS('NOV DUMP'!$C:$C,'PARTNERS SUMMARY'!$B6,'NOV DUMP'!$S:$S,"Confirmed") -> 9 | AA6: =COUNTIFS('NOV DUMP'!$C:$C,'PARTNERS SUMMARY'!$B6,'NOV DUMP'!$S:$S,"Rejected") -> 1 | AB6: =COUNTIFS('NOV DUMP'!$C:$C,'PARTNERS SUMMARY'!$B6,'NOV DUMP'!$S:$S,"Unreachable") -> 0 | AC6: =COUNTIFS('NOV DUMP'!$C:$C,'PARTNERS SUMMARY'!$B6,'NOV DUMP'!$S:$S,"Postponed(Update Y)") -> 0 | AD6: =SUM(CQ6:DT6) -> 20 | AE6: =COUNTIFS('ACTIVATED LEADS '!$H:$H,'PARTNERS SUMMARY'!$B6,'ACTIVATED LEADS '!$K:$K,'PARTNERS SUMMARY'!$AE$2,'ACTIVATED LEADS '!$C:$C,"16") -> 6 | AF6: =IFERROR(AD6/X6,0) -> 0.57142857 | AH6: =COUNTIFS('ACTIVATED LEADS '!$H:$H,$B6,'ACTIVATED LEADS '!$D:$D,'PARTNERS SUMMARY'!AH$3) -> 0 | AI6: =COUNTIFS('ACTIVATED LEADS '!$H:$H,$B6,'ACTIVATED LEADS '!$D:$D,'PARTNERS SUMMARY'!AI$3) -> 0 | AJ6: =COUNTIFS('ACTIVATED LEADS '!$H:$H,$B6,'ACTIVATED LEADS '!$D:$D,'PARTNERS SUMMARY'!AJ$3) -> 0 | AK6: =COUNTIFS('ACTIVATED LEADS '!$H:$H,$B6,'ACTIVATED LEADS '!$D:$D,'PARTNERS SUMMARY'!AK$3) -> 0 | AL6: =COUNTIFS('ACTIVATED LEADS '!$H:$H,$B6,'ACTIVATED LEADS '!$D:$D,'PARTNERS SUMMARY'!AL$3) -> 0 | AM6: =COUNTIFS('ACTIVATED LEADS '!$H:$H,$B6,'ACTIVATED LEADS '!$D:$D,'PARTNERS SUMMARY'!AM$3) -> 0 | AN6: =COUNTIFS('ACTIVATED LEADS '!$H:$H,$B6,'ACTIVATED LEADS '!$D:$D,'PARTNERS SUMMARY'!AN$3) -> 0 | AO6: =COUNTIFS('ACTIVATED LEADS '!$H:$H,$B6,'ACTIVATED LEADS '!$D:$D,'PARTNERS SUMMARY'!AO$3) -> 0 | ... DO6: =COUNTIFS('ACTIVATED LEADS '!$H:$H,$B6,'ACTIVATED LEADS '!$D:$D,'PARTNERS SUMMARY'!DO$3) -> 2
A7: Brian Odero | B7: DENTECH INNOVATIONS | C7: 107373669 | D7: geoffreywasikeh@gmail.com | E7: Nairobi | F7: Nairobi | G7: =COUNTIF('SEPT DUMP '!$C:$C,'PARTNERS SUMMARY'!$B7) -> 2 | H7: =COUNTIFS('SEPT DUMP '!$C:$C,'PARTNERS SUMMARY'!$B7,'SEPT DUMP '!$O:$O,"Confirmed") -> 1 | I7: =COUNTIFS('SEPT DUMP '!$C:$C,'PARTNERS SUMMARY'!$B7,'SEPT DUMP '!$O:$O,"Rejected") -> 1 | J7: =COUNTIFS('SEPT DUMP '!$C:$C,'PARTNERS SUMMARY'!$B7,'SEPT DUMP '!$O:$O,"Unreachable") -> 0 | K7: =COUNTIFS('SEPT DUMP '!$C:$C,'PARTNERS SUMMARY'!$B7,'SEPT DUMP '!$O:$O,"Postponed(Update Y)") -> 0 | L7: =SUM(AH7:BK7) -> 1 | M7: =IFERROR(L7/G7,0) -> 0.5 | O7: =COUNTIF('OCT DUMP'!$D:$D,'PARTNERS SUMMARY'!$B7) -> 17 | P7: =COUNTIFS('OCT DUMP'!$D:$D,'PARTNERS SUMMARY'!$B7,'OCT DUMP'!Q:Q,"Prospect") -> 0 | Q7: =COUNTIFS('OCT DUMP'!$D:$D,'PARTNERS SUMMARY'!$B7,'OCT DUMP'!$Q:$Q,"Confirmed") -> 14 | R7: =COUNTIFS('OCT DUMP'!$D:$D,'PARTNERS SUMMARY'!$B7,'OCT DUMP'!$Q:$Q,"Rejected") -> 2 | S7: =COUNTIFS('OCT DUMP'!$D:$D,'PARTNERS SUMMARY'!$B7,'OCT DUMP'!$Q:$Q,"Unreachable") -> 1 | T7: =COUNTIFS('OCT DUMP'!$D:$D,'PARTNERS SUMMARY'!$B7,'OCT DUMP'!$Q:$Q,"Postponed(Update Y)") -> 0 | U7: =SUM(BL7:CP7) -> 15 | V7: =IFERROR(U7/O7,0) -> 0.88235294 | X7: =COUNTIF('NOV DUMP'!C:C,'PARTNERS SUMMARY'!$B7) -> 16 | Y7: =COUNTIFS('NOV DUMP'!$C:$C,'PARTNERS SUMMARY'!$B7,'NOV DUMP'!$S:$S,"Prospect") -> 0 | Z7: =COUNTIFS('NOV DUMP'!$C:$C,'PARTNERS SUMMARY'!$B7,'NOV DUMP'!$S:$S,"Confirmed") -> 2 | AA7: =COUNTIFS('NOV DUMP'!$C:$C,'PARTNERS SUMMARY'!$B7,'NOV DUMP'!$S:$S,"Rejected") -> 1 | AB7: =COUNTIFS('NOV DUMP'!$C:$C,'PARTNERS SUMMARY'!$B7,'NOV DUMP'!$S:$S,"Unreachable") -> 0 | AC7: =COUNTIFS('NOV DUMP'!$C:$C,'PARTNERS SUMMARY'!$B7,'NOV DUMP'!$S:$S,"Postponed(Update Y)") -> 0 | AD7: =SUM(CQ7:DT7) -> 16 | AE7: =COUNTIFS('ACTIVATED LEADS '!$H:$H,'PARTNERS SUMMARY'!$B7,'ACTIVATED LEADS '!$K:$K,'PARTNERS SUMMARY'!$AE$2,'ACTIVATED LEADS '!$C:$C,"16") -> 9 | AF7: =IFERROR(AD7/X7,0) -> 1 | AH7: =COUNTIFS('ACTIVATED LEADS '!$H:$H,$B7,'ACTIVATED LEADS '!$D:$D,'PARTNERS SUMMARY'!AH$3) -> 0 | AI7: =COUNTIFS('ACTIVATED LEADS '!$H:$H,$B7,'ACTIVATED LEADS '!$D:$D,'PARTNERS SUMMARY'!AI$3) -> 0 | AJ7: =COUNTIFS('ACTIVATED LEADS '!$H:$H,$B7,'ACTIVATED LEADS '!$D:$D,'PARTNERS SUMMARY'!AJ$3) -> 0 | AK7: =COUNTIFS('ACTIVATED LEADS '!$H:$H,$B7,'ACTIVATED LEADS '!$D:$D,'PARTNERS SUMMARY'!AK$3) -> 0 | AL7: =COUNTIFS('ACTIVATED LEADS '!$H:$H,$B7,'ACTIVATED LEADS '!$D:$D,'PARTNERS SUMMARY'!AL$3) -> 0 | AM7: =COUNTIFS('ACTIVATED LEADS '!$H:$H,$B7,'ACTIVATED LEADS '!$D:$D,'PARTNERS SUMMARY'!AM$3) -> 0 | AN7: =COUNTIFS('ACTIVATED LEADS '!$H:$H,$B7,'ACTIVATED LEADS '!$D:$D,'PARTNERS SUMMARY'!AN$3) -> 0 | AO7: =COUNTIFS('ACTIVATED LEADS '!$H:$H,$B7,'ACTIVATED LEADS '!$D:$D,'PARTNERS SUMMARY'!AO$3) -> 0 | ... DO7: =COUNTIFS('ACTIVATED LEADS '!$H:$H,$B7,'ACTIVATED LEADS '!$D:$D,'PARTNERS SUMMARY'!DO$3) -> 2
A8: Mariana Hongo | B8: RYDEME EAST AFRICA LTD | C8: 788338738 | D8: Kenombette@gmail.com | E8: Kisii | F8: Western | G8: =COUNTIF('SEPT DUMP '!$C:$C,'PARTNERS SUMMARY'!$B8) -> 1 | H8: =COUNTIFS('SEPT DUMP '!$C:$C,'PARTNERS SUMMARY'!$B8,'SEPT DUMP '!$O:$O,"Confirmed") -> 1 | I8: =COUNTIFS('SEPT DUMP '!$C:$C,'PARTNERS SUMMARY'!$B8,'SEPT DUMP '!$O:$O,"Rejected") -> 0 | J8: =COUNTIFS('SEPT DUMP '!$C:$C,'PARTNERS SUMMARY'!$B8,'SEPT DUMP '!$O:$O,"Unreachable") -> 0 | K8: =COUNTIFS('SEPT DUMP '!$C:$C,'PARTNERS SUMMARY'!$B8,'SEPT DUMP '!$O:$O,"Postponed(Update Y)") -> 0 | L8: =SUM(AH8:BK8) -> 1 | M8: =IFERROR(L8/G8,0) -> 1 | O8: =COUNTIF('OCT DUMP'!$D:$D,'PARTNERS SUMMARY'!$B8) -> 7 | P8: =COUNTIFS('OCT DUMP'!$D:$D,'PARTNERS SUMMARY'!$B8,'OCT DUMP'!Q:Q,"Prospect") -> 0 | Q8: =COUNTIFS('OCT DUMP'!$D:$D,'PARTNERS SUMMARY'!$B8,'OCT DUMP'!$Q:$Q,"Confirmed") -> 4 | R8: =COUNTIFS('OCT DUMP'!$D:$D,'PARTNERS SUMMARY'!$B8,'OCT DUMP'!$Q:$Q,"Rejected") -> 3 | S8: =COUNTIFS('OCT DUMP'!$D:$D,'PARTNERS SUMMARY'!$B8,'OCT DUMP'!$Q:$Q,"Unreachable") -> 0 | T8: =COUNTIFS('OCT DUMP'!$D:$D,'PARTNERS SUMMARY'!$B8,'OCT DUMP'!$Q:$Q,"Postponed(Update Y)") -> 0 | U8: =SUM(BL8:CP8) -> 8 | V8: =IFERROR(U8/O8,0) -> 1.1428571 | X8: =COUNTIF('NOV DUMP'!C:C,'PARTNERS SUMMARY'!$B8) -> 18 | Y8: =COUNTIFS('NOV DUMP'!$C:$C,'PARTNERS SUMMARY'!$B8,'NOV DUMP'!$S:$S,"Prospect") -> 0 | Z8: =COUNTIFS('NOV DUMP'!$C:$C,'PARTNERS SUMMARY'!$B8,'NOV DUMP'!$S:$S,"Confirmed") -> 8 | AA8: =COUNTIFS('NOV DUMP'!$C:$C,'PARTNERS SUMMARY'!$B8,'NOV DUMP'!$S:$S,"Rejected") -> 0 | AB8: =COUNTIFS('NOV DUMP'!$C:$C,'PARTNERS SUMMARY'!$B8,'NOV DUMP'!$S:$S,"Unreachable") -> 0 | AC8: =COUNTIFS('NOV DUMP'!$C:$C,'PARTNERS SUMMARY'!$B8,'NOV DUMP'!$S:$S,"Postponed(Update Y)") -> 0 | AD8: =SUM(CQ8:DT8) -> 13 | AE8: =COUNTIFS('ACTIVATED LEADS '!$H:$H,'PARTNERS SUMMARY'!$B8,'ACTIVATED LEADS '!$K:$K,'PARTNERS SUMMARY'!$AE$2,'ACTIVATED LEADS '!$C:$C,"16") -> 13 | AF8: =IFERROR(AD8/X8,0) -> 0.72222222 | AH8: =COUNTIFS('ACTIVATED LEADS '!$H:$H,$B8,'ACTIVATED LEADS '!$D:$D,'PARTNERS SUMMARY'!AH$3) -> 0 | AI8: =COUNTIFS('ACTIVATED LEADS '!$H:$H,$B8,'ACTIVATED LEADS '!$D:$D,'PARTNERS SUMMARY'!AI$3) -> 0 | AJ8: =COUNTIFS('ACTIVATED LEADS '!$H:$H,$B8,'ACTIVATED LEADS '!$D:$D,'PARTNERS SUMMARY'!AJ$3) -> 0 | AK8: =COUNTIFS('ACTIVATED LEADS '!$H:$H,$B8,'ACTIVATED LEADS '!$D:$D,'PARTNERS SUMMARY'!AK$3) -> 0 | AL8: =COUNTIFS('ACTIVATED LEADS '!$H:$H,$B8,'ACTIVATED LEADS '!$D:$D,'PARTNERS SUMMARY'!AL$3) -> 0 | AM8: =COUNTIFS('ACTIVATED LEADS '!$H:$H,$B8,'ACTIVATED LEADS '!$D:$D,'PARTNERS SUMMARY'!AM$3) -> 0 | AN8: =COUNTIFS('ACTIVATED LEADS '!$H:$H,$B8,'ACTIVATED LEADS '!$D:$D,'PARTNERS SUMMARY'!AN$3) -> 0 | AO8: =COUNTIFS('ACTIVATED LEADS '!$H:$H,$B8,'ACTIVATED LEADS '!$D:$D,'PARTNERS SUMMARY'!AO$3) -> 0 | ... DO8: =COUNTIFS('ACTIVATED LEADS '!$H:$H,$B8,'ACTIVATED LEADS '!$D:$D,'PARTNERS SUMMARY'!DO$3) -> 0
A9: Mariana Hongo | B9: DULO INVESTMENTS | C9: 735153617 | D9: Wuodjasega4@gmail.com | E9: Kisumu | F9: Western | G9: =COUNTIF('SEPT DUMP '!$C:$C,'PARTNERS SUMMARY'!$B9) -> 5 | H9: =COUNTIFS('SEPT DUMP '!$C:$C,'PARTNERS SUMMARY'!$B9,'SEPT DUMP '!$O:$O,"Confirmed") -> 4 | I9: =COUNTIFS('SEPT DUMP '!$C:$C,'PARTNERS SUMMARY'!$B9,'SEPT DUMP '!$O:$O,"Rejected") -> 1 | J9: =COUNTIFS('SEPT DUMP '!$C:$C,'PARTNERS SUMMARY'!$B9,'SEPT DUMP '!$O:$O,"Unreachable") -> 0 | K9: =COUNTIFS('SEPT DUMP '!$C:$C,'PARTNERS SUMMARY'!$B9,'SEPT DUMP '!$O:$O,"Postponed(Update Y)") -> 0 | L9: =SUM(AH9:BK9) -> 3 | M9: =IFERROR(L9/G9,0) -> 0.6 | O9: =COUNTIF('OCT DUMP'!$D:$D,'PARTNERS SUMMARY'!$B9) -> 42 | P9: =COUNTIFS('OCT DUMP'!$D:$D,'PARTNERS SUMMARY'!$B9,'OCT DUMP'!Q:Q,"Prospect") -> 0 | Q9: =COUNTIFS('OCT DUMP'!$D:$D,'PARTNERS SUMMARY'!$B9,'OCT DUMP'!$Q:$Q,"Confirmed") -> 29 | R9: =COUNTIFS('OCT DUMP'!$D:$D,'PARTNERS SUMMARY'!$B9,'OCT DUMP'!$Q:$Q,"Rejected") -> 6 | S9: =COUNTIFS('OCT DUMP'!$D:$D,'PARTNERS SUMMARY'!$B9,'OCT DUMP'!$Q:$Q,"Unreachable") -> 7 | T9: =COUNTIFS('OCT DUMP'!$D:$D,'PARTNERS SUMMARY'!$B9,'OCT DUMP'!$Q:$Q,"Postponed(Update Y)") -> 0 | U9: =SUM(BL9:CP9) -> 27 | V9: =IFERROR(U9/O9,0) -> 0.64285714 | X9: =COUNTIF('NOV DUMP'!C:C,'PARTNERS SUMMARY'!$B9) -> 42 | Y9: =COUNTIFS('NOV DUMP'!$C:$C,'PARTNERS SUMMARY'!$B9,'NOV DUMP'!$S:$S,"Prospect") -> 0 | Z9: =COUNTIFS('NOV DUMP'!$C:$C,'PARTNERS SUMMARY'!$B9,'NOV DUMP'!$S:$S,"Confirmed") -> 12 | AA9: =COUNTIFS('NOV DUMP'!$C:$C,'PARTNERS SUMMARY'!$B9,'NOV DUMP'!$S:$S,"Rejected") -> 9 | AB9: =COUNTIFS('NOV DUMP'!$C:$C,'PARTNERS SUMMARY'!$B9,'NOV DUMP'!$S:$S,"Unreachable") -> 2 | AC9: =COUNTIFS('NOV DUMP'!$C:$C,'PARTNERS SUMMARY'!$B9,'NOV DUMP'!$S:$S,"Postponed(Update Y)") -> 0 | AD9: =SUM(CQ9:DT9) -> 20 | AE9: =COUNTIFS('ACTIVATED LEADS '!$H:$H,'PARTNERS SUMMARY'!$B9,'ACTIVATED LEADS '!$K:$K,'PARTNERS SUMMARY'!$AE$2,'ACTIVATED LEADS '!$C:$C,"16") -> 4 | AF9: =IFERROR(AD9/X9,0) -> 0.47619048 | AH9: =COUNTIFS('ACTIVATED LEADS '!$H:$H,$B9,'ACTIVATED LEADS '!$D:$D,'PARTNERS SUMMARY'!AH$3) -> 0 | AI9: =COUNTIFS('ACTIVATED LEADS '!$H:$H,$B9,'ACTIVATED LEADS '!$D:$D,'PARTNERS SUMMARY'!AI$3) -> 0 | AJ9: =COUNTIFS('ACTIVATED LEADS '!$H:$H,$B9,'ACTIVATED LEADS '!$D:$D,'PARTNERS SUMMARY'!AJ$3) -> 0 | AK9: =COUNTIFS('ACTIVATED LEADS '!$H:$H,$B9,'ACTIVATED LEADS '!$D:$D,'PARTNERS SUMMARY'!AK$3) -> 0 | AL9: =COUNTIFS('ACTIVATED LEADS '!$H:$H,$B9,'ACTIVATED LEADS '!$D:$D,'PARTNERS SUMMARY'!AL$3) -> 0 | AM9: =COUNTIFS('ACTIVATED LEADS '!$H:$H,$B9,'ACTIVATED LEADS '!$D:$D,'PARTNERS SUMMARY'!AM$3) -> 0 | AN9: =COUNTIFS('ACTIVATED LEADS '!$H:$H,$B9,'ACTIVATED LEADS '!$D:$D,'PARTNERS SUMMARY'!AN$3) -> 0 | AO9: =COUNTIFS('ACTIVATED LEADS '!$H:$H,$B9,'ACTIVATED LEADS '!$D:$D,'PARTNERS SUMMARY'!AO$3) -> 0 | ... DO9: =COUNTIFS('ACTIVATED LEADS '!$H:$H,$B9,'ACTIVATED LEADS '!$D:$D,'PARTNERS SUMMARY'!DO$3) -> 2
A10: Fiona Maiyo | B10: LUHYA LUO DOLLAR CONNECTION | C10: 100866403 | D10: modizoali@gmail.com | E10: Eldoret | F10: Rift | G10: =COUNTIF('SEPT DUMP '!$C:$C,'PARTNERS SUMMARY'!$B10) -> 0 | H10: =COUNTIFS('SEPT DUMP '!$C:$C,'PARTNERS SUMMARY'!$B10,'SEPT DUMP '!$O:$O,"Confirmed") -> 0 | I10: =COUNTIFS('SEPT DUMP '!$C:$C,'PARTNERS SUMMARY'!$B10,'SEPT DUMP '!$O:$O,"Rejected") -> 0 | J10: =COUNTIFS('SEPT DUMP '!$C:$C,'PARTNERS SUMMARY'!$B10,'SEPT DUMP '!$O:$O,"Unreachable") -> 0 | K10: =COUNTIFS('SEPT DUMP '!$C:$C,'PARTNERS SUMMARY'!$B10,'SEPT DUMP '!$O:$O,"Postponed(Update Y)") -> 0 | L10: =SUM(AH10:BK10) -> 0 | M10: =IFERROR(L10/G10,0) -> 0 | O10: =COUNTIF('OCT DUMP'!$D:$D,'PARTNERS SUMMARY'!$B10) -> 49 | P10: =COUNTIFS('OCT DUMP'!$D:$D,'PARTNERS SUMMARY'!$B10,'OCT DUMP'!Q:Q,"Prospect") -> 0 | Q10: =COUNTIFS('OCT DUMP'!$D:$D,'PARTNERS SUMMARY'!$B10,'OCT DUMP'!$Q:$Q,"Confirmed") -> 37 | R10: =COUNTIFS('OCT DUMP'!$D:$D,'PARTNERS SUMMARY'!$B10,'OCT DUMP'!$Q:$Q,"Rejected") -> 6 | S10: =COUNTIFS('OCT DUMP'!$D:$D,'PARTNERS SUMMARY'!$B10,'OCT DUMP'!$Q:$Q,"Unreachable") -> 6 | T10: =COUNTIFS('OCT DUMP'!$D:$D,'PARTNERS SUMMARY'!$B10,'OCT DUMP'!$Q:$Q,"Postponed(Update Y)") -> 0 | U10: =SUM(BL10:CP10) -> 21 | V10: =IFERROR(U10/O10,0) -> 0.42857143 | X10: =COUNTIF('NOV DUMP'!C:C,'PARTNERS SUMMARY'!$B10) -> 75 | Y10: =COUNTIFS('NOV DUMP'!$C:$C,'PARTNERS SUMMARY'!$B10,'NOV DUMP'!$S:$S,"Prospect") -> 1 | Z10: =COUNTIFS('NOV DUMP'!$C:$C,'PARTNERS SUMMARY'!$B10,'NOV DUMP'!$S:$S,"Confirmed") -> 16 | AA10: =COUNTIFS('NOV DUMP'!$C:$C,'PARTNERS SUMMARY'!$B10,'NOV DUMP'!$S:$S,"Rejected") -> 3 | AB10: =COUNTIFS('NOV DUMP'!$C:$C,'PARTNERS SUMMARY'!$B10,'NOV DUMP'!$S:$S,"Unreachable") -> 0 | AC10: =COUNTIFS('NOV DUMP'!$C:$C,'PARTNERS SUMMARY'!$B10,'NOV DUMP'!$S:$S,"Postponed(Update Y)") -> 0 | AD10: =SUM(CQ10:DT10) -> 47 | AE10: =COUNTIFS('ACTIVATED LEADS '!$H:$H,'PARTNERS SUMMARY'!$B10,'ACTIVATED LEADS '!$K:$K,'PARTNERS SUMMARY'!$AE$2,'ACTIVATED LEADS '!$C:$C,"16") -> 46 | AF10: =IFERROR(AD10/X10,0) -> 0.62666667 | AH10: =COUNTIFS('ACTIVATED LEADS '!$H:$H,$B10,'ACTIVATED LEADS '!$D:$D,'PARTNERS SUMMARY'!AH$3) -> 0 | AI10: =COUNTIFS('ACTIVATED LEADS '!$H:$H,$B10,'ACTIVATED LEADS '!$D:$D,'PARTNERS SUMMARY'!AI$3) -> 0 | AJ10: =COUNTIFS('ACTIVATED LEADS '!$H:$H,$B10,'ACTIVATED LEADS '!$D:$D,'PARTNERS SUMMARY'!AJ$3) -> 0 | AK10: =COUNTIFS('ACTIVATED LEADS '!$H:$H,$B10,'ACTIVATED LEADS '!$D:$D,'PARTNERS SUMMARY'!AK$3) -> 0 | AL10: =COUNTIFS('ACTIVATED LEADS '!$H:$H,$B10,'ACTIVATED LEADS '!$D:$D,'PARTNERS SUMMARY'!AL$3) -> 0 | AM10: =COUNTIFS('ACTIVATED LEADS '!$H:$H,$B10,'ACTIVATED LEADS '!$D:$D,'PARTNERS SUMMARY'!AM$3) -> 0 | AN10: =COUNTIFS('ACTIVATED LEADS '!$H:$H,$B10,'ACTIVATED LEADS '!$D:$D,'PARTNERS SUMMARY'!AN$3) -> 0 | AO10: =COUNTIFS('ACTIVATED LEADS '!$H:$H,$B10,'ACTIVATED LEADS '!$D:$D,'PARTNERS SUMMARY'!AO$3) -> 0 | ... DO10: =COUNTIFS('ACTIVATED LEADS '!$H:$H,$B10,'ACTIVATED LEADS '!$D:$D,'PARTNERS SUMMARY'!DO$3) -> 0
A11: Brian Odero | B11: WEZESHA MTANDAO MASHINANI | C11: 103505274 | D11: everlyn.ameyo@gmail.com | E11: Runda | F11: Nairobi | G11: =COUNTIF('SEPT DUMP '!$C:$C,'PARTNERS SUMMARY'!$B11) -> 0 | H11: =COUNTIFS('SEPT DUMP '!$C:$C,'PARTNERS SUMMARY'!$B11,'SEPT DUMP '!$O:$O,"Confirmed") -> 0 | I11: =COUNTIFS('SEPT DUMP '!$C:$C,'PARTNERS SUMMARY'!$B11,'SEPT DUMP '!$O:$O,"Rejected") -> 0 | J11: =COUNTIFS('SEPT DUMP '!$C:$C,'PARTNERS SUMMARY'!$B11,'SEPT DUMP '!$O:$O,"Unreachable") -> 0 | K11: =COUNTIFS('SEPT DUMP '!$C:$C,'PARTNERS SUMMARY'!$B11,'SEPT DUMP '!$O:$O,"Postponed(Update Y)") -> 0 | L11: =SUM(AH11:BK11) -> 0 | M11: =IFERROR(L11/G11,0) -> 0 | O11: =COUNTIF('OCT DUMP'!$D:$D,'PARTNERS SUMMARY'!$B11) -> 3 | P11: =COUNTIFS('OCT DUMP'!$D:$D,'PARTNERS SUMMARY'!$B11,'OCT DUMP'!Q:Q,"Prospect") -> 0 | Q11: =COUNTIFS('OCT DUMP'!$D:$D,'PARTNERS SUMMARY'!$B11,'OCT DUMP'!$Q:$Q,"Confirmed") -> 2 | R11: =COUNTIFS('OCT DUMP'!$D:$D,'PARTNERS SUMMARY'!$B11,'OCT DUMP'!$Q:$Q,"Rejected") -> 0 | S11: =COUNTIFS('OCT DUMP'!$D:$D,'PARTNERS SUMMARY'!$B11,'OCT DUMP'!$Q:$Q,"Unreachable") -> 1 | T11: =COUNTIFS('OCT DUMP'!$D:$D,'PARTNERS SUMMARY'!$B11,'OCT DUMP'!$Q:$Q,"Postponed(Update Y)") -> 0 | U11: =SUM(BL11:CP11) -> 1 | V11: =IFERROR(U11/O11,0) -> 0.33333333 | X11: =COUNTIF('NOV DUMP'!C:C,'PARTNERS SUMMARY'!$B11) -> 0 | Y11: =COUNTIFS('NOV DUMP'!$C:$C,'PARTNERS SUMMARY'!$B11,'NOV DUMP'!$S:$S,"Prospect") -> 0 | Z11: =COUNTIFS('NOV DUMP'!$C:$C,'PARTNERS SUMMARY'!$B11,'NOV DUMP'!$S:$S,"Confirmed") -> 0 | AA11: =COUNTIFS('NOV DUMP'!$C:$C,'PARTNERS SUMMARY'!$B11,'NOV DUMP'!$S:$S,"Rejected") -> 0 | AB11: =COUNTIFS('NOV DUMP'!$C:$C,'PARTNERS SUMMARY'!$B11,'NOV DUMP'!$S:$S,"Unreachable") -> 0 | AC11: =COUNTIFS('NOV DUMP'!$C:$C,'PARTNERS SUMMARY'!$B11,'NOV DUMP'!$S:$S,"Postponed(Update Y)") -> 0 | AD11: =SUM(CQ11:DT11) -> 0 | AE11: =COUNTIFS('ACTIVATED LEADS '!$H:$H,'PARTNERS SUMMARY'!$B11,'ACTIVATED LEADS '!$K:$K,'PARTNERS SUMMARY'!$AE$2,'ACTIVATED LEADS '!$C:$C,"16") -> 0 | AF11: =IFERROR(AD11/X11,0) -> 0 | AH11: =COUNTIFS('ACTIVATED LEADS '!$H:$H,$B11,'ACTIVATED LEADS '!$D:$D,'PARTNERS SUMMARY'!AH$3) -> 0 | AI11: =COUNTIFS('ACTIVATED LEADS '!$H:$H,$B11,'ACTIVATED LEADS '!$D:$D,'PARTNERS SUMMARY'!AI$3) -> 0 | AJ11: =COUNTIFS('ACTIVATED LEADS '!$H:$H,$B11,'ACTIVATED LEADS '!$D:$D,'PARTNERS SUMMARY'!AJ$3) -> 0 | AK11: =COUNTIFS('ACTIVATED LEADS '!$H:$H,$B11,'ACTIVATED LEADS '!$D:$D,'PARTNERS SUMMARY'!AK$3) -> 0 | AL11: =COUNTIFS('ACTIVATED LEADS '!$H:$H,$B11,'ACTIVATED LEADS '!$D:$D,'PARTNERS SUMMARY'!AL$3) -> 0 | AM11: =COUNTIFS('ACTIVATED LEADS '!$H:$H,$B11,'ACTIVATED LEADS '!$D:$D,'PARTNERS SUMMARY'!AM$3) -> 0 | AN11: =COUNTIFS('ACTIVATED LEADS '!$H:$H,$B11,'ACTIVATED LEADS '!$D:$D,'PARTNERS SUMMARY'!AN$3) -> 0 | AO11: =COUNTIFS('ACTIVATED LEADS '!$H:$H,$B11,'ACTIVATED LEADS '!$D:$D,'PARTNERS SUMMARY'!AO$3) -> 0 | ... DO11: =COUNTIFS('ACTIVATED LEADS '!$H:$H,$B11,'ACTIVATED LEADS '!$D:$D,'PARTNERS SUMMARY'!DO$3) -> 0
A12: Brian Odero | B12: MANYA FIRM | C12: 108499681 | D12: Pishmouti@gmail.com | E12: Mulolongo | F12: Nairobi | G12: =COUNTIF('SEPT DUMP '!$C:$C,'PARTNERS SUMMARY'!$B12) -> 0 | H12: =COUNTIFS('SEPT DUMP '!$C:$C,'PARTNERS SUMMARY'!$B12,'SEPT DUMP '!$O:$O,"Confirmed") -> 0 | I12: =COUNTIFS('SEPT DUMP '!$C:$C,'PARTNERS SUMMARY'!$B12,'SEPT DUMP '!$O:$O,"Rejected") -> 0 | J12: =COUNTIFS('SEPT DUMP '!$C:$C,'PARTNERS SUMMARY'!$B12,'SEPT DUMP '!$O:$O,"Unreachable") -> 0 | K12: =COUNTIFS('SEPT DUMP '!$C:$C,'PARTNERS SUMMARY'!$B12,'SEPT DUMP '!$O:$O,"Postponed(Update Y)") -> 0 | L12: =SUM(AH12:BK12) -> 0 | M12: =IFERROR(L12/G12,0) -> 0 | O12: =COUNTIF('OCT DUMP'!$D:$D,'PARTNERS SUMMARY'!$B12) -> 7 | P12: =COUNTIFS('OCT DUMP'!$D:$D,'PARTNERS SUMMARY'!$B12,'OCT DUMP'!Q:Q,"Prospect") -> 0 | Q12: =COUNTIFS('OCT DUMP'!$D:$D,'PARTNERS SUMMARY'!$B12,'OCT DUMP'!$Q:$Q,"Confirmed") -> 5 | R12: =COUNTIFS('OCT DUMP'!$D:$D,'PARTNERS SUMMARY'!$B12,'OCT DUMP'!$Q:$Q,"Rejected") -> 1 | S12: =COUNTIFS('OCT DUMP'!$D:$D,'PARTNERS SUMMARY'!$B12,'OCT DUMP'!$Q:$Q,"Unreachable") -> 1 | T12: =COUNTIFS('OCT DUMP'!$D:$D,'PARTNERS SUMMARY'!$B12,'OCT DUMP'!$Q:$Q,"Postponed(Update Y)") -> 0 | U12: =SUM(BL12:CP12) -> 2 | V12: =IFERROR(U12/O12,0) -> 0.28571429 | X12: =COUNTIF('NOV DUMP'!C:C,'PARTNERS SUMMARY'!$B12) -> 2 | Y12: =COUNTIFS('NOV DUMP'!$C:$C,'PARTNERS SUMMARY'!$B12,'NOV DUMP'!$S:$S,"Prospect") -> 0 | Z12: =COUNTIFS('NOV DUMP'!$C:$C,'PARTNERS SUMMARY'!$B12,'NOV DUMP'!$S:$S,"Confirmed") -> 1 | AA12: =COUNTIFS('NOV DUMP'!$C:$C,'PARTNERS SUMMARY'!$B12,'NOV DUMP'!$S:$S,"Rejected") -> 0 | AB12: =COUNTIFS('NOV DUMP'!$C:$C,'PARTNERS SUMMARY'!$B12,'NOV DUMP'!$S:$S,"Unreachable") -> 0 | AC12: =COUNTIFS('NOV DUMP'!$C:$C,'PARTNERS SUMMARY'!$B12,'NOV DUMP'!$S:$S,"Postponed(Update Y)") -> 0 | AD12: =SUM(CQ12:DT12) -> 1 | AE12: =COUNTIFS('ACTIVATED LEADS '!$H:$H,'PARTNERS SUMMARY'!$B12,'ACTIVATED LEADS '!$K:$K,'PARTNERS SUMMARY'!$AE$2,'ACTIVATED LEADS '!$C:$C,"16") -> 1 | AF12: =IFERROR(AD12/X12,0) -> 0.5 | AH12: =COUNTIFS('ACTIVATED LEADS '!$H:$H,$B12,'ACTIVATED LEADS '!$D:$D,'PARTNERS SUMMARY'!AH$3) -> 0 | AI12: =COUNTIFS('ACTIVATED LEADS '!$H:$H,$B12,'ACTIVATED LEADS '!$D:$D,'PARTNERS SUMMARY'!AI$3) -> 0 | AJ12: =COUNTIFS('ACTIVATED LEADS '!$H:$H,$B12,'ACTIVATED LEADS '!$D:$D,'PARTNERS SUMMARY'!AJ$3) -> 0 | AK12: =COUNTIFS('ACTIVATED LEADS '!$H:$H,$B12,'ACTIVATED LEADS '!$D:$D,'PARTNERS SUMMARY'!AK$3) -> 0 | AL12: =COUNTIFS('ACTIVATED LEADS '!$H:$H,$B12,'ACTIVATED LEADS '!$D:$D,'PARTNERS SUMMARY'!AL$3) -> 0 | AM12: =COUNTIFS('ACTIVATED LEADS '!$H:$H,$B12,'ACTIVATED LEADS '!$D:$D,'PARTNERS SUMMARY'!AM$3) -> 0 | AN12: =COUNTIFS('ACTIVATED LEADS '!$H:$H,$B12,'ACTIVATED LEADS '!$D:$D,'PARTNERS SUMMARY'!AN$3) -> 0 | AO12: =COUNTIFS('ACTIVATED LEADS '!$H:$H,$B12,'ACTIVATED LEADS '!$D:$D,'PARTNERS SUMMARY'!AO$3) -> 0 | ... DO12: =COUNTIFS('ACTIVATED LEADS '!$H:$H,$B12,'ACTIVATED LEADS '!$D:$D,'PARTNERS SUMMARY'!DO$3) -> 0
A13: Damaris Mainga | B13: SALAMA COMMUNICATIONS LIMITED | C13: 782036662 | D13: Nyumujacinta@gmail.com | E13: Machakos | F13: Nairobi | G13: =COUNTIF('SEPT DUMP '!$C:$C,'PARTNERS SUMMARY'!$B13) -> 0 | H13: =COUNTIFS('SEPT DUMP '!$C:$C,'PARTNERS SUMMARY'!$B13,'SEPT DUMP '!$O:$O,"Confirmed") -> 0 | I13: =COUNTIFS('SEPT DUMP '!$C:$C,'PARTNERS SUMMARY'!$B13,'SEPT DUMP '!$O:$O,"Rejected") -> 0 | J13: =COUNTIFS('SEPT DUMP '!$C:$C,'PARTNERS SUMMARY'!$B13,'SEPT DUMP '!$O:$O,"Unreachable") -> 0 | K13: =COUNTIFS('SEPT DUMP '!$C:$C,'PARTNERS SUMMARY'!$B13,'SEPT DUMP '!$O:$O,"Postponed(Update Y)") -> 0 | L13: =SUM(AH13:BK13) -> 0 | M13: =IFERROR(L13/G13,0) -> 0 | O13: =COUNTIF('OCT DUMP'!$D:$D,'PARTNERS SUMMARY'!$B13) -> 13 | P13: =COUNTIFS('OCT DUMP'!$D:$D,'PARTNERS SUMMARY'!$B13,'OCT DUMP'!Q:Q,"Prospect") -> 0 | Q13: =COUNTIFS('OCT DUMP'!$D:$D,'PARTNERS SUMMARY'!$B13,'OCT DUMP'!$Q:$Q,"Confirmed") -> 5 | R13: =COUNTIFS('OCT DUMP'!$D:$D,'PARTNERS SUMMARY'!$B13,'OCT DUMP'!$Q:$Q,"Rejected") -> 6 | S13: =COUNTIFS('OCT DUMP'!$D:$D,'PARTNERS SUMMARY'!$B13,'OCT DUMP'!$Q:$Q,"Unreachable") -> 2 | T13: =COUNTIFS('OCT DUMP'!$D:$D,'PARTNERS SUMMARY'!$B13,'OCT DUMP'!$Q:$Q,"Postponed(Update Y)") -> 0 | U13: =SUM(BL13:CP13) -> 5 | V13: =IFERROR(U13/O13,0) -> 0.38461538 | X13: =COUNTIF('NOV DUMP'!C:C,'PARTNERS SUMMARY'!$B13) -> 29 | Y13: =COUNTIFS('NOV DUMP'!$C:$C,'PARTNERS SUMMARY'!$B13,'NOV DUMP'!$S:$S,"Prospect") -> 1 | Z13: =COUNTIFS('NOV DUMP'!$C:$C,'PARTNERS SUMMARY'!$B13,'NOV DUMP'!$S:$S,"Confirmed") -> 2 | AA13: =COUNTIFS('NOV DUMP'!$C:$C,'PARTNERS SUMMARY'!$B13,'NOV DUMP'!$S:$S,"Rejected") -> 1 | AB13: =COUNTIFS('NOV DUMP'!$C:$C,'PARTNERS SUMMARY'!$B13,'NOV DUMP'!$S:$S,"Unreachable") -> 0 | AC13: =COUNTIFS('NOV DUMP'!$C:$C,'PARTNERS SUMMARY'!$B13,'NOV DUMP'!$S:$S,"Postponed(Update Y)") -> 0 | AD13: =SUM(CQ13:DT13) -> 9 | AE13: =COUNTIFS('ACTIVATED LEADS '!$H:$H,'PARTNERS SUMMARY'!$B13,'ACTIVATED LEADS '!$K:$K,'PARTNERS SUMMARY'!$AE$2,'ACTIVATED LEADS '!$C:$C,"16") -> 7 | AF13: =IFERROR(AD13/X13,0) -> 0.31034483 | AH13: =COUNTIFS('ACTIVATED LEADS '!$H:$H,$B13,'ACTIVATED LEADS '!$D:$D,'PARTNERS SUMMARY'!AH$3) -> 0 | AI13: =COUNTIFS('ACTIVATED LEADS '!$H:$H,$B13,'ACTIVATED LEADS '!$D:$D,'PARTNERS SUMMARY'!AI$3) -> 0 | AJ13: =COUNTIFS('ACTIVATED LEADS '!$H:$H,$B13,'ACTIVATED LEADS '!$D:$D,'PARTNERS SUMMARY'!AJ$3) -> 0 | AK13: =COUNTIFS('ACTIVATED LEADS '!$H:$H,$B13,'ACTIVATED LEADS '!$D:$D,'PARTNERS SUMMARY'!AK$3) -> 0 | AL13: =COUNTIFS('ACTIVATED LEADS '!$H:$H,$B13,'ACTIVATED LEADS '!$D:$D,'PARTNERS SUMMARY'!AL$3) -> 0 | AM13: =COUNTIFS('ACTIVATED LEADS '!$H:$H,$B13,'ACTIVATED LEADS '!$D:$D,'PARTNERS SUMMARY'!AM$3) -> 0 | AN13: =COUNTIFS('ACTIVATED LEADS '!$H:$H,$B13,'ACTIVATED LEADS '!$D:$D,'PARTNERS SUMMARY'!AN$3) -> 0 | AO13: =COUNTIFS('ACTIVATED LEADS '!$H:$H,$B13,'ACTIVATED LEADS '!$D:$D,'PARTNERS SUMMARY'!AO$3) -> 0 | ... DO13: =COUNTIFS('ACTIVATED LEADS '!$H:$H,$B13,'ACTIVATED LEADS '!$D:$D,'PARTNERS SUMMARY'!DO$3) -> 1
A14: Damaris Mainga | B14: AIRTIME TRADERS LIMITED | C14: 103339563 | D14: Codhiambo386@gmail.com | E14: NAIROBI TOWN | F14: Nairobi | G14: =COUNTIF('SEPT DUMP '!$C:$C,'PARTNERS SUMMARY'!$B14) -> 1 | H14: =COUNTIFS('SEPT DUMP '!$C:$C,'PARTNERS SUMMARY'!$B14,'SEPT DUMP '!$O:$O,"Confirmed") -> 0 | I14: =COUNTIFS('SEPT DUMP '!$C:$C,'PARTNERS SUMMARY'!$B14,'SEPT DUMP '!$O:$O,"Rejected") -> 0 | J14: =COUNTIFS('SEPT DUMP '!$C:$C,'PARTNERS SUMMARY'!$B14,'SEPT DUMP '!$O:$O,"Unreachable") -> 0 | K14: =COUNTIFS('SEPT DUMP '!$C:$C,'PARTNERS SUMMARY'!$B14,'SEPT DUMP '!$O:$O,"Postponed(Update Y)") -> 1 | L14: =SUM(AH14:BK14) -> 0 | M14: =IFERROR(L14/G14,0) -> 0 | O14: =COUNTIF('OCT DUMP'!$D:$D,'PARTNERS SUMMARY'!$B14) -> 15 | P14: =COUNTIFS('OCT DUMP'!$D:$D,'PARTNERS SUMMARY'!$B14,'OCT DUMP'!Q:Q,"Prospect") -> 3 | Q14: =COUNTIFS('OCT DUMP'!$D:$D,'PARTNERS SUMMARY'!$B14,'OCT DUMP'!$Q:$Q,"Confirmed") -> 7 | R14: =COUNTIFS('OCT DUMP'!$D:$D,'PARTNERS SUMMARY'!$B14,'OCT DUMP'!$Q:$Q,"Rejected") -> 3 | S14: =COUNTIFS('OCT DUMP'!$D:$D,'PARTNERS SUMMARY'!$B14,'OCT DUMP'!$Q:$Q,"Unreachable") -> 2 | T14: =COUNTIFS('OCT DUMP'!$D:$D,'PARTNERS SUMMARY'!$B14,'OCT DUMP'!$Q:$Q,"Postponed(Update Y)") -> 0 | U14: =SUM(BL14:CP14) -> 1 | V14: =IFERROR(U14/O14,0) -> 0.066666667 | X14: =COUNTIF('NOV DUMP'!C:C,'PARTNERS SUMMARY'!$B14) -> 37 | Y14: =COUNTIFS('NOV DUMP'!$C:$C,'PARTNERS SUMMARY'!$B14,'NOV DUMP'!$S:$S,"Prospect") -> 0 | Z14: =COUNTIFS('NOV DUMP'!$C:$C,'PARTNERS SUMMARY'!$B14,'NOV DUMP'!$S:$S,"Confirmed") -> 14 | AA14: =COUNTIFS('NOV DUMP'!$C:$C,'PARTNERS SUMMARY'!$B14,'NOV DUMP'!$S:$S,"Rejected") -> 1 | AB14: =COUNTIFS('NOV DUMP'!$C:$C,'PARTNERS SUMMARY'!$B14,'NOV DUMP'!$S:$S,"Unreachable") -> 0 | AC14: =COUNTIFS('NOV DUMP'!$C:$C,'PARTNERS SUMMARY'!$B14,'NOV DUMP'!$S:$S,"Postponed(Update Y)") -> 0 | AD14: =SUM(CQ14:DT14) -> 10 | AE14: =COUNTIFS('ACTIVATED LEADS '!$H:$H,'PARTNERS SUMMARY'!$B14,'ACTIVATED LEADS '!$K:$K,'PARTNERS SUMMARY'!$AE$2,'ACTIVATED LEADS '!$C:$C,"16") -> 10 | AF14: =IFERROR(AD14/X14,0) -> 0.27027027 | AH14: =COUNTIFS('ACTIVATED LEADS '!$H:$H,$B14,'ACTIVATED LEADS '!$D:$D,'PARTNERS SUMMARY'!AH$3) -> 0 | AI14: =COUNTIFS('ACTIVATED LEADS '!$H:$H,$B14,'ACTIVATED LEADS '!$D:$D,'PARTNERS SUMMARY'!AI$3) -> 0 | AJ14: =COUNTIFS('ACTIVATED LEADS '!$H:$H,$B14,'ACTIVATED LEADS '!$D:$D,'PARTNERS SUMMARY'!AJ$3) -> 0 | AK14: =COUNTIFS('ACTIVATED LEADS '!$H:$H,$B14,'ACTIVATED LEADS '!$D:$D,'PARTNERS SUMMARY'!AK$3) -> 0 | AL14: =COUNTIFS('ACTIVATED LEADS '!$H:$H,$B14,'ACTIVATED LEADS '!$D:$D,'PARTNERS SUMMARY'!AL$3) -> 0 | AM14: =COUNTIFS('ACTIVATED LEADS '!$H:$H,$B14,'ACTIVATED LEADS '!$D:$D,'PARTNERS SUMMARY'!AM$3) -> 0 | AN14: =COUNTIFS('ACTIVATED LEADS '!$H:$H,$B14,'ACTIVATED LEADS '!$D:$D,'PARTNERS SUMMARY'!AN$3) -> 0 | AO14: =COUNTIFS('ACTIVATED LEADS '!$H:$H,$B14,'ACTIVATED LEADS '!$D:$D,'PARTNERS SUMMARY'!AO$3) -> 0 | ... DO14: =COUNTIFS('ACTIVATED LEADS '!$H:$H,$B14,'ACTIVATED LEADS '!$D:$D,'PARTNERS SUMMARY'!DO$3) -> 0
A15: Brian Odero | B15: HIDAWEY ENTERPRISE LIMITED | C15: 729062128 | D15: iomach54@gmail.com | E15: Nairobi CBD | F15: Nairobi | G15: =COUNTIF('SEPT DUMP '!$C:$C,'PARTNERS SUMMARY'!$B15) -> 0 | H15: =COUNTIFS('SEPT DUMP '!$C:$C,'PARTNERS SUMMARY'!$B15,'SEPT DUMP '!$O:$O,"Confirmed") -> 0 | I15: =COUNTIFS('SEPT DUMP '!$C:$C,'PARTNERS SUMMARY'!$B15,'SEPT DUMP '!$O:$O,"Rejected") -> 0 | J15: =COUNTIFS('SEPT DUMP '!$C:$C,'PARTNERS SUMMARY'!$B15,'SEPT DUMP '!$O:$O,"Unreachable") -> 0 | K15: =COUNTIFS('SEPT DUMP '!$C:$C,'PARTNERS SUMMARY'!$B15,'SEPT DUMP '!$O:$O,"Postponed(Update Y)") -> 0 | L15: =SUM(AH15:BK15) -> 0 | M15: =IFERROR(L15/G15,0) -> 0 | O15: =COUNTIF('OCT DUMP'!$D:$D,'PARTNERS SUMMARY'!$B15) -> 3 | P15: =COUNTIFS('OCT DUMP'!$D:$D,'PARTNERS SUMMARY'!$B15,'OCT DUMP'!Q:Q,"Prospect") -> 0 | Q15: =COUNTIFS('OCT DUMP'!$D:$D,'PARTNERS SUMMARY'!$B15,'OCT DUMP'!$Q:$Q,"Confirmed") -> 1 | R15: =COUNTIFS('OCT DUMP'!$D:$D,'PARTNERS SUMMARY'!$B15,'OCT DUMP'!$Q:$Q,"Rejected") -> 2 | S15: =COUNTIFS('OCT DUMP'!$D:$D,'PARTNERS SUMMARY'!$B15,'OCT DUMP'!$Q:$Q,"Unreachable") -> 0 | T15: =COUNTIFS('OCT DUMP'!$D:$D,'PARTNERS SUMMARY'!$B15,'OCT DUMP'!$Q:$Q,"Postponed(Update Y)") -> 0 | U15: =SUM(BL15:CP15) -> 0 | V15: =IFERROR(U15/O15,0) -> 0 | X15: =COUNTIF('NOV DUMP'!C:C,'PARTNERS SUMMARY'!$B15) -> 0 | Y15: =COUNTIFS('NOV DUMP'!$C:$C,'PARTNERS SUMMARY'!$B15,'NOV DUMP'!$S:$S,"Prospect") -> 0 | Z15: =COUNTIFS('NOV DUMP'!$C:$C,'PARTNERS SUMMARY'!$B15,'NOV DUMP'!$S:$S,"Confirmed") -> 0 | AA15: =COUNTIFS('NOV DUMP'!$C:$C,'PARTNERS SUMMARY'!$B15,'NOV DUMP'!$S:$S,"Rejected") -> 0 | AB15: =COUNTIFS('NOV DUMP'!$C:$C,'PARTNERS SUMMARY'!$B15,'NOV DUMP'!$S:$S,"Unreachable") -> 0 | AC15: =COUNTIFS('NOV DUMP'!$C:$C,'PARTNERS SUMMARY'!$B15,'NOV DUMP'!$S:$S,"Postponed(Update Y)") -> 0 | AD15: =SUM(CQ15:DT15) -> 1 | AE15: =COUNTIFS('ACTIVATED LEADS '!$H:$H,'PARTNERS SUMMARY'!$B15,'ACTIVATED LEADS '!$K:$K,'PARTNERS SUMMARY'!$AE$2,'ACTIVATED LEADS '!$C:$C,"16") -> 1 | AF15: =IFERROR(AD15/X15,0) -> 0 | AH15: =COUNTIFS('ACTIVATED LEADS '!$H:$H,$B15,'ACTIVATED LEADS '!$D:$D,'PARTNERS SUMMARY'!AH$3) -> 0 | AI15: =COUNTIFS('ACTIVATED LEADS '!$H:$H,$B15,'ACTIVATED LEADS '!$D:$D,'PARTNERS SUMMARY'!AI$3) -> 0 | AJ15: =COUNTIFS('ACTIVATED LEADS '!$H:$H,$B15,'ACTIVATED LEADS '!$D:$D,'PARTNERS SUMMARY'!AJ$3) -> 0 | AK15: =COUNTIFS('ACTIVATED LEADS '!$H:$H,$B15,'ACTIVATED LEADS '!$D:$D,'PARTNERS SUMMARY'!AK$3) -> 0 | AL15: =COUNTIFS('ACTIVATED LEADS '!$H:$H,$B15,'ACTIVATED LEADS '!$D:$D,'PARTNERS SUMMARY'!AL$3) -> 0 | AM15: =COUNTIFS('ACTIVATED LEADS '!$H:$H,$B15,'ACTIVATED LEADS '!$D:$D,'PARTNERS SUMMARY'!AM$3) -> 0 | AN15: =COUNTIFS('ACTIVATED LEADS '!$H:$H,$B15,'ACTIVATED LEADS '!$D:$D,'PARTNERS SUMMARY'!AN$3) -> 0 | AO15: =COUNTIFS('ACTIVATED LEADS '!$H:$H,$B15,'ACTIVATED LEADS '!$D:$D,'PARTNERS SUMMARY'!AO$3) -> 0 | ... DO15: =COUNTIFS('ACTIVATED LEADS '!$H:$H,$B15,'ACTIVATED LEADS '!$D:$D,'PARTNERS SUMMARY'!DO$3) -> 0
... A17: Damaris Mainga | B17: M NET TECHNOLOGIES | C17: 731396245 | D17: damanja12@gmail.com | E17: Gumba | F17: Nairobi | G17: =COUNTIF('SEPT DUMP '!$C:$C,'PARTNERS SUMMARY'!$B17) -> 0 | H17: =COUNTIFS('SEPT DUMP '!$C:$C,'PARTNERS SUMMARY'!$B17,'SEPT DUMP '!$O:$O,"Confirmed") -> 0 | I17: =COUNTIFS('SEPT DUMP '!$C:$C,'PARTNERS SUMMARY'!$B17,'SEPT DUMP '!$O:$O,"Rejected") -> 0 | J17: =COUNTIFS('SEPT DUMP '!$C:$C,'PARTNERS SUMMARY'!$B17,'SEPT DUMP '!$O:$O,"Unreachable") -> 0 | K17: =COUNTIFS('SEPT DUMP '!$C:$C,'PARTNERS SUMMARY'!$B17,'SEPT DUMP '!$O:$O,"Postponed(Update Y)") -> 0 | L17: =SUM(AH17:BK17) -> 0 | M17: =IFERROR(L17/G17,0) -> 0 | O17: =COUNTIF('OCT DUMP'!$D:$D,'PARTNERS SUMMARY'!$B17) -> 12 | P17: =COUNTIFS('OCT DUMP'!$D:$D,'PARTNERS SUMMARY'!$B17,'OCT DUMP'!Q:Q,"Prospect") -> 1 | Q17: =COUNTIFS('OCT DUMP'!$D:$D,'PARTNERS SUMMARY'!$B17,'OCT DUMP'!$Q:$Q,"Confirmed") -> 7 | R17: =COUNTIFS('OCT DUMP'!$D:$D,'PARTNERS SUMMARY'!$B17,'OCT DUMP'!$Q:$Q,"Rejected") -> 3 | S17: =COUNTIFS('OCT DUMP'!$D:$D,'PARTNERS SUMMARY'!$B17,'OCT DUMP'!$Q:$Q,"Unreachable") -> 0 | T17: =COUNTIFS('OCT DUMP'!$D:$D,'PARTNERS SUMMARY'!$B17,'OCT DUMP'!$Q:$Q,"Postponed(Update Y)") -> 1 | U17: =SUM(BL17:CP17) -> 0 | V17: =IFERROR(U17/O17,0) -> 0 | X17: =COUNTIF('NOV DUMP'!C:C,'PARTNERS SUMMARY'!$B17) -> 7 | Y17: =COUNTIFS('NOV DUMP'!$C:$C,'PARTNERS SUMMARY'!$B17,'NOV DUMP'!$S:$S,"Prospect") -> 0 | Z17: =COUNTIFS('NOV DUMP'!$C:$C,'PARTNERS SUMMARY'!$B17,'NOV DUMP'!$S:$S,"Confirmed") -> 1 | AA17: =COUNTIFS('NOV DUMP'!$C:$C,'PARTNERS SUMMARY'!$B17,'NOV DUMP'!$S:$S,"Rejected") -> 1 | AB17: =COUNTIFS('NOV DUMP'!$C:$C,'PARTNERS SUMMARY'!$B17,'NOV DUMP'!$S:$S,"Unreachable") -> 0 | AC17: =COUNTIFS('NOV DUMP'!$C:$C,'PARTNERS SUMMARY'!$B17,'NOV DUMP'!$S:$S,"Postponed(Update Y)") -> 0 | AD17: =SUM(CQ17:DT17) -> 1 | AE17: =COUNTIFS('ACTIVATED LEADS '!$H:$H,'PARTNERS SUMMARY'!$B17,'ACTIVATED LEADS '!$K:$K,'PARTNERS SUMMARY'!$AE$2,'ACTIVATED LEADS '!$C:$C,"16") -> 0 | AF17: =IFERROR(AD17/X17,0) -> 0.14285714 | AH17: =COUNTIFS('ACTIVATED LEADS '!$H:$H,$B17,'ACTIVATED LEADS '!$D:$D,'PARTNERS SUMMARY'!AH$3) -> 0 | AI17: =COUNTIFS('ACTIVATED LEADS '!$H:$H,$B17,'ACTIVATED LEADS '!$D:$D,'PARTNERS SUMMARY'!AI$3) -> 0 | AJ17: =COUNTIFS('ACTIVATED LEADS '!$H:$H,$B17,'ACTIVATED LEADS '!$D:$D,'PARTNERS SUMMARY'!AJ$3) -> 0 | AK17: =COUNTIFS('ACTIVATED LEADS '!$H:$H,$B17,'ACTIVATED LEADS '!$D:$D,'PARTNERS SUMMARY'!AK$3) -> 0 | AL17: =COUNTIFS('ACTIVATED LEADS '!$H:$H,$B17,'ACTIVATED LEADS '!$D:$D,'PARTNERS SUMMARY'!AL$3) -> 0 | AM17: =COUNTIFS('ACTIVATED LEADS '!$H:$H,$B17,'ACTIVATED LEADS '!$D:$D,'PARTNERS SUMMARY'!AM$3) -> 0 | AN17: =COUNTIFS('ACTIVATED LEADS '!$H:$H,$B17,'ACTIVATED LEADS '!$D:$D,'PARTNERS SUMMARY'!AN$3) -> 0 | AO17: =COUNTIFS('ACTIVATED LEADS '!$H:$H,$B17,'ACTIVATED LEADS '!$D:$D,'PARTNERS SUMMARY'!AO$3) -> 0 | ... DO17: =COUNTIFS('ACTIVATED LEADS '!$H:$H,$B17,'ACTIVATED LEADS '!$D:$D,'PARTNERS SUMMARY'!DO$3) -> 0
A18: Brian Odero | B18: TORESCOE LIMITED | C18: 733262252 | D18: info@torescoe.com | F18: Nairobi | G18: =COUNTIF('SEPT DUMP '!$C:$C,'PARTNERS SUMMARY'!$B18) -> 0 | H18: =COUNTIFS('SEPT DUMP '!$C:$C,'PARTNERS SUMMARY'!$B18,'SEPT DUMP '!$O:$O,"Confirmed") -> 0 | I18: =COUNTIFS('SEPT DUMP '!$C:$C,'PARTNERS SUMMARY'!$B18,'SEPT DUMP '!$O:$O,"Rejected") -> 0 | J18: =COUNTIFS('SEPT DUMP '!$C:$C,'PARTNERS SUMMARY'!$B18,'SEPT DUMP '!$O:$O,"Unreachable") -> 0 | K18: =COUNTIFS('SEPT DUMP '!$C:$C,'PARTNERS SUMMARY'!$B18,'SEPT DUMP '!$O:$O,"Postponed(Update Y)") -> 0 | L18: =SUM(AH18:BK18) -> 0 | M18: =IFERROR(L18/G18,0) -> 0 | O18: =COUNTIF('OCT DUMP'!$D:$D,'PARTNERS SUMMARY'!$B18) -> 2 | P18: =COUNTIFS('OCT DUMP'!$D:$D,'PARTNERS SUMMARY'!$B18,'OCT DUMP'!Q:Q,"Prospect") -> 0 | Q18: =COUNTIFS('OCT DUMP'!$D:$D,'PARTNERS SUMMARY'!$B18,'OCT DUMP'!$Q:$Q,"Confirmed") -> 0 | R18: =COUNTIFS('OCT DUMP'!$D:$D,'PARTNERS SUMMARY'!$B18,'OCT DUMP'!$Q:$Q,"Rejected") -> 0 | S18: =COUNTIFS('OCT DUMP'!$D:$D,'PARTNERS SUMMARY'!$B18,'OCT DUMP'!$Q:$Q,"Unreachable") -> 2 | T18: =COUNTIFS('OCT DUMP'!$D:$D,'PARTNERS SUMMARY'!$B18,'OCT DUMP'!$Q:$Q,"Postponed(Update Y)") -> 0 | U18: =SUM(BL18:CP18) -> 0 | V18: =IFERROR(U18/O18,0) -> 0 | X18: =COUNTIF('NOV DUMP'!C:C,'PARTNERS SUMMARY'!$B18) -> 1 | Y18: =COUNTIFS('NOV DUMP'!$C:$C,'PARTNERS SUMMARY'!$B18,'NOV DUMP'!$S:$S,"Prospect") -> 0 | Z18: =COUNTIFS('NOV DUMP'!$C:$C,'PARTNERS SUMMARY'!$B18,'NOV DUMP'!$S:$S,"Confirmed") -> 0 | AA18: =COUNTIFS('NOV DUMP'!$C:$C,'PARTNERS SUMMARY'!$B18,'NOV DUMP'!$S:$S,"Rejected") -> 0 | AB18: =COUNTIFS('NOV DUMP'!$C:$C,'PARTNERS SUMMARY'!$B18,'NOV DUMP'!$S:$S,"Unreachable") -> 0 | AC18: =COUNTIFS('NOV DUMP'!$C:$C,'PARTNERS SUMMARY'!$B18,'NOV DUMP'!$S:$S,"Postponed(Update Y)") -> 0 | AD18: =SUM(CQ18:DT18) -> 1 | AE18: =COUNTIFS('ACTIVATED LEADS '!$H:$H,'PARTNERS SUMMARY'!$B18,'ACTIVATED LEADS '!$K:$K,'PARTNERS SUMMARY'!$AE$2,'ACTIVATED LEADS '!$C:$C,"16") -> 1 | AF18: =IFERROR(AD18/X18,0) -> 1 | AH18: =COUNTIFS('ACTIVATED LEADS '!$H:$H,$B18,'ACTIVATED LEADS '!$D:$D,'PARTNERS SUMMARY'!AH$3) -> 0 | AI18: =COUNTIFS('ACTIVATED LEADS '!$H:$H,$B18,'ACTIVATED LEADS '!$D:$D,'PARTNERS SUMMARY'!AI$3) -> 0 | AJ18: =COUNTIFS('ACTIVATED LEADS '!$H:$H,$B18,'ACTIVATED LEADS '!$D:$D,'PARTNERS SUMMARY'!AJ$3) -> 0 | AK18: =COUNTIFS('ACTIVATED LEADS '!$H:$H,$B18,'ACTIVATED LEADS '!$D:$D,'PARTNERS SUMMARY'!AK$3) -> 0 | AL18: =COUNTIFS('ACTIVATED LEADS '!$H:$H,$B18,'ACTIVATED LEADS '!$D:$D,'PARTNERS SUMMARY'!AL$3) -> 0 | AM18: =COUNTIFS('ACTIVATED LEADS '!$H:$H,$B18,'ACTIVATED LEADS '!$D:$D,'PARTNERS SUMMARY'!AM$3) -> 0 | AN18: =COUNTIFS('ACTIVATED LEADS '!$H:$H,$B18,'ACTIVATED LEADS '!$D:$D,'PARTNERS SUMMARY'!AN$3) -> 0 | AO18: =COUNTIFS('ACTIVATED LEADS '!$H:$H,$B18,'ACTIVATED LEADS '!$D:$D,'PARTNERS SUMMARY'!AO$3) -> 0 | ... DO18: =COUNTIFS('ACTIVATED LEADS '!$H:$H,$B18,'ACTIVATED LEADS '!$D:$D,'PARTNERS SUMMARY'!DO$3) -> 0
A19: Betreace Chebet | B19: KACHO INVESTMENT | C19: 738748828 | D19: kachoinvestment@gmail.com | E19: Nakuru Town | F19: Rift | G19: =COUNTIF('SEPT DUMP '!$C:$C,'PARTNERS SUMMARY'!$B19) -> 0 | H19: =COUNTIFS('SEPT DUMP '!$C:$C,'PARTNERS SUMMARY'!$B19,'SEPT DUMP '!$O:$O,"Confirmed") -> 0 | I19: =COUNTIFS('SEPT DUMP '!$C:$C,'PARTNERS SUMMARY'!$B19,'SEPT DUMP '!$O:$O,"Rejected") -> 0 | J19: =COUNTIFS('SEPT DUMP '!$C:$C,'PARTNERS SUMMARY'!$B19,'SEPT DUMP '!$O:$O,"Unreachable") -> 0 | K19: =COUNTIFS('SEPT DUMP '!$C:$C,'PARTNERS SUMMARY'!$B19,'SEPT DUMP '!$O:$O,"Postponed(Update Y)") -> 0 | L19: =SUM(AH19:BK19) -> 0 | M19: =IFERROR(L19/G19,0) -> 0 | O19: =COUNTIF('OCT DUMP'!$D:$D,'PARTNERS SUMMARY'!$B19) -> 4 | P19: =COUNTIFS('OCT DUMP'!$D:$D,'PARTNERS SUMMARY'!$B19,'OCT DUMP'!Q:Q,"Prospect") -> 0 | Q19: =COUNTIFS('OCT DUMP'!$D:$D,'PARTNERS SUMMARY'!$B19,'OCT DUMP'!$Q:$Q,"Confirmed") -> 4 | R19: =COUNTIFS('OCT DUMP'!$D:$D,'PARTNERS SUMMARY'!$B19,'OCT DUMP'!$Q:$Q,"Rejected") -> 0 | S19: =COUNTIFS('OCT DUMP'!$D:$D,'PARTNERS SUMMARY'!$B19,'OCT DUMP'!$Q:$Q,"Unreachable") -> 0 | T19: =COUNTIFS('OCT DUMP'!$D:$D,'PARTNERS SUMMARY'!$B19,'OCT DUMP'!$Q:$Q,"Postponed(Update Y)") -> 0 | U19: =SUM(BL19:CP19) -> 0 | V19: =IFERROR(U19/O19,0) -> 0 | X19: =COUNTIF('NOV DUMP'!C:C,'PARTNERS SUMMARY'!$B19) -> 2 | Y19: =COUNTIFS('NOV DUMP'!$C:$C,'PARTNERS SUMMARY'!$B19,'NOV DUMP'!$S:$S,"Prospect") -> 0 | Z19: =COUNTIFS('NOV DUMP'!$C:$C,'PARTNERS SUMMARY'!$B19,'NOV DUMP'!$S:$S,"Confirmed") -> 0 | AA19: =COUNTIFS('NOV DUMP'!$C:$C,'PARTNERS SUMMARY'!$B19,'NOV DUMP'!$S:$S,"Rejected") -> 0 | AB19: =COUNTIFS('NOV DUMP'!$C:$C,'PARTNERS SUMMARY'!$B19,'NOV DUMP'!$S:$S,"Unreachable") -> 0 | AC19: =COUNTIFS('NOV DUMP'!$C:$C,'PARTNERS SUMMARY'!$B19,'NOV DUMP'!$S:$S,"Postponed(Update Y)") -> 0 | AD19: =SUM(CQ19:DT19) -> 2 | AE19: =COUNTIFS('ACTIVATED LEADS '!$H:$H,'PARTNERS SUMMARY'!$B19,'ACTIVATED LEADS '!$K:$K,'PARTNERS SUMMARY'!$AE$2,'ACTIVATED LEADS '!$C:$C,"16") -> 1 | AF19: =IFERROR(AD19/X19,0) -> 1 | AH19: =COUNTIFS('ACTIVATED LEADS '!$H:$H,$B19,'ACTIVATED LEADS '!$D:$D,'PARTNERS SUMMARY'!AH$3) -> 0 | AI19: =COUNTIFS('ACTIVATED LEADS '!$H:$H,$B19,'ACTIVATED LEADS '!$D:$D,'PARTNERS SUMMARY'!AI$3) -> 0 | AJ19: =COUNTIFS('ACTIVATED LEADS '!$H:$H,$B19,'ACTIVATED LEADS '!$D:$D,'PARTNERS SUMMARY'!AJ$3) -> 0 | AK19: =COUNTIFS('ACTIVATED LEADS '!$H:$H,$B19,'ACTIVATED LEADS '!$D:$D,'PARTNERS SUMMARY'!AK$3) -> 0 | AL19: =COUNTIFS('ACTIVATED LEADS '!$H:$H,$B19,'ACTIVATED LEADS '!$D:$D,'PARTNERS SUMMARY'!AL$3) -> 0 | AM19: =COUNTIFS('ACTIVATED LEADS '!$H:$H,$B19,'ACTIVATED LEADS '!$D:$D,'PARTNERS SUMMARY'!AM$3) -> 0 | AN19: =COUNTIFS('ACTIVATED LEADS '!$H:$H,$B19,'ACTIVATED LEADS '!$D:$D,'PARTNERS SUMMARY'!AN$3) -> 0 | AO19: =COUNTIFS('ACTIVATED LEADS '!$H:$H,$B19,'ACTIVATED LEADS '!$D:$D,'PARTNERS SUMMARY'!AO$3) -> 0 | ... DO19: =COUNTIFS('ACTIVATED LEADS '!$H:$H,$B19,'ACTIVATED LEADS '!$D:$D,'PARTNERS SUMMARY'!DO$3) -> 0
A20: Brian Odero | B20: AJ KENYA LIMITED | C20: 736284530 | D20: gfredrick15@gmail.com | E20: Westlands, Krishna centre,6th floor | F20: Nairobi | G20: =COUNTIF('SEPT DUMP '!$C:$C,'PARTNERS SUMMARY'!$B20) -> 1 | H20: =COUNTIFS('SEPT DUMP '!$C:$C,'PARTNERS SUMMARY'!$B20,'SEPT DUMP '!$O:$O,"Confirmed") -> 1 | I20: =COUNTIFS('SEPT DUMP '!$C:$C,'PARTNERS SUMMARY'!$B20,'SEPT DUMP '!$O:$O,"Rejected") -> 0 | J20: =COUNTIFS('SEPT DUMP '!$C:$C,'PARTNERS SUMMARY'!$B20,'SEPT DUMP '!$O:$O,"Unreachable") -> 0 | K20: =COUNTIFS('SEPT DUMP '!$C:$C,'PARTNERS SUMMARY'!$B20,'SEPT DUMP '!$O:$O,"Postponed(Update Y)") -> 0 | L20: =SUM(AH20:BK20) -> 0 | M20: =IFERROR(L20/G20,0) -> 0 | O20: =COUNTIF('OCT DUMP'!$D:$D,'PARTNERS SUMMARY'!$B20) -> 0 | P20: =COUNTIFS('OCT DUMP'!$D:$D,'PARTNERS SUMMARY'!$B20,'OCT DUMP'!Q:Q,"Prospect") -> 0 | Q20: =COUNTIFS('OCT DUMP'!$D:$D,'PARTNERS SUMMARY'!$B20,'OCT DUMP'!$Q:$Q,"Confirmed") -> 0 | R20: =COUNTIFS('OCT DUMP'!$D:$D,'PARTNERS SUMMARY'!$B20,'OCT DUMP'!$Q:$Q,"Rejected") -> 0 | S20: =COUNTIFS('OCT DUMP'!$D:$D,'PARTNERS SUMMARY'!$B20,'OCT DUMP'!$Q:$Q,"Unreachable") -> 0 | T20: =COUNTIFS('OCT DUMP'!$D:$D,'PARTNERS SUMMARY'!$B20,'OCT DUMP'!$Q:$Q,"Postponed(Update Y)") -> 0 | U20: =SUM(BL20:CP20) -> 0 | V20: =IFERROR(U20/O20,0) -> 0 | X20: =COUNTIF('NOV DUMP'!C:C,'PARTNERS SUMMARY'!$B20) -> 0 | Y20: =COUNTIFS('NOV DUMP'!$C:$C,'PARTNERS SUMMARY'!$B20,'NOV DUMP'!$S:$S,"Prospect") -> 0 | Z20: =COUNTIFS('NOV DUMP'!$C:$C,'PARTNERS SUMMARY'!$B20,'NOV DUMP'!$S:$S,"Confirmed") -> 0 | AA20: =COUNTIFS('NOV DUMP'!$C:$C,'PARTNERS SUMMARY'!$B20,'NOV DUMP'!$S:$S,"Rejected") -> 0 | AB20: =COUNTIFS('NOV DUMP'!$C:$C,'PARTNERS SUMMARY'!$B20,'NOV DUMP'!$S:$S,"Unreachable") -> 0 | AC20: =COUNTIFS('NOV DUMP'!$C:$C,'PARTNERS SUMMARY'!$B20,'NOV DUMP'!$S:$S,"Postponed(Update Y)") -> 0 | AD20: =SUM(CQ20:DT20) -> 0 | AE20: =COUNTIFS('ACTIVATED LEADS '!$H:$H,'PARTNERS SUMMARY'!$B20,'ACTIVATED LEADS '!$K:$K,'PARTNERS SUMMARY'!$AE$2,'ACTIVATED LEADS '!$C:$C,"16") -> 0 | AF20: =IFERROR(AD20/X20,0) -> 0 | AH20: =COUNTIFS('ACTIVATED LEADS '!$H:$H,$B20,'ACTIVATED LEADS '!$D:$D,'PARTNERS SUMMARY'!AH$3) -> 0 | AI20: =COUNTIFS('ACTIVATED LEADS '!$H:$H,$B20,'ACTIVATED LEADS '!$D:$D,'PARTNERS SUMMARY'!AI$3) -> 0 | AJ20: =COUNTIFS('ACTIVATED LEADS '!$H:$H,$B20,'ACTIVATED LEADS '!$D:$D,'PARTNERS SUMMARY'!AJ$3) -> 0 | AK20: =COUNTIFS('ACTIVATED LEADS '!$H:$H,$B20,'ACTIVATED LEADS '!$D:$D,'PARTNERS SUMMARY'!AK$3) -> 0 | AL20: =COUNTIFS('ACTIVATED LEADS '!$H:$H,$B20,'ACTIVATED LEADS '!$D:$D,'PARTNERS SUMMARY'!AL$3) -> 0 | AM20: =COUNTIFS('ACTIVATED LEADS '!$H:$H,$B20,'ACTIVATED LEADS '!$D:$D,'PARTNERS SUMMARY'!AM$3) -> 0 | AN20: =COUNTIFS('ACTIVATED LEADS '!$H:$H,$B20,'ACTIVATED LEADS '!$D:$D,'PARTNERS SUMMARY'!AN$3) -> 0 | AO20: =COUNTIFS('ACTIVATED LEADS '!$H:$H,$B20,'ACTIVATED LEADS '!$D:$D,'PARTNERS SUMMARY'!AO$3) -> 0 | ... DO20: =COUNTIFS('ACTIVATED LEADS '!$H:$H,$B20,'ACTIVATED LEADS '!$D:$D,'PARTNERS SUMMARY'!DO$3) -> 0
A21: Mariana Hongo | B21: BAMBANET TECHNOLOGIES | C21: 732895814 | D21: calebokonji@gmail.com | F21: Western | G21: =COUNTIF('SEPT DUMP '!$C:$C,'PARTNERS SUMMARY'!$B21) -> 0 | H21: =COUNTIFS('SEPT DUMP '!$C:$C,'PARTNERS SUMMARY'!$B21,'SEPT DUMP '!$O:$O,"Confirmed") -> 0 | I21: =COUNTIFS('SEPT DUMP '!$C:$C,'PARTNERS SUMMARY'!$B21,'SEPT DUMP '!$O:$O,"Rejected") -> 0 | J21: =COUNTIFS('SEPT DUMP '!$C:$C,'PARTNERS SUMMARY'!$B21,'SEPT DUMP '!$O:$O,"Unreachable") -> 0 | K21: =COUNTIFS('SEPT DUMP '!$C:$C,'PARTNERS SUMMARY'!$B21,'SEPT DUMP '!$O:$O,"Postponed(Update Y)") -> 0 | L21: =SUM(AH21:BK21) -> 0 | M21: =IFERROR(L21/G21,0) -> 0 | O21: =COUNTIF('OCT DUMP'!$D:$D,'PARTNERS SUMMARY'!$B21) -> 2 | P21: =COUNTIFS('OCT DUMP'!$D:$D,'PARTNERS SUMMARY'!$B21,'OCT DUMP'!Q:Q,"Prospect") -> 0 | Q21: =COUNTIFS('OCT DUMP'!$D:$D,'PARTNERS SUMMARY'!$B21,'OCT DUMP'!$Q:$Q,"Confirmed") -> 2 | R21: =COUNTIFS('OCT DUMP'!$D:$D,'PARTNERS SUMMARY'!$B21,'OCT DUMP'!$Q:$Q,"Rejected") -> 0 | S21: =COUNTIFS('OCT DUMP'!$D:$D,'PARTNERS SUMMARY'!$B21,'OCT DUMP'!$Q:$Q,"Unreachable") -> 0 | T21: =COUNTIFS('OCT DUMP'!$D:$D,'PARTNERS SUMMARY'!$B21,'OCT DUMP'!$Q:$Q,"Postponed(Update Y)") -> 0 | U21: =SUM(BL21:CP21) -> 1 | V21: =IFERROR(U21/O21,0) -> 0.5 | X21: =COUNTIF('NOV DUMP'!C:C,'PARTNERS SUMMARY'!$B21) -> 0 | Y21: =COUNTIFS('NOV DUMP'!$C:$C,'PARTNERS SUMMARY'!$B21,'NOV DUMP'!$S:$S,"Prospect") -> 0 | Z21: =COUNTIFS('NOV DUMP'!$C:$C,'PARTNERS SUMMARY'!$B21,'NOV DUMP'!$S:$S,"Confirmed") -> 0 | AA21: =COUNTIFS('NOV DUMP'!$C:$C,'PARTNERS SUMMARY'!$B21,'NOV DUMP'!$S:$S,"Rejected") -> 0 | AB21: =COUNTIFS('NOV DUMP'!$C:$C,'PARTNERS SUMMARY'!$B21,'NOV DUMP'!$S:$S,"Unreachable") -> 0 | AC21: =COUNTIFS('NOV DUMP'!$C:$C,'PARTNERS SUMMARY'!$B21,'NOV DUMP'!$S:$S,"Postponed(Update Y)") -> 0 | AD21: =SUM(CQ21:DT21) -> 1 | AE21: =COUNTIFS('ACTIVATED LEADS '!$H:$H,'PARTNERS SUMMARY'!$B21,'ACTIVATED LEADS '!$K:$K,'PARTNERS SUMMARY'!$AE$2,'ACTIVATED LEADS '!$C:$C,"16") -> 1 | AF21: =IFERROR(AD21/X21,0) -> 0 | AH21: =COUNTIFS('ACTIVATED LEADS '!$H:$H,$B21,'ACTIVATED LEADS '!$D:$D,'PARTNERS SUMMARY'!AH$3) -> 0 | AI21: =COUNTIFS('ACTIVATED LEADS '!$H:$H,$B21,'ACTIVATED LEADS '!$D:$D,'PARTNERS SUMMARY'!AI$3) -> 0 | AJ21: =COUNTIFS('ACTIVATED LEADS '!$H:$H,$B21,'ACTIVATED LEADS '!$D:$D,'PARTNERS SUMMARY'!AJ$3) -> 0 | AK21: =COUNTIFS('ACTIVATED LEADS '!$H:$H,$B21,'ACTIVATED LEADS '!$D:$D,'PARTNERS SUMMARY'!AK$3) -> 0 | AL21: =COUNTIFS('ACTIVATED LEADS '!$H:$H,$B21,'ACTIVATED LEADS '!$D:$D,'PARTNERS SUMMARY'!AL$3) -> 0 | AM21: =COUNTIFS('ACTIVATED LEADS '!$H:$H,$B21,'ACTIVATED LEADS '!$D:$D,'PARTNERS SUMMARY'!AM$3) -> 0 | AN21: =COUNTIFS('ACTIVATED LEADS '!$H:$H,$B21,'ACTIVATED LEADS '!$D:$D,'PARTNERS SUMMARY'!AN$3) -> 0 | AO21: =COUNTIFS('ACTIVATED LEADS '!$H:$H,$B21,'ACTIVATED LEADS '!$D:$D,'PARTNERS SUMMARY'!AO$3) -> 0 | ... DO21: =COUNTIFS('ACTIVATED LEADS '!$H:$H,$B21,'ACTIVATED LEADS '!$D:$D,'PARTNERS SUMMARY'!DO$3) -> 0
A22: Brian Odero | B22: LEARNERS BRIDGE SOLUTION | C22: 738895780 | D22: edwinoyugi254@gmail.com | E22: Umoja | F22: Nairobi | G22: =COUNTIF('SEPT DUMP '!$C:$C,'PARTNERS SUMMARY'!$B22) -> 0 | H22: =COUNTIFS('SEPT DUMP '!$C:$C,'PARTNERS SUMMARY'!$B22,'SEPT DUMP '!$O:$O,"Confirmed") -> 0 | I22: =COUNTIFS('SEPT DUMP '!$C:$C,'PARTNERS SUMMARY'!$B22,'SEPT DUMP '!$O:$O,"Rejected") -> 0 | J22: =COUNTIFS('SEPT DUMP '!$C:$C,'PARTNERS SUMMARY'!$B22,'SEPT DUMP '!$O:$O,"Unreachable") -> 0 | K22: =COUNTIFS('SEPT DUMP '!$C:$C,'PARTNERS SUMMARY'!$B22,'SEPT DUMP '!$O:$O,"Postponed(Update Y)") -> 0 | L22: =SUM(AH22:BK22) -> 0 | M22: =IFERROR(L22/G22,0) -> 0 | O22: =COUNTIF('OCT DUMP'!$D:$D,'PARTNERS SUMMARY'!$B22) -> 2 | P22: =COUNTIFS('OCT DUMP'!$D:$D,'PARTNERS SUMMARY'!$B22,'OCT DUMP'!Q:Q,"Prospect") -> 0 | Q22: =COUNTIFS('OCT DUMP'!$D:$D,'PARTNERS SUMMARY'!$B22,'OCT DUMP'!$Q:$Q,"Confirmed") -> 0 | R22: =COUNTIFS('OCT DUMP'!$D:$D,'PARTNERS SUMMARY'!$B22,'OCT DUMP'!$Q:$Q,"Rejected") -> 2 | S22: =COUNTIFS('OCT DUMP'!$D:$D,'PARTNERS SUMMARY'!$B22,'OCT DUMP'!$Q:$Q,"Unreachable") -> 0 | T22: =COUNTIFS('OCT DUMP'!$D:$D,'PARTNERS SUMMARY'!$B22,'OCT DUMP'!$Q:$Q,"Postponed(Update Y)") -> 0 | U22: =SUM(BL22:CP22) -> 0 | V22: =IFERROR(U22/O22,0) -> 0 | X22: =COUNTIF('NOV DUMP'!C:C,'PARTNERS SUMMARY'!$B22) -> 0 | Y22: =COUNTIFS('NOV DUMP'!$C:$C,'PARTNERS SUMMARY'!$B22,'NOV DUMP'!$S:$S,"Prospect") -> 0 | Z22: =COUNTIFS('NOV DUMP'!$C:$C,'PARTNERS SUMMARY'!$B22,'NOV DUMP'!$S:$S,"Confirmed") -> 0 | AA22: =COUNTIFS('NOV DUMP'!$C:$C,'PARTNERS SUMMARY'!$B22,'NOV DUMP'!$S:$S,"Rejected") -> 0 | AB22: =COUNTIFS('NOV DUMP'!$C:$C,'PARTNERS SUMMARY'!$B22,'NOV DUMP'!$S:$S,"Unreachable") -> 0 | AC22: =COUNTIFS('NOV DUMP'!$C:$C,'PARTNERS SUMMARY'!$B22,'NOV DUMP'!$S:$S,"Postponed(Update Y)") -> 0 | AD22: =SUM(CQ22:DT22) -> 0 | AE22: =COUNTIFS('ACTIVATED LEADS '!$H:$H,'PARTNERS SUMMARY'!$B22,'ACTIVATED LEADS '!$K:$K,'PARTNERS SUMMARY'!$AE$2,'ACTIVATED LEADS '!$C:$C,"16") -> 0 | AF22: =IFERROR(AD22/X22,0) -> 0 | AH22: =COUNTIFS('ACTIVATED LEADS '!$H:$H,$B22,'ACTIVATED LEADS '!$D:$D,'PARTNERS SUMMARY'!AH$3) -> 0 | AI22: =COUNTIFS('ACTIVATED LEADS '!$H:$H,$B22,'ACTIVATED LEADS '!$D:$D,'PARTNERS SUMMARY'!AI$3) -> 0 | AJ22: =COUNTIFS('ACTIVATED LEADS '!$H:$H,$B22,'ACTIVATED LEADS '!$D:$D,'PARTNERS SUMMARY'!AJ$3) -> 0 | AK22: =COUNTIFS('ACTIVATED LEADS '!$H:$H,$B22,'ACTIVATED LEADS '!$D:$D,'PARTNERS SUMMARY'!AK$3) -> 0 | AL22: =COUNTIFS('ACTIVATED LEADS '!$H:$H,$B22,'ACTIVATED LEADS '!$D:$D,'PARTNERS SUMMARY'!AL$3) -> 0 | AM22: =COUNTIFS('ACTIVATED LEADS '!$H:$H,$B22,'ACTIVATED LEADS '!$D:$D,'PARTNERS SUMMARY'!AM$3) -> 0 | AN22: =COUNTIFS('ACTIVATED LEADS '!$H:$H,$B22,'ACTIVATED LEADS '!$D:$D,'PARTNERS SUMMARY'!AN$3) -> 0 | AO22: =COUNTIFS('ACTIVATED LEADS '!$H:$H,$B22,'ACTIVATED LEADS '!$D:$D,'PARTNERS SUMMARY'!AO$3) -> 0 | ... DO22: =COUNTIFS('ACTIVATED LEADS '!$H:$H,$B22,'ACTIVATED LEADS '!$D:$D,'PARTNERS SUMMARY'!DO$3) -> 0
A23: Damaris Mainga | B23: Ramitech Networks Ltd | C23: 105460674 | D23: Benson@gmail.com | E23: TRM | F23: Nairobi | G23: =COUNTIF('SEPT DUMP '!$C:$C,'PARTNERS SUMMARY'!$B23) -> 1 | H23: =COUNTIFS('SEPT DUMP '!$C:$C,'PARTNERS SUMMARY'!$B23,'SEPT DUMP '!$O:$O,"Confirmed") -> 1 | I23: =COUNTIFS('SEPT DUMP '!$C:$C,'PARTNERS SUMMARY'!$B23,'SEPT DUMP '!$O:$O,"Rejected") -> 0 | J23: =COUNTIFS('SEPT DUMP '!$C:$C,'PARTNERS SUMMARY'!$B23,'SEPT DUMP '!$O:$O,"Unreachable") -> 0 | K23: =COUNTIFS('SEPT DUMP '!$C:$C,'PARTNERS SUMMARY'!$B23,'SEPT DUMP '!$O:$O,"Postponed(Update Y)") -> 0 | L23: =SUM(AH23:BK23) -> 0 | M23: =IFERROR(L23/G23,0) -> 0 | O23: =COUNTIF('OCT DUMP'!$D:$D,'PARTNERS SUMMARY'!$B23) -> 0 | P23: =COUNTIFS('OCT DUMP'!$D:$D,'PARTNERS SUMMARY'!$B23,'OCT DUMP'!Q:Q,"Prospect") -> 0 | Q23: =COUNTIFS('OCT DUMP'!$D:$D,'PARTNERS SUMMARY'!$B23,'OCT DUMP'!$Q:$Q,"Confirmed") -> 0 | R23: =COUNTIFS('OCT DUMP'!$D:$D,'PARTNERS SUMMARY'!$B23,'OCT DUMP'!$Q:$Q,"Rejected") -> 0 | S23: =COUNTIFS('OCT DUMP'!$D:$D,'PARTNERS SUMMARY'!$B23,'OCT DUMP'!$Q:$Q,"Unreachable") -> 0 | T23: =COUNTIFS('OCT DUMP'!$D:$D,'PARTNERS SUMMARY'!$B23,'OCT DUMP'!$Q:$Q,"Postponed(Update Y)") -> 0 | U23: =SUM(BL23:CP23) -> 1 | V23: =IFERROR(U23/O23,0) -> 0 | X23: =COUNTIF('NOV DUMP'!C:C,'PARTNERS SUMMARY'!$B23) -> 1 | Y23: =COUNTIFS('NOV DUMP'!$C:$C,'PARTNERS SUMMARY'!$B23,'NOV DUMP'!$S:$S,"Prospect") -> 0 | Z23: =COUNTIFS('NOV DUMP'!$C:$C,'PARTNERS SUMMARY'!$B23,'NOV DUMP'!$S:$S,"Confirmed") -> 0 | AA23: =COUNTIFS('NOV DUMP'!$C:$C,'PARTNERS SUMMARY'!$B23,'NOV DUMP'!$S:$S,"Rejected") -> 0 | AB23: =COUNTIFS('NOV DUMP'!$C:$C,'PARTNERS SUMMARY'!$B23,'NOV DUMP'!$S:$S,"Unreachable") -> 0 | AC23: =COUNTIFS('NOV DUMP'!$C:$C,'PARTNERS SUMMARY'!$B23,'NOV DUMP'!$S:$S,"Postponed(Update Y)") -> 0 | AD23: =SUM(CQ23:DT23) -> 0 | AE23: =COUNTIFS('ACTIVATED LEADS '!$H:$H,'PARTNERS SUMMARY'!$B23,'ACTIVATED LEADS '!$K:$K,'PARTNERS SUMMARY'!$AE$2,'ACTIVATED LEADS '!$C:$C,"16") -> 0 | AF23: =IFERROR(AD23/X23,0) -> 0 | AH23: =COUNTIFS('ACTIVATED LEADS '!$H:$H,$B23,'ACTIVATED LEADS '!$D:$D,'PARTNERS SUMMARY'!AH$3) -> 0 | AI23: =COUNTIFS('ACTIVATED LEADS '!$H:$H,$B23,'ACTIVATED LEADS '!$D:$D,'PARTNERS SUMMARY'!AI$3) -> 0 | AJ23: =COUNTIFS('ACTIVATED LEADS '!$H:$H,$B23,'ACTIVATED LEADS '!$D:$D,'PARTNERS SUMMARY'!AJ$3) -> 0 | AK23: =COUNTIFS('ACTIVATED LEADS '!$H:$H,$B23,'ACTIVATED LEADS '!$D:$D,'PARTNERS SUMMARY'!AK$3) -> 0 | AL23: =COUNTIFS('ACTIVATED LEADS '!$H:$H,$B23,'ACTIVATED LEADS '!$D:$D,'PARTNERS SUMMARY'!AL$3) -> 0 | AM23: =COUNTIFS('ACTIVATED LEADS '!$H:$H,$B23,'ACTIVATED LEADS '!$D:$D,'PARTNERS SUMMARY'!AM$3) -> 0 | AN23: =COUNTIFS('ACTIVATED LEADS '!$H:$H,$B23,'ACTIVATED LEADS '!$D:$D,'PARTNERS SUMMARY'!AN$3) -> 0 | AO23: =COUNTIFS('ACTIVATED LEADS '!$H:$H,$B23,'ACTIVATED LEADS '!$D:$D,'PARTNERS SUMMARY'!AO$3) -> 0 | ... DO23: =COUNTIFS('ACTIVATED LEADS '!$H:$H,$B23,'ACTIVATED LEADS '!$D:$D,'PARTNERS SUMMARY'!DO$3) -> 0
A24: Damaris Mainga | B24: HUBTECH | C24: 781013332 | E24: Nairobi CBD | F24: Nairobi | G24: =COUNTIF('SEPT DUMP '!$C:$C,'PARTNERS SUMMARY'!$B24) -> 0 | H24: =COUNTIFS('SEPT DUMP '!$C:$C,'PARTNERS SUMMARY'!$B24,'SEPT DUMP '!$O:$O,"Confirmed") -> 0 | I24: =COUNTIFS('SEPT DUMP '!$C:$C,'PARTNERS SUMMARY'!$B24,'SEPT DUMP '!$O:$O,"Rejected") -> 0 | J24: =COUNTIFS('SEPT DUMP '!$C:$C,'PARTNERS SUMMARY'!$B24,'SEPT DUMP '!$O:$O,"Unreachable") -> 0 | K24: =COUNTIFS('SEPT DUMP '!$C:$C,'PARTNERS SUMMARY'!$B24,'SEPT DUMP '!$O:$O,"Postponed(Update Y)") -> 0 | L24: =SUM(AH24:BK24) -> 0 | M24: =IFERROR(L24/G24,0) -> 0 | O24: =COUNTIF('OCT DUMP'!$D:$D,'PARTNERS SUMMARY'!$B24) -> 0 | P24: =COUNTIFS('OCT DUMP'!$D:$D,'PARTNERS SUMMARY'!$B24,'OCT DUMP'!Q:Q,"Prospect") -> 0 | Q24: =COUNTIFS('OCT DUMP'!$D:$D,'PARTNERS SUMMARY'!$B24,'OCT DUMP'!$Q:$Q,"Confirmed") -> 0 | R24: =COUNTIFS('OCT DUMP'!$D:$D,'PARTNERS SUMMARY'!$B24,'OCT DUMP'!$Q:$Q,"Rejected") -> 0 | S24: =COUNTIFS('OCT DUMP'!$D:$D,'PARTNERS SUMMARY'!$B24,'OCT DUMP'!$Q:$Q,"Unreachable") -> 0 | T24: =COUNTIFS('OCT DUMP'!$D:$D,'PARTNERS SUMMARY'!$B24,'OCT DUMP'!$Q:$Q,"Postponed(Update Y)") -> 0 | U24: =SUM(BL24:CP24) -> 0 | V24: =IFERROR(U24/O24,0) -> 0 | X24: =COUNTIF('NOV DUMP'!C:C,'PARTNERS SUMMARY'!$B24) -> 0 | Y24: =COUNTIFS('NOV DUMP'!$C:$C,'PARTNERS SUMMARY'!$B24,'NOV DUMP'!$S:$S,"Prospect") -> 0 | Z24: =COUNTIFS('NOV DUMP'!$C:$C,'PARTNERS SUMMARY'!$B24,'NOV DUMP'!$S:$S,"Confirmed") -> 0 | AA24: =COUNTIFS('NOV DUMP'!$C:$C,'PARTNERS SUMMARY'!$B24,'NOV DUMP'!$S:$S,"Rejected") -> 0 | AB24: =COUNTIFS('NOV DUMP'!$C:$C,'PARTNERS SUMMARY'!$B24,'NOV DUMP'!$S:$S,"Unreachable") -> 0 | AC24: =COUNTIFS('NOV DUMP'!$C:$C,'PARTNERS SUMMARY'!$B24,'NOV DUMP'!$S:$S,"Postponed(Update Y)") -> 0 | AD24: =SUM(CQ24:DT24) -> 0 | AE24: =COUNTIFS('ACTIVATED LEADS '!$H:$H,'PARTNERS SUMMARY'!$B24,'ACTIVATED LEADS '!$K:$K,'PARTNERS SUMMARY'!$AE$2,'ACTIVATED LEADS '!$C:$C,"16") -> 0 | AF24: =IFERROR(AD24/X24,0) -> 0 | AH24: =COUNTIFS('ACTIVATED LEADS '!$H:$H,$B24,'ACTIVATED LEADS '!$D:$D,'PARTNERS SUMMARY'!AH$3) -> 0 | AI24: =COUNTIFS('ACTIVATED LEADS '!$H:$H,$B24,'ACTIVATED LEADS '!$D:$D,'PARTNERS SUMMARY'!AI$3) -> 0 | AJ24: =COUNTIFS('ACTIVATED LEADS '!$H:$H,$B24,'ACTIVATED LEADS '!$D:$D,'PARTNERS SUMMARY'!AJ$3) -> 0 | AK24: =COUNTIFS('ACTIVATED LEADS '!$H:$H,$B24,'ACTIVATED LEADS '!$D:$D,'PARTNERS SUMMARY'!AK$3) -> 0 | AL24: =COUNTIFS('ACTIVATED LEADS '!$H:$H,$B24,'ACTIVATED LEADS '!$D:$D,'PARTNERS SUMMARY'!AL$3) -> 0 | AM24: =COUNTIFS('ACTIVATED LEADS '!$H:$H,$B24,'ACTIVATED LEADS '!$D:$D,'PARTNERS SUMMARY'!AM$3) -> 0 | AN24: =COUNTIFS('ACTIVATED LEADS '!$H:$H,$B24,'ACTIVATED LEADS '!$D:$D,'PARTNERS SUMMARY'!AN$3) -> 0 | AO24: =COUNTIFS('ACTIVATED LEADS '!$H:$H,$B24,'ACTIVATED LEADS '!$D:$D,'PARTNERS SUMMARY'!AO$3) -> 0 | ... DO24: =COUNTIFS('ACTIVATED LEADS '!$H:$H,$B24,'ACTIVATED LEADS '!$D:$D,'PARTNERS SUMMARY'!DO$3) -> 0
A25: Mariana Hongo | B25: MBALEICT INVESTMENTS | C25: 782877935 | E25: Vihiga | F25: Western | G25: =COUNTIF('SEPT DUMP '!$C:$C,'PARTNERS SUMMARY'!$B25) -> 0 | H25: =COUNTIFS('SEPT DUMP '!$C:$C,'PARTNERS SUMMARY'!$B25,'SEPT DUMP '!$O:$O,"Confirmed") -> 0 | I25: =COUNTIFS('SEPT DUMP '!$C:$C,'PARTNERS SUMMARY'!$B25,'SEPT DUMP '!$O:$O,"Rejected") -> 0 | J25: =COUNTIFS('SEPT DUMP '!$C:$C,'PARTNERS SUMMARY'!$B25,'SEPT DUMP '!$O:$O,"Unreachable") -> 0 | K25: =COUNTIFS('SEPT DUMP '!$C:$C,'PARTNERS SUMMARY'!$B25,'SEPT DUMP '!$O:$O,"Postponed(Update Y)") -> 0 | L25: =SUM(AH25:BK25) -> 0 | M25: =IFERROR(L25/G25,0) -> 0 | O25: =COUNTIF('OCT DUMP'!$D:$D,'PARTNERS SUMMARY'!$B25) -> 0 | P25: =COUNTIFS('OCT DUMP'!$D:$D,'PARTNERS SUMMARY'!$B25,'OCT DUMP'!Q:Q,"Prospect") -> 0 | Q25: =COUNTIFS('OCT DUMP'!$D:$D,'PARTNERS SUMMARY'!$B25,'OCT DUMP'!$Q:$Q,"Confirmed") -> 0 | R25: =COUNTIFS('OCT DUMP'!$D:$D,'PARTNERS SUMMARY'!$B25,'OCT DUMP'!$Q:$Q,"Rejected") -> 0 | S25: =COUNTIFS('OCT DUMP'!$D:$D,'PARTNERS SUMMARY'!$B25,'OCT DUMP'!$Q:$Q,"Unreachable") -> 0 | T25: =COUNTIFS('OCT DUMP'!$D:$D,'PARTNERS SUMMARY'!$B25,'OCT DUMP'!$Q:$Q,"Postponed(Update Y)") -> 0 | U25: =SUM(BL25:CP25) -> 0 | V25: =IFERROR(U25/O25,0) -> 0 | X25: =COUNTIF('NOV DUMP'!C:C,'PARTNERS SUMMARY'!$B25) -> 0 | Y25: =COUNTIFS('NOV DUMP'!$C:$C,'PARTNERS SUMMARY'!$B25,'NOV DUMP'!$S:$S,"Prospect") -> 0 | Z25: =COUNTIFS('NOV DUMP'!$C:$C,'PARTNERS SUMMARY'!$B25,'NOV DUMP'!$S:$S,"Confirmed") -> 0 | AA25: =COUNTIFS('NOV DUMP'!$C:$C,'PARTNERS SUMMARY'!$B25,'NOV DUMP'!$S:$S,"Rejected") -> 0 | AB25: =COUNTIFS('NOV DUMP'!$C:$C,'PARTNERS SUMMARY'!$B25,'NOV DUMP'!$S:$S,"Unreachable") -> 0 | AC25: =COUNTIFS('NOV DUMP'!$C:$C,'PARTNERS SUMMARY'!$B25,'NOV DUMP'!$S:$S,"Postponed(Update Y)") -> 0 | AD25: =SUM(CQ25:DT25) -> 0 | AE25: =COUNTIFS('ACTIVATED LEADS '!$H:$H,'PARTNERS SUMMARY'!$B25,'ACTIVATED LEADS '!$K:$K,'PARTNERS SUMMARY'!$AE$2,'ACTIVATED LEADS '!$C:$C,"16") -> 0 | AF25: =IFERROR(AD25/X25,0) -> 0 | AH25: =COUNTIFS('ACTIVATED LEADS '!$H:$H,$B25,'ACTIVATED LEADS '!$D:$D,'PARTNERS SUMMARY'!AH$3) -> 0 | AI25: =COUNTIFS('ACTIVATED LEADS '!$H:$H,$B25,'ACTIVATED LEADS '!$D:$D,'PARTNERS SUMMARY'!AI$3) -> 0 | AJ25: =COUNTIFS('ACTIVATED LEADS '!$H:$H,$B25,'ACTIVATED LEADS '!$D:$D,'PARTNERS SUMMARY'!AJ$3) -> 0 | AK25: =COUNTIFS('ACTIVATED LEADS '!$H:$H,$B25,'ACTIVATED LEADS '!$D:$D,'PARTNERS SUMMARY'!AK$3) -> 0 | AL25: =COUNTIFS('ACTIVATED LEADS '!$H:$H,$B25,'ACTIVATED LEADS '!$D:$D,'PARTNERS SUMMARY'!AL$3) -> 0 | AM25: =COUNTIFS('ACTIVATED LEADS '!$H:$H,$B25,'ACTIVATED LEADS '!$D:$D,'PARTNERS SUMMARY'!AM$3) -> 0 | AN25: =COUNTIFS('ACTIVATED LEADS '!$H:$H,$B25,'ACTIVATED LEADS '!$D:$D,'PARTNERS SUMMARY'!AN$3) -> 0 | AO25: =COUNTIFS('ACTIVATED LEADS '!$H:$H,$B25,'ACTIVATED LEADS '!$D:$D,'PARTNERS SUMMARY'!AO$3) -> 0 | ... DO25: =COUNTIFS('ACTIVATED LEADS '!$H:$H,$B25,'ACTIVATED LEADS '!$D:$D,'PARTNERS SUMMARY'!DO$3) -> 0
A26: Damaris Mainga | B26: TEGEMEO TELKOM | F26: Nairobi | G26: =COUNTIF('SEPT DUMP '!$C:$C,'PARTNERS SUMMARY'!$B26) -> 0 | H26: =COUNTIFS('SEPT DUMP '!$C:$C,'PARTNERS SUMMARY'!$B26,'SEPT DUMP '!$O:$O,"Confirmed") -> 0 | I26: =COUNTIFS('SEPT DUMP '!$C:$C,'PARTNERS SUMMARY'!$B26,'SEPT DUMP '!$O:$O,"Rejected") -> 0 | J26: =COUNTIFS('SEPT DUMP '!$C:$C,'PARTNERS SUMMARY'!$B26,'SEPT DUMP '!$O:$O,"Unreachable") -> 0 | K26: =COUNTIFS('SEPT DUMP '!$C:$C,'PARTNERS SUMMARY'!$B26,'SEPT DUMP '!$O:$O,"Postponed(Update Y)") -> 0 | L26: =SUM(AH26:BK26) -> 0 | M26: =IFERROR(L26/G26,0) -> 0 | O26: =COUNTIF('OCT DUMP'!$D:$D,'PARTNERS SUMMARY'!$B26) -> 0 | P26: =COUNTIFS('OCT DUMP'!$D:$D,'PARTNERS SUMMARY'!$B26,'OCT DUMP'!Q:Q,"Prospect") -> 0 | Q26: =COUNTIFS('OCT DUMP'!$D:$D,'PARTNERS SUMMARY'!$B26,'OCT DUMP'!$Q:$Q,"Confirmed") -> 0 | R26: =COUNTIFS('OCT DUMP'!$D:$D,'PARTNERS SUMMARY'!$B26,'OCT DUMP'!$Q:$Q,"Rejected") -> 0 | S26: =COUNTIFS('OCT DUMP'!$D:$D,'PARTNERS SUMMARY'!$B26,'OCT DUMP'!$Q:$Q,"Unreachable") -> 0 | T26: =COUNTIFS('OCT DUMP'!$D:$D,'PARTNERS SUMMARY'!$B26,'OCT DUMP'!$Q:$Q,"Postponed(Update Y)") -> 0 | U26: =SUM(BL26:CP26) -> 0 | V26: =IFERROR(U26/O26,0) -> 0 | X26: =COUNTIF('NOV DUMP'!C:C,'PARTNERS SUMMARY'!$B26) -> 0 | Y26: =COUNTIFS('NOV DUMP'!$C:$C,'PARTNERS SUMMARY'!$B26,'NOV DUMP'!$S:$S,"Prospect") -> 0 | Z26: =COUNTIFS('NOV DUMP'!$C:$C,'PARTNERS SUMMARY'!$B26,'NOV DUMP'!$S:$S,"Confirmed") -> 0 | AA26: =COUNTIFS('NOV DUMP'!$C:$C,'PARTNERS SUMMARY'!$B26,'NOV DUMP'!$S:$S,"Rejected") -> 0 | AB26: =COUNTIFS('NOV DUMP'!$C:$C,'PARTNERS SUMMARY'!$B26,'NOV DUMP'!$S:$S,"Unreachable") -> 0 | AC26: =COUNTIFS('NOV DUMP'!$C:$C,'PARTNERS SUMMARY'!$B26,'NOV DUMP'!$S:$S,"Postponed(Update Y)") -> 0 | AD26: =SUM(CQ26:DT26) -> 0 | AE26: =COUNTIFS('ACTIVATED LEADS '!$H:$H,'PARTNERS SUMMARY'!$B26,'ACTIVATED LEADS '!$K:$K,'PARTNERS SUMMARY'!$AE$2,'ACTIVATED LEADS '!$C:$C,"16") -> 0 | AF26: =IFERROR(AD26/X26,0) -> 0 | AH26: =COUNTIFS('ACTIVATED LEADS '!$H:$H,$B26,'ACTIVATED LEADS '!$D:$D,'PARTNERS SUMMARY'!AH$3) -> 0 | AI26: =COUNTIFS('ACTIVATED LEADS '!$H:$H,$B26,'ACTIVATED LEADS '!$D:$D,'PARTNERS SUMMARY'!AI$3) -> 0 | AJ26: =COUNTIFS('ACTIVATED LEADS '!$H:$H,$B26,'ACTIVATED LEADS '!$D:$D,'PARTNERS SUMMARY'!AJ$3) -> 0 | AK26: =COUNTIFS('ACTIVATED LEADS '!$H:$H,$B26,'ACTIVATED LEADS '!$D:$D,'PARTNERS SUMMARY'!AK$3) -> 0 | AL26: =COUNTIFS('ACTIVATED LEADS '!$H:$H,$B26,'ACTIVATED LEADS '!$D:$D,'PARTNERS SUMMARY'!AL$3) -> 0 | AM26: =COUNTIFS('ACTIVATED LEADS '!$H:$H,$B26,'ACTIVATED LEADS '!$D:$D,'PARTNERS SUMMARY'!AM$3) -> 0 | AN26: =COUNTIFS('ACTIVATED LEADS '!$H:$H,$B26,'ACTIVATED LEADS '!$D:$D,'PARTNERS SUMMARY'!AN$3) -> 0 | AO26: =COUNTIFS('ACTIVATED LEADS '!$H:$H,$B26,'ACTIVATED LEADS '!$D:$D,'PARTNERS SUMMARY'!AO$3) -> 0 | ... DO26: =COUNTIFS('ACTIVATED LEADS '!$H:$H,$B26,'ACTIVATED LEADS '!$D:$D,'PARTNERS SUMMARY'!DO$3) -> 0
A27: Fiona Maiyo | B27: SPICY LUMINARIES ENTERPRISE | C27: 739982832 | E27: Eldoret | F27: Rift | G27: =COUNTIF('SEPT DUMP '!$C:$C,'PARTNERS SUMMARY'!$B27) -> 0 | H27: =COUNTIFS('SEPT DUMP '!$C:$C,'PARTNERS SUMMARY'!$B27,'SEPT DUMP '!$O:$O,"Confirmed") -> 0 | I27: =COUNTIFS('SEPT DUMP '!$C:$C,'PARTNERS SUMMARY'!$B27,'SEPT DUMP '!$O:$O,"Rejected") -> 0 | J27: =COUNTIFS('SEPT DUMP '!$C:$C,'PARTNERS SUMMARY'!$B27,'SEPT DUMP '!$O:$O,"Unreachable") -> 0 | K27: =COUNTIFS('SEPT DUMP '!$C:$C,'PARTNERS SUMMARY'!$B27,'SEPT DUMP '!$O:$O,"Postponed(Update Y)") -> 0 | L27: =SUM(AH27:BK27) -> 0 | M27: =IFERROR(L27/G27,0) -> 0 | O27: =COUNTIF('OCT DUMP'!$D:$D,'PARTNERS SUMMARY'!$B27) -> 3 | P27: =COUNTIFS('OCT DUMP'!$D:$D,'PARTNERS SUMMARY'!$B27,'OCT DUMP'!Q:Q,"Prospect") -> 0 | Q27: =COUNTIFS('OCT DUMP'!$D:$D,'PARTNERS SUMMARY'!$B27,'OCT DUMP'!$Q:$Q,"Confirmed") -> 2 | R27: =COUNTIFS('OCT DUMP'!$D:$D,'PARTNERS SUMMARY'!$B27,'OCT DUMP'!$Q:$Q,"Rejected") -> 0 | S27: =COUNTIFS('OCT DUMP'!$D:$D,'PARTNERS SUMMARY'!$B27,'OCT DUMP'!$Q:$Q,"Unreachable") -> 1 | T27: =COUNTIFS('OCT DUMP'!$D:$D,'PARTNERS SUMMARY'!$B27,'OCT DUMP'!$Q:$Q,"Postponed(Update Y)") -> 0 | U27: =SUM(BL27:CP27) -> 2 | V27: =IFERROR(U27/O27,0) -> 0.66666667 | X27: =COUNTIF('NOV DUMP'!C:C,'PARTNERS SUMMARY'!$B27) -> 2 | Y27: =COUNTIFS('NOV DUMP'!$C:$C,'PARTNERS SUMMARY'!$B27,'NOV DUMP'!$S:$S,"Prospect") -> 0 | Z27: =COUNTIFS('NOV DUMP'!$C:$C,'PARTNERS SUMMARY'!$B27,'NOV DUMP'!$S:$S,"Confirmed") -> 0 | AA27: =COUNTIFS('NOV DUMP'!$C:$C,'PARTNERS SUMMARY'!$B27,'NOV DUMP'!$S:$S,"Rejected") -> 0 | AB27: =COUNTIFS('NOV DUMP'!$C:$C,'PARTNERS SUMMARY'!$B27,'NOV DUMP'!$S:$S,"Unreachable") -> 0 | AC27: =COUNTIFS('NOV DUMP'!$C:$C,'PARTNERS SUMMARY'!$B27,'NOV DUMP'!$S:$S,"Postponed(Update Y)") -> 0 | AD27: =SUM(CQ27:DT27) -> 1 | AE27: =COUNTIFS('ACTIVATED LEADS '!$H:$H,'PARTNERS SUMMARY'!$B27,'ACTIVATED LEADS '!$K:$K,'PARTNERS SUMMARY'!$AE$2,'ACTIVATED LEADS '!$C:$C,"16") -> 0 | AF27: =IFERROR(AD27/X27,0) -> 0.5 | AH27: =COUNTIFS('ACTIVATED LEADS '!$H:$H,$B27,'ACTIVATED LEADS '!$D:$D,'PARTNERS SUMMARY'!AH$3) -> 0 | AI27: =COUNTIFS('ACTIVATED LEADS '!$H:$H,$B27,'ACTIVATED LEADS '!$D:$D,'PARTNERS SUMMARY'!AI$3) -> 0 | AJ27: =COUNTIFS('ACTIVATED LEADS '!$H:$H,$B27,'ACTIVATED LEADS '!$D:$D,'PARTNERS SUMMARY'!AJ$3) -> 0 | AK27: =COUNTIFS('ACTIVATED LEADS '!$H:$H,$B27,'ACTIVATED LEADS '!$D:$D,'PARTNERS SUMMARY'!AK$3) -> 0 | AL27: =COUNTIFS('ACTIVATED LEADS '!$H:$H,$B27,'ACTIVATED LEADS '!$D:$D,'PARTNERS SUMMARY'!AL$3) -> 0 | AM27: =COUNTIFS('ACTIVATED LEADS '!$H:$H,$B27,'ACTIVATED LEADS '!$D:$D,'PARTNERS SUMMARY'!AM$3) -> 0 | AN27: =COUNTIFS('ACTIVATED LEADS '!$H:$H,$B27,'ACTIVATED LEADS '!$D:$D,'PARTNERS SUMMARY'!AN$3) -> 0 | AO27: =COUNTIFS('ACTIVATED LEADS '!$H:$H,$B27,'ACTIVATED LEADS '!$D:$D,'PARTNERS SUMMARY'!AO$3) -> 0 | ... DO27: =COUNTIFS('ACTIVATED LEADS '!$H:$H,$B27,'ACTIVATED LEADS '!$D:$D,'PARTNERS SUMMARY'!DO$3) -> 0
A28: Brian Odero | B28: OLIPHERNET BUSINESS SOLUTIONS | C28: 731366744 | E28: rongai | F28: Nairobi | G28: =COUNTIF('SEPT DUMP '!$C:$C,'PARTNERS SUMMARY'!$B28) -> 0 | H28: =COUNTIFS('SEPT DUMP '!$C:$C,'PARTNERS SUMMARY'!$B28,'SEPT DUMP '!$O:$O,"Confirmed") -> 0 | I28: =COUNTIFS('SEPT DUMP '!$C:$C,'PARTNERS SUMMARY'!$B28,'SEPT DUMP '!$O:$O,"Rejected") -> 0 | J28: =COUNTIFS('SEPT DUMP '!$C:$C,'PARTNERS SUMMARY'!$B28,'SEPT DUMP '!$O:$O,"Unreachable") -> 0 | K28: =COUNTIFS('SEPT DUMP '!$C:$C,'PARTNERS SUMMARY'!$B28,'SEPT DUMP '!$O:$O,"Postponed(Update Y)") -> 0 | L28: =SUM(AH28:BK28) -> 0 | M28: =IFERROR(L28/G28,0) -> 0 | O28: =COUNTIF('OCT DUMP'!$D:$D,'PARTNERS SUMMARY'!$B28) -> 1 | P28: =COUNTIFS('OCT DUMP'!$D:$D,'PARTNERS SUMMARY'!$B28,'OCT DUMP'!Q:Q,"Prospect") -> 0 | Q28: =COUNTIFS('OCT DUMP'!$D:$D,'PARTNERS SUMMARY'!$B28,'OCT DUMP'!$Q:$Q,"Confirmed") -> 1 | R28: =COUNTIFS('OCT DUMP'!$D:$D,'PARTNERS SUMMARY'!$B28,'OCT DUMP'!$Q:$Q,"Rejected") -> 0 | S28: =COUNTIFS('OCT DUMP'!$D:$D,'PARTNERS SUMMARY'!$B28,'OCT DUMP'!$Q:$Q,"Unreachable") -> 0 | T28: =COUNTIFS('OCT DUMP'!$D:$D,'PARTNERS SUMMARY'!$B28,'OCT DUMP'!$Q:$Q,"Postponed(Update Y)") -> 0 | U28: =SUM(BL28:CP28) -> 1 | V28: =IFERROR(U28/O28,0) -> 1 | X28: =COUNTIF('NOV DUMP'!C:C,'PARTNERS SUMMARY'!$B28) -> 7 | Y28: =COUNTIFS('NOV DUMP'!$C:$C,'PARTNERS SUMMARY'!$B28,'NOV DUMP'!$S:$S,"Prospect") -> 0 | Z28: =COUNTIFS('NOV DUMP'!$C:$C,'PARTNERS SUMMARY'!$B28,'NOV DUMP'!$S:$S,"Confirmed") -> 0 | AA28: =COUNTIFS('NOV DUMP'!$C:$C,'PARTNERS SUMMARY'!$B28,'NOV DUMP'!$S:$S,"Rejected") -> 0 | AB28: =COUNTIFS('NOV DUMP'!$C:$C,'PARTNERS SUMMARY'!$B28,'NOV DUMP'!$S:$S,"Unreachable") -> 0 | AC28: =COUNTIFS('NOV DUMP'!$C:$C,'PARTNERS SUMMARY'!$B28,'NOV DUMP'!$S:$S,"Postponed(Update Y)") -> 0 | AD28: =SUM(CQ28:DT28) -> 4 | AE28: =COUNTIFS('ACTIVATED LEADS '!$H:$H,'PARTNERS SUMMARY'!$B28,'ACTIVATED LEADS '!$K:$K,'PARTNERS SUMMARY'!$AE$2,'ACTIVATED LEADS '!$C:$C,"16") -> 4 | AF28: =IFERROR(AD28/X28,0) -> 0.57142857 | AH28: =COUNTIFS('ACTIVATED LEADS '!$H:$H,$B28,'ACTIVATED LEADS '!$D:$D,'PARTNERS SUMMARY'!AH$3) -> 0 | AI28: =COUNTIFS('ACTIVATED LEADS '!$H:$H,$B28,'ACTIVATED LEADS '!$D:$D,'PARTNERS SUMMARY'!AI$3) -> 0 | AJ28: =COUNTIFS('ACTIVATED LEADS '!$H:$H,$B28,'ACTIVATED LEADS '!$D:$D,'PARTNERS SUMMARY'!AJ$3) -> 0 | AK28: =COUNTIFS('ACTIVATED LEADS '!$H:$H,$B28,'ACTIVATED LEADS '!$D:$D,'PARTNERS SUMMARY'!AK$3) -> 0 | AL28: =COUNTIFS('ACTIVATED LEADS '!$H:$H,$B28,'ACTIVATED LEADS '!$D:$D,'PARTNERS SUMMARY'!AL$3) -> 0 | AM28: =COUNTIFS('ACTIVATED LEADS '!$H:$H,$B28,'ACTIVATED LEADS '!$D:$D,'PARTNERS SUMMARY'!AM$3) -> 0 | AN28: =COUNTIFS('ACTIVATED LEADS '!$H:$H,$B28,'ACTIVATED LEADS '!$D:$D,'PARTNERS SUMMARY'!AN$3) -> 0 | AO28: =COUNTIFS('ACTIVATED LEADS '!$H:$H,$B28,'ACTIVATED LEADS '!$D:$D,'PARTNERS SUMMARY'!AO$3) -> 0 | ... DO28: =COUNTIFS('ACTIVATED LEADS '!$H:$H,$B28,'ACTIVATED LEADS '!$D:$D,'PARTNERS SUMMARY'!DO$3) -> 0
A29: Damaris Mainga | B29: BLUEDAH SOLUTION | C29: 108611722 | E29: Utawala | F29: Nairobi | G29: =COUNTIF('SEPT DUMP '!$C:$C,'PARTNERS SUMMARY'!$B29) -> 0 | H29: =COUNTIFS('SEPT DUMP '!$C:$C,'PARTNERS SUMMARY'!$B29,'SEPT DUMP '!$O:$O,"Confirmed") -> 0 | I29: =COUNTIFS('SEPT DUMP '!$C:$C,'PARTNERS SUMMARY'!$B29,'SEPT DUMP '!$O:$O,"Rejected") -> 0 | J29: =COUNTIFS('SEPT DUMP '!$C:$C,'PARTNERS SUMMARY'!$B29,'SEPT DUMP '!$O:$O,"Unreachable") -> 0 | K29: =COUNTIFS('SEPT DUMP '!$C:$C,'PARTNERS SUMMARY'!$B29,'SEPT DUMP '!$O:$O,"Postponed(Update Y)") -> 0 | L29: =SUM(AH29:BK29) -> 0 | M29: =IFERROR(L29/G29,0) -> 0 | O29: =COUNTIF('OCT DUMP'!$D:$D,'PARTNERS SUMMARY'!$B29) -> 0 | P29: =COUNTIFS('OCT DUMP'!$D:$D,'PARTNERS SUMMARY'!$B29,'OCT DUMP'!Q:Q,"Prospect") -> 0 | Q29: =COUNTIFS('OCT DUMP'!$D:$D,'PARTNERS SUMMARY'!$B29,'OCT DUMP'!$Q:$Q,"Confirmed") -> 0 | R29: =COUNTIFS('OCT DUMP'!$D:$D,'PARTNERS SUMMARY'!$B29,'OCT DUMP'!$Q:$Q,"Rejected") -> 0 | S29: =COUNTIFS('OCT DUMP'!$D:$D,'PARTNERS SUMMARY'!$B29,'OCT DUMP'!$Q:$Q,"Unreachable") -> 0 | T29: =COUNTIFS('OCT DUMP'!$D:$D,'PARTNERS SUMMARY'!$B29,'OCT DUMP'!$Q:$Q,"Postponed(Update Y)") -> 0 | U29: =SUM(BL29:CP29) -> 0 | V29: =IFERROR(U29/O29,0) -> 0 | X29: =COUNTIF('NOV DUMP'!C:C,'PARTNERS SUMMARY'!$B29) -> 0 | Y29: =COUNTIFS('NOV DUMP'!$C:$C,'PARTNERS SUMMARY'!$B29,'NOV DUMP'!$S:$S,"Prospect") -> 0 | Z29: =COUNTIFS('NOV DUMP'!$C:$C,'PARTNERS SUMMARY'!$B29,'NOV DUMP'!$S:$S,"Confirmed") -> 0 | AA29: =COUNTIFS('NOV DUMP'!$C:$C,'PARTNERS SUMMARY'!$B29,'NOV DUMP'!$S:$S,"Rejected") -> 0 | AB29: =COUNTIFS('NOV DUMP'!$C:$C,'PARTNERS SUMMARY'!$B29,'NOV DUMP'!$S:$S,"Unreachable") -> 0 | AC29: =COUNTIFS('NOV DUMP'!$C:$C,'PARTNERS SUMMARY'!$B29,'NOV DUMP'!$S:$S,"Postponed(Update Y)") -> 0 | AD29: =SUM(CQ29:DT29) -> 0 | AE29: =COUNTIFS('ACTIVATED LEADS '!$H:$H,'PARTNERS SUMMARY'!$B29,'ACTIVATED LEADS '!$K:$K,'PARTNERS SUMMARY'!$AE$2,'ACTIVATED LEADS '!$C:$C,"16") -> 0 | AF29: =IFERROR(AD29/X29,0) -> 0 | AH29: =COUNTIFS('ACTIVATED LEADS '!$H:$H,$B29,'ACTIVATED LEADS '!$D:$D,'PARTNERS SUMMARY'!AH$3) -> 0 | AI29: =COUNTIFS('ACTIVATED LEADS '!$H:$H,$B29,'ACTIVATED LEADS '!$D:$D,'PARTNERS SUMMARY'!AI$3) -> 0 | AJ29: =COUNTIFS('ACTIVATED LEADS '!$H:$H,$B29,'ACTIVATED LEADS '!$D:$D,'PARTNERS SUMMARY'!AJ$3) -> 0 | AK29: =COUNTIFS('ACTIVATED LEADS '!$H:$H,$B29,'ACTIVATED LEADS '!$D:$D,'PARTNERS SUMMARY'!AK$3) -> 0 | AL29: =COUNTIFS('ACTIVATED LEADS '!$H:$H,$B29,'ACTIVATED LEADS '!$D:$D,'PARTNERS SUMMARY'!AL$3) -> 0 | AM29: =COUNTIFS('ACTIVATED LEADS '!$H:$H,$B29,'ACTIVATED LEADS '!$D:$D,'PARTNERS SUMMARY'!AM$3) -> 0 | AN29: =COUNTIFS('ACTIVATED LEADS '!$H:$H,$B29,'ACTIVATED LEADS '!$D:$D,'PARTNERS SUMMARY'!AN$3) -> 0 | AO29: =COUNTIFS('ACTIVATED LEADS '!$H:$H,$B29,'ACTIVATED LEADS '!$D:$D,'PARTNERS SUMMARY'!AO$3) -> 0 | ... DO29: =COUNTIFS('ACTIVATED LEADS '!$H:$H,$B29,'ACTIVATED LEADS '!$D:$D,'PARTNERS SUMMARY'!DO$3) -> 0
A30: Damaris Mainga | B30: DIGNITY TRADERS | E30: Nairobi CBD | F30: Nairobi | G30: =COUNTIF('SEPT DUMP '!$C:$C,'PARTNERS SUMMARY'!$B30) -> 0 | H30: =COUNTIFS('SEPT DUMP '!$C:$C,'PARTNERS SUMMARY'!$B30,'SEPT DUMP '!$O:$O,"Confirmed") -> 0 | I30: =COUNTIFS('SEPT DUMP '!$C:$C,'PARTNERS SUMMARY'!$B30,'SEPT DUMP '!$O:$O,"Rejected") -> 0 | J30: =COUNTIFS('SEPT DUMP '!$C:$C,'PARTNERS SUMMARY'!$B30,'SEPT DUMP '!$O:$O,"Unreachable") -> 0 | K30: =COUNTIFS('SEPT DUMP '!$C:$C,'PARTNERS SUMMARY'!$B30,'SEPT DUMP '!$O:$O,"Postponed(Update Y)") -> 0 | L30: =SUM(AH30:BK30) -> 0 | M30: =IFERROR(L30/G30,0) -> 0 | O30: =COUNTIF('OCT DUMP'!$D:$D,'PARTNERS SUMMARY'!$B30) -> 0 | P30: =COUNTIFS('OCT DUMP'!$D:$D,'PARTNERS SUMMARY'!$B30,'OCT DUMP'!Q:Q,"Prospect") -> 0 | Q30: =COUNTIFS('OCT DUMP'!$D:$D,'PARTNERS SUMMARY'!$B30,'OCT DUMP'!$Q:$Q,"Confirmed") -> 0 | R30: =COUNTIFS('OCT DUMP'!$D:$D,'PARTNERS SUMMARY'!$B30,'OCT DUMP'!$Q:$Q,"Rejected") -> 0 | S30: =COUNTIFS('OCT DUMP'!$D:$D,'PARTNERS SUMMARY'!$B30,'OCT DUMP'!$Q:$Q,"Unreachable") -> 0 | T30: =COUNTIFS('OCT DUMP'!$D:$D,'PARTNERS SUMMARY'!$B30,'OCT DUMP'!$Q:$Q,"Postponed(Update Y)") -> 0 | U30: =SUM(BL30:CP30) -> 0 | V30: =IFERROR(U30/O30,0) -> 0 | X30: =COUNTIF('NOV DUMP'!C:C,'PARTNERS SUMMARY'!$B30) -> 0 | Y30: =COUNTIFS('NOV DUMP'!$C:$C,'PARTNERS SUMMARY'!$B30,'NOV DUMP'!$S:$S,"Prospect") -> 0 | Z30: =COUNTIFS('NOV DUMP'!$C:$C,'PARTNERS SUMMARY'!$B30,'NOV DUMP'!$S:$S,"Confirmed") -> 0 | AA30: =COUNTIFS('NOV DUMP'!$C:$C,'PARTNERS SUMMARY'!$B30,'NOV DUMP'!$S:$S,"Rejected") -> 0 | AB30: =COUNTIFS('NOV DUMP'!$C:$C,'PARTNERS SUMMARY'!$B30,'NOV DUMP'!$S:$S,"Unreachable") -> 0 | AC30: =COUNTIFS('NOV DUMP'!$C:$C,'PARTNERS SUMMARY'!$B30,'NOV DUMP'!$S:$S,"Postponed(Update Y)") -> 0 | AD30: =SUM(CQ30:DT30) -> 0 | AE30: =COUNTIFS('ACTIVATED LEADS '!$H:$H,'PARTNERS SUMMARY'!$B30,'ACTIVATED LEADS '!$K:$K,'PARTNERS SUMMARY'!$AE$2,'ACTIVATED LEADS '!$C:$C,"16") -> 0 | AF30: =IFERROR(AD30/X30,0) -> 0 | AH30: =COUNTIFS('ACTIVATED LEADS '!$H:$H,$B30,'ACTIVATED LEADS '!$D:$D,'PARTNERS SUMMARY'!AH$3) -> 0 | AI30: =COUNTIFS('ACTIVATED LEADS '!$H:$H,$B30,'ACTIVATED LEADS '!$D:$D,'PARTNERS SUMMARY'!AI$3) -> 0 | AJ30: =COUNTIFS('ACTIVATED LEADS '!$H:$H,$B30,'ACTIVATED LEADS '!$D:$D,'PARTNERS SUMMARY'!AJ$3) -> 0 | AK30: =COUNTIFS('ACTIVATED LEADS '!$H:$H,$B30,'ACTIVATED LEADS '!$D:$D,'PARTNERS SUMMARY'!AK$3) -> 0 | AL30: =COUNTIFS('ACTIVATED LEADS '!$H:$H,$B30,'ACTIVATED LEADS '!$D:$D,'PARTNERS SUMMARY'!AL$3) -> 0 | AM30: =COUNTIFS('ACTIVATED LEADS '!$H:$H,$B30,'ACTIVATED LEADS '!$D:$D,'PARTNERS SUMMARY'!AM$3) -> 0 | AN30: =COUNTIFS('ACTIVATED LEADS '!$H:$H,$B30,'ACTIVATED LEADS '!$D:$D,'PARTNERS SUMMARY'!AN$3) -> 0 | AO30: =COUNTIFS('ACTIVATED LEADS '!$H:$H,$B30,'ACTIVATED LEADS '!$D:$D,'PARTNERS SUMMARY'!AO$3) -> 0 | ... DO30: =COUNTIFS('ACTIVATED LEADS '!$H:$H,$B30,'ACTIVATED LEADS '!$D:$D,'PARTNERS SUMMARY'!DO$3) -> 0
A31: Mariana Hongo | B31: ALIM COMMUNICATIONS | C31: 105148076 | E31: Nairobi | F31: Nairobi | G31: =COUNTIF('SEPT DUMP '!$C:$C,'PARTNERS SUMMARY'!$B31) -> 0 | H31: =COUNTIFS('SEPT DUMP '!$C:$C,'PARTNERS SUMMARY'!$B31,'SEPT DUMP '!$O:$O,"Confirmed") -> 0 | I31: =COUNTIFS('SEPT DUMP '!$C:$C,'PARTNERS SUMMARY'!$B31,'SEPT DUMP '!$O:$O,"Rejected") -> 0 | J31: =COUNTIFS('SEPT DUMP '!$C:$C,'PARTNERS SUMMARY'!$B31,'SEPT DUMP '!$O:$O,"Unreachable") -> 0 | K31: =COUNTIFS('SEPT DUMP '!$C:$C,'PARTNERS SUMMARY'!$B31,'SEPT DUMP '!$O:$O,"Postponed(Update Y)") -> 0 | L31: =SUM(AH31:BK31) -> 0 | M31: =IFERROR(L31/G31,0) -> 0 | O31: =COUNTIF('OCT DUMP'!$D:$D,'PARTNERS SUMMARY'!$B31) -> 0 | P31: =COUNTIFS('OCT DUMP'!$D:$D,'PARTNERS SUMMARY'!$B31,'OCT DUMP'!Q:Q,"Prospect") -> 0 | Q31: =COUNTIFS('OCT DUMP'!$D:$D,'PARTNERS SUMMARY'!$B31,'OCT DUMP'!$Q:$Q,"Confirmed") -> 0 | R31: =COUNTIFS('OCT DUMP'!$D:$D,'PARTNERS SUMMARY'!$B31,'OCT DUMP'!$Q:$Q,"Rejected") -> 0 | S31: =COUNTIFS('OCT DUMP'!$D:$D,'PARTNERS SUMMARY'!$B31,'OCT DUMP'!$Q:$Q,"Unreachable") -> 0 | T31: =COUNTIFS('OCT DUMP'!$D:$D,'PARTNERS SUMMARY'!$B31,'OCT DUMP'!$Q:$Q,"Postponed(Update Y)") -> 0 | U31: =SUM(BL31:CP31) -> 0 | V31: =IFERROR(U31/O31,0) -> 0 | X31: =COUNTIF('NOV DUMP'!C:C,'PARTNERS SUMMARY'!$B31) -> 0 | Y31: =COUNTIFS('NOV DUMP'!$C:$C,'PARTNERS SUMMARY'!$B31,'NOV DUMP'!$S:$S,"Prospect") -> 0 | Z31: =COUNTIFS('NOV DUMP'!$C:$C,'PARTNERS SUMMARY'!$B31,'NOV DUMP'!$S:$S,"Confirmed") -> 0 | AA31: =COUNTIFS('NOV DUMP'!$C:$C,'PARTNERS SUMMARY'!$B31,'NOV DUMP'!$S:$S,"Rejected") -> 0 | AB31: =COUNTIFS('NOV DUMP'!$C:$C,'PARTNERS SUMMARY'!$B31,'NOV DUMP'!$S:$S,"Unreachable") -> 0 | AC31: =COUNTIFS('NOV DUMP'!$C:$C,'PARTNERS SUMMARY'!$B31,'NOV DUMP'!$S:$S,"Postponed(Update Y)") -> 0 | AD31: =SUM(CQ31:DT31) -> 0 | AE31: =COUNTIFS('ACTIVATED LEADS '!$H:$H,'PARTNERS SUMMARY'!$B31,'ACTIVATED LEADS '!$K:$K,'PARTNERS SUMMARY'!$AE$2,'ACTIVATED LEADS '!$C:$C,"16") -> 0 | AF31: =IFERROR(AD31/X31,0) -> 0 | AH31: =COUNTIFS('ACTIVATED LEADS '!$H:$H,$B31,'ACTIVATED LEADS '!$D:$D,'PARTNERS SUMMARY'!AH$3) -> 0 | AI31: =COUNTIFS('ACTIVATED LEADS '!$H:$H,$B31,'ACTIVATED LEADS '!$D:$D,'PARTNERS SUMMARY'!AI$3) -> 0 | AJ31: =COUNTIFS('ACTIVATED LEADS '!$H:$H,$B31,'ACTIVATED LEADS '!$D:$D,'PARTNERS SUMMARY'!AJ$3) -> 0 | AK31: =COUNTIFS('ACTIVATED LEADS '!$H:$H,$B31,'ACTIVATED LEADS '!$D:$D,'PARTNERS SUMMARY'!AK$3) -> 0 | AL31: =COUNTIFS('ACTIVATED LEADS '!$H:$H,$B31,'ACTIVATED LEADS '!$D:$D,'PARTNERS SUMMARY'!AL$3) -> 0 | AM31: =COUNTIFS('ACTIVATED LEADS '!$H:$H,$B31,'ACTIVATED LEADS '!$D:$D,'PARTNERS SUMMARY'!AM$3) -> 0 | AN31: =COUNTIFS('ACTIVATED LEADS '!$H:$H,$B31,'ACTIVATED LEADS '!$D:$D,'PARTNERS SUMMARY'!AN$3) -> 0 | AO31: =COUNTIFS('ACTIVATED LEADS '!$H:$H,$B31,'ACTIVATED LEADS '!$D:$D,'PARTNERS SUMMARY'!AO$3) -> 0 | ... DO31: =COUNTIFS('ACTIVATED LEADS '!$H:$H,$B31,'ACTIVATED LEADS '!$D:$D,'PARTNERS SUMMARY'!DO$3) -> 0
A32: Brian Odero | B32: BEYOND DEALS ENTERPRISES | C32: 784312517 | E32: adams arcade | F32: Nairobi | G32: =COUNTIF('SEPT DUMP '!$C:$C,'PARTNERS SUMMARY'!$B32) -> 0 | H32: =COUNTIFS('SEPT DUMP '!$C:$C,'PARTNERS SUMMARY'!$B32,'SEPT DUMP '!$O:$O,"Confirmed") -> 0 | I32: =COUNTIFS('SEPT DUMP '!$C:$C,'PARTNERS SUMMARY'!$B32,'SEPT DUMP '!$O:$O,"Rejected") -> 0 | J32: =COUNTIFS('SEPT DUMP '!$C:$C,'PARTNERS SUMMARY'!$B32,'SEPT DUMP '!$O:$O,"Unreachable") -> 0 | K32: =COUNTIFS('SEPT DUMP '!$C:$C,'PARTNERS SUMMARY'!$B32,'SEPT DUMP '!$O:$O,"Postponed(Update Y)") -> 0 | L32: =SUM(AH32:BK32) -> 0 | M32: =IFERROR(L32/G32,0) -> 0 | O32: =COUNTIF('OCT DUMP'!$D:$D,'PARTNERS SUMMARY'!$B32) -> 0 | P32: =COUNTIFS('OCT DUMP'!$D:$D,'PARTNERS SUMMARY'!$B32,'OCT DUMP'!Q:Q,"Prospect") -> 0 | Q32: =COUNTIFS('OCT DUMP'!$D:$D,'PARTNERS SUMMARY'!$B32,'OCT DUMP'!$Q:$Q,"Confirmed") -> 0 | R32: =COUNTIFS('OCT DUMP'!$D:$D,'PARTNERS SUMMARY'!$B32,'OCT DUMP'!$Q:$Q,"Rejected") -> 0 | S32: =COUNTIFS('OCT DUMP'!$D:$D,'PARTNERS SUMMARY'!$B32,'OCT DUMP'!$Q:$Q,"Unreachable") -> 0 | T32: =COUNTIFS('OCT DUMP'!$D:$D,'PARTNERS SUMMARY'!$B32,'OCT DUMP'!$Q:$Q,"Postponed(Update Y)") -> 0 | U32: =SUM(BL32:CP32) -> 0 | V32: =IFERROR(U32/O32,0) -> 0 | X32: =COUNTIF('NOV DUMP'!C:C,'PARTNERS SUMMARY'!$B32) -> 0 | Y32: =COUNTIFS('NOV DUMP'!$C:$C,'PARTNERS SUMMARY'!$B32,'NOV DUMP'!$S:$S,"Prospect") -> 0 | Z32: =COUNTIFS('NOV DUMP'!$C:$C,'PARTNERS SUMMARY'!$B32,'NOV DUMP'!$S:$S,"Confirmed") -> 0 | AA32: =COUNTIFS('NOV DUMP'!$C:$C,'PARTNERS SUMMARY'!$B32,'NOV DUMP'!$S:$S,"Rejected") -> 0 | AB32: =COUNTIFS('NOV DUMP'!$C:$C,'PARTNERS SUMMARY'!$B32,'NOV DUMP'!$S:$S,"Unreachable") -> 0 | AC32: =COUNTIFS('NOV DUMP'!$C:$C,'PARTNERS SUMMARY'!$B32,'NOV DUMP'!$S:$S,"Postponed(Update Y)") -> 0 | AD32: =SUM(CQ32:DT32) -> 0 | AE32: =COUNTIFS('ACTIVATED LEADS '!$H:$H,'PARTNERS SUMMARY'!$B32,'ACTIVATED LEADS '!$K:$K,'PARTNERS SUMMARY'!$AE$2,'ACTIVATED LEADS '!$C:$C,"16") -> 0 | AF32: =IFERROR(AD32/X32,0) -> 0 | AH32: =COUNTIFS('ACTIVATED LEADS '!$H:$H,$B32,'ACTIVATED LEADS '!$D:$D,'PARTNERS SUMMARY'!AH$3) -> 0 | AI32: =COUNTIFS('ACTIVATED LEADS '!$H:$H,$B32,'ACTIVATED LEADS '!$D:$D,'PARTNERS SUMMARY'!AI$3) -> 0 | AJ32: =COUNTIFS('ACTIVATED LEADS '!$H:$H,$B32,'ACTIVATED LEADS '!$D:$D,'PARTNERS SUMMARY'!AJ$3) -> 0 | AK32: =COUNTIFS('ACTIVATED LEADS '!$H:$H,$B32,'ACTIVATED LEADS '!$D:$D,'PARTNERS SUMMARY'!AK$3) -> 0 | AL32: =COUNTIFS('ACTIVATED LEADS '!$H:$H,$B32,'ACTIVATED LEADS '!$D:$D,'PARTNERS SUMMARY'!AL$3) -> 0 | AM32: =COUNTIFS('ACTIVATED LEADS '!$H:$H,$B32,'ACTIVATED LEADS '!$D:$D,'PARTNERS SUMMARY'!AM$3) -> 0 | AN32: =COUNTIFS('ACTIVATED LEADS '!$H:$H,$B32,'ACTIVATED LEADS '!$D:$D,'PARTNERS SUMMARY'!AN$3) -> 0 | AO32: =COUNTIFS('ACTIVATED LEADS '!$H:$H,$B32,'ACTIVATED LEADS '!$D:$D,'PARTNERS SUMMARY'!AO$3) -> 0 | ... DO32: =COUNTIFS('ACTIVATED LEADS '!$H:$H,$B32,'ACTIVATED LEADS '!$D:$D,'PARTNERS SUMMARY'!DO$3) -> 0
A33: Damaris Mainga | B33: ONFON MEDIA LIMITED | C33: 107345420 | E33: Cabanas | F33: Nairobi | G33: =COUNTIF('SEPT DUMP '!$C:$C,'PARTNERS SUMMARY'!$B33) -> 0 | H33: =COUNTIFS('SEPT DUMP '!$C:$C,'PARTNERS SUMMARY'!$B33,'SEPT DUMP '!$O:$O,"Confirmed") -> 0 | I33: =COUNTIFS('SEPT DUMP '!$C:$C,'PARTNERS SUMMARY'!$B33,'SEPT DUMP '!$O:$O,"Rejected") -> 0 | J33: =COUNTIFS('SEPT DUMP '!$C:$C,'PARTNERS SUMMARY'!$B33,'SEPT DUMP '!$O:$O,"Unreachable") -> 0 | K33: =COUNTIFS('SEPT DUMP '!$C:$C,'PARTNERS SUMMARY'!$B33,'SEPT DUMP '!$O:$O,"Postponed(Update Y)") -> 0 | L33: =SUM(AH33:BK33) -> 0 | M33: =IFERROR(L33/G33,0) -> 0 | O33: =COUNTIF('OCT DUMP'!$D:$D,'PARTNERS SUMMARY'!$B33) -> 0 | P33: =COUNTIFS('OCT DUMP'!$D:$D,'PARTNERS SUMMARY'!$B33,'OCT DUMP'!Q:Q,"Prospect") -> 0 | Q33: =COUNTIFS('OCT DUMP'!$D:$D,'PARTNERS SUMMARY'!$B33,'OCT DUMP'!$Q:$Q,"Confirmed") -> 0 | R33: =COUNTIFS('OCT DUMP'!$D:$D,'PARTNERS SUMMARY'!$B33,'OCT DUMP'!$Q:$Q,"Rejected") -> 0 | S33: =COUNTIFS('OCT DUMP'!$D:$D,'PARTNERS SUMMARY'!$B33,'OCT DUMP'!$Q:$Q,"Unreachable") -> 0 | T33: =COUNTIFS('OCT DUMP'!$D:$D,'PARTNERS SUMMARY'!$B33,'OCT DUMP'!$Q:$Q,"Postponed(Update Y)") -> 0 | U33: =SUM(BL33:CP33) -> 0 | V33: =IFERROR(U33/O33,0) -> 0 | X33: =COUNTIF('NOV DUMP'!C:C,'PARTNERS SUMMARY'!$B33) -> 0 | Y33: =COUNTIFS('NOV DUMP'!$C:$C,'PARTNERS SUMMARY'!$B33,'NOV DUMP'!$S:$S,"Prospect") -> 0 | Z33: =COUNTIFS('NOV DUMP'!$C:$C,'PARTNERS SUMMARY'!$B33,'NOV DUMP'!$S:$S,"Confirmed") -> 0 | AA33: =COUNTIFS('NOV DUMP'!$C:$C,'PARTNERS SUMMARY'!$B33,'NOV DUMP'!$S:$S,"Rejected") -> 0 | AB33: =COUNTIFS('NOV DUMP'!$C:$C,'PARTNERS SUMMARY'!$B33,'NOV DUMP'!$S:$S,"Unreachable") -> 0 | AC33: =COUNTIFS('NOV DUMP'!$C:$C,'PARTNERS SUMMARY'!$B33,'NOV DUMP'!$S:$S,"Postponed(Update Y)") -> 0 | AD33: =SUM(CQ33:DT33) -> 0 | AE33: =COUNTIFS('ACTIVATED LEADS '!$H:$H,'PARTNERS SUMMARY'!$B33,'ACTIVATED LEADS '!$K:$K,'PARTNERS SUMMARY'!$AE$2,'ACTIVATED LEADS '!$C:$C,"16") -> 0 | AF33: =IFERROR(AD33/X33,0) -> 0 | AH33: =COUNTIFS('ACTIVATED LEADS '!$H:$H,$B33,'ACTIVATED LEADS '!$D:$D,'PARTNERS SUMMARY'!AH$3) -> 0 | AI33: =COUNTIFS('ACTIVATED LEADS '!$H:$H,$B33,'ACTIVATED LEADS '!$D:$D,'PARTNERS SUMMARY'!AI$3) -> 0 | AJ33: =COUNTIFS('ACTIVATED LEADS '!$H:$H,$B33,'ACTIVATED LEADS '!$D:$D,'PARTNERS SUMMARY'!AJ$3) -> 0 | AK33: =COUNTIFS('ACTIVATED LEADS '!$H:$H,$B33,'ACTIVATED LEADS '!$D:$D,'PARTNERS SUMMARY'!AK$3) -> 0 | AL33: =COUNTIFS('ACTIVATED LEADS '!$H:$H,$B33,'ACTIVATED LEADS '!$D:$D,'PARTNERS SUMMARY'!AL$3) -> 0 | AM33: =COUNTIFS('ACTIVATED LEADS '!$H:$H,$B33,'ACTIVATED LEADS '!$D:$D,'PARTNERS SUMMARY'!AM$3) -> 0 | AN33: =COUNTIFS('ACTIVATED LEADS '!$H:$H,$B33,'ACTIVATED LEADS '!$D:$D,'PARTNERS SUMMARY'!AN$3) -> 0 | AO33: =COUNTIFS('ACTIVATED LEADS '!$H:$H,$B33,'ACTIVATED LEADS '!$D:$D,'PARTNERS SUMMARY'!AO$3) -> 0 | ... DO33: =COUNTIFS('ACTIVATED LEADS '!$H:$H,$B33,'ACTIVATED LEADS '!$D:$D,'PARTNERS SUMMARY'!DO$3) -> 0
A34: Salome Sule | B34: JOECHARLIE ENTERPRISES | C34: 103335970 | E34: Voi | F34: Coast | G34: =COUNTIF('SEPT DUMP '!$C:$C,'PARTNERS SUMMARY'!$B34) -> 0 | H34: =COUNTIFS('SEPT DUMP '!$C:$C,'PARTNERS SUMMARY'!$B34,'SEPT DUMP '!$O:$O,"Confirmed") -> 0 | I34: =COUNTIFS('SEPT DUMP '!$C:$C,'PARTNERS SUMMARY'!$B34,'SEPT DUMP '!$O:$O,"Rejected") -> 0 | J34: =COUNTIFS('SEPT DUMP '!$C:$C,'PARTNERS SUMMARY'!$B34,'SEPT DUMP '!$O:$O,"Unreachable") -> 0 | K34: =COUNTIFS('SEPT DUMP '!$C:$C,'PARTNERS SUMMARY'!$B34,'SEPT DUMP '!$O:$O,"Postponed(Update Y)") -> 0 | L34: =SUM(AH34:BK34) -> 0 | M34: =IFERROR(L34/G34,0) -> 0 | O34: =COUNTIF('OCT DUMP'!$D:$D,'PARTNERS SUMMARY'!$B34) -> 0 | P34: =COUNTIFS('OCT DUMP'!$D:$D,'PARTNERS SUMMARY'!$B34,'OCT DUMP'!Q:Q,"Prospect") -> 0 | Q34: =COUNTIFS('OCT DUMP'!$D:$D,'PARTNERS SUMMARY'!$B34,'OCT DUMP'!$Q:$Q,"Confirmed") -> 0 | R34: =COUNTIFS('OCT DUMP'!$D:$D,'PARTNERS SUMMARY'!$B34,'OCT DUMP'!$Q:$Q,"Rejected") -> 0 | S34: =COUNTIFS('OCT DUMP'!$D:$D,'PARTNERS SUMMARY'!$B34,'OCT DUMP'!$Q:$Q,"Unreachable") -> 0 | T34: =COUNTIFS('OCT DUMP'!$D:$D,'PARTNERS SUMMARY'!$B34,'OCT DUMP'!$Q:$Q,"Postponed(Update Y)") -> 0 | U34: =SUM(BL34:CP34) -> 0 | V34: =IFERROR(U34/O34,0) -> 0 | X34: =COUNTIF('NOV DUMP'!C:C,'PARTNERS SUMMARY'!$B34) -> 7 | Y34: =COUNTIFS('NOV DUMP'!$C:$C,'PARTNERS SUMMARY'!$B34,'NOV DUMP'!$S:$S,"Prospect") -> 0 | Z34: =COUNTIFS('NOV DUMP'!$C:$C,'PARTNERS SUMMARY'!$B34,'NOV DUMP'!$S:$S,"Confirmed") -> 2 | AA34: =COUNTIFS('NOV DUMP'!$C:$C,'PARTNERS SUMMARY'!$B34,'NOV DUMP'!$S:$S,"Rejected") -> 0 | AB34: =COUNTIFS('NOV DUMP'!$C:$C,'PARTNERS SUMMARY'!$B34,'NOV DUMP'!$S:$S,"Unreachable") -> 0 | AC34: =COUNTIFS('NOV DUMP'!$C:$C,'PARTNERS SUMMARY'!$B34,'NOV DUMP'!$S:$S,"Postponed(Update Y)") -> 0 | AD34: =SUM(CQ34:DT34) -> 4 | AE34: =COUNTIFS('ACTIVATED LEADS '!$H:$H,'PARTNERS SUMMARY'!$B34,'ACTIVATED LEADS '!$K:$K,'PARTNERS SUMMARY'!$AE$2,'ACTIVATED LEADS '!$C:$C,"16") -> 3 | AF34: =IFERROR(AD34/X34,0) -> 0.57142857 | AH34: =COUNTIFS('ACTIVATED LEADS '!$H:$H,$B34,'ACTIVATED LEADS '!$D:$D,'PARTNERS SUMMARY'!AH$3) -> 0 | AI34: =COUNTIFS('ACTIVATED LEADS '!$H:$H,$B34,'ACTIVATED LEADS '!$D:$D,'PARTNERS SUMMARY'!AI$3) -> 0 | AJ34: =COUNTIFS('ACTIVATED LEADS '!$H:$H,$B34,'ACTIVATED LEADS '!$D:$D,'PARTNERS SUMMARY'!AJ$3) -> 0 | AK34: =COUNTIFS('ACTIVATED LEADS '!$H:$H,$B34,'ACTIVATED LEADS '!$D:$D,'PARTNERS SUMMARY'!AK$3) -> 0 | AL34: =COUNTIFS('ACTIVATED LEADS '!$H:$H,$B34,'ACTIVATED LEADS '!$D:$D,'PARTNERS SUMMARY'!AL$3) -> 0 | AM34: =COUNTIFS('ACTIVATED LEADS '!$H:$H,$B34,'ACTIVATED LEADS '!$D:$D,'PARTNERS SUMMARY'!AM$3) -> 0 | AN34: =COUNTIFS('ACTIVATED LEADS '!$H:$H,$B34,'ACTIVATED LEADS '!$D:$D,'PARTNERS SUMMARY'!AN$3) -> 0 | AO34: =COUNTIFS('ACTIVATED LEADS '!$H:$H,$B34,'ACTIVATED LEADS '!$D:$D,'PARTNERS SUMMARY'!AO$3) -> 0 | ... DO34: =COUNTIFS('ACTIVATED LEADS '!$H:$H,$B34,'ACTIVATED LEADS '!$D:$D,'PARTNERS SUMMARY'!DO$3) -> 1
A35: Salome Sule | B35: SEGO COMMUNICATIONS | C35: 785912466 | E35: Likoni | F35: Coast | G35: =COUNTIF('SEPT DUMP '!$C:$C,'PARTNERS SUMMARY'!$B35) -> 0 | H35: =COUNTIFS('SEPT DUMP '!$C:$C,'PARTNERS SUMMARY'!$B35,'SEPT DUMP '!$O:$O,"Confirmed") -> 0 | I35: =COUNTIFS('SEPT DUMP '!$C:$C,'PARTNERS SUMMARY'!$B35,'SEPT DUMP '!$O:$O,"Rejected") -> 0 | J35: =COUNTIFS('SEPT DUMP '!$C:$C,'PARTNERS SUMMARY'!$B35,'SEPT DUMP '!$O:$O,"Unreachable") -> 0 | K35: =COUNTIFS('SEPT DUMP '!$C:$C,'PARTNERS SUMMARY'!$B35,'SEPT DUMP '!$O:$O,"Postponed(Update Y)") -> 0 | L35: =SUM(AH35:BK35) -> 0 | M35: =IFERROR(L35/G35,0) -> 0 | O35: =COUNTIF('OCT DUMP'!$D:$D,'PARTNERS SUMMARY'!$B35) -> 0 | P35: =COUNTIFS('OCT DUMP'!$D:$D,'PARTNERS SUMMARY'!$B35,'OCT DUMP'!Q:Q,"Prospect") -> 0 | Q35: =COUNTIFS('OCT DUMP'!$D:$D,'PARTNERS SUMMARY'!$B35,'OCT DUMP'!$Q:$Q,"Confirmed") -> 0 | R35: =COUNTIFS('OCT DUMP'!$D:$D,'PARTNERS SUMMARY'!$B35,'OCT DUMP'!$Q:$Q,"Rejected") -> 0 | S35: =COUNTIFS('OCT DUMP'!$D:$D,'PARTNERS SUMMARY'!$B35,'OCT DUMP'!$Q:$Q,"Unreachable") -> 0 | T35: =COUNTIFS('OCT DUMP'!$D:$D,'PARTNERS SUMMARY'!$B35,'OCT DUMP'!$Q:$Q,"Postponed(Update Y)") -> 0 | U35: =SUM(BL35:CP35) -> 0 | V35: =IFERROR(U35/O35,0) -> 0 | X35: =COUNTIF('NOV DUMP'!C:C,'PARTNERS SUMMARY'!$B35) -> 8 | Y35: =COUNTIFS('NOV DUMP'!$C:$C,'PARTNERS SUMMARY'!$B35,'NOV DUMP'!$S:$S,"Prospect") -> 0 | Z35: =COUNTIFS('NOV DUMP'!$C:$C,'PARTNERS SUMMARY'!$B35,'NOV DUMP'!$S:$S,"Confirmed") -> 3 | AA35: =COUNTIFS('NOV DUMP'!$C:$C,'PARTNERS SUMMARY'!$B35,'NOV DUMP'!$S:$S,"Rejected") -> 0 | AB35: =COUNTIFS('NOV DUMP'!$C:$C,'PARTNERS SUMMARY'!$B35,'NOV DUMP'!$S:$S,"Unreachable") -> 0 | AC35: =COUNTIFS('NOV DUMP'!$C:$C,'PARTNERS SUMMARY'!$B35,'NOV DUMP'!$S:$S,"Postponed(Update Y)") -> 0 | AD35: =SUM(CQ35:DT35) -> 4 | AE35: =COUNTIFS('ACTIVATED LEADS '!$H:$H,'PARTNERS SUMMARY'!$B35,'ACTIVATED LEADS '!$K:$K,'PARTNERS SUMMARY'!$AE$2,'ACTIVATED LEADS '!$C:$C,"16") -> 2 | AF35: =IFERROR(AD35/X35,0) -> 0.5 | AH35: =COUNTIFS('ACTIVATED LEADS '!$H:$H,$B35,'ACTIVATED LEADS '!$D:$D,'PARTNERS SUMMARY'!AH$3) -> 0 | AI35: =COUNTIFS('ACTIVATED LEADS '!$H:$H,$B35,'ACTIVATED LEADS '!$D:$D,'PARTNERS SUMMARY'!AI$3) -> 0 | AJ35: =COUNTIFS('ACTIVATED LEADS '!$H:$H,$B35,'ACTIVATED LEADS '!$D:$D,'PARTNERS SUMMARY'!AJ$3) -> 0 | AK35: =COUNTIFS('ACTIVATED LEADS '!$H:$H,$B35,'ACTIVATED LEADS '!$D:$D,'PARTNERS SUMMARY'!AK$3) -> 0 | AL35: =COUNTIFS('ACTIVATED LEADS '!$H:$H,$B35,'ACTIVATED LEADS '!$D:$D,'PARTNERS SUMMARY'!AL$3) -> 0 | AM35: =COUNTIFS('ACTIVATED LEADS '!$H:$H,$B35,'ACTIVATED LEADS '!$D:$D,'PARTNERS SUMMARY'!AM$3) -> 0 | AN35: =COUNTIFS('ACTIVATED LEADS '!$H:$H,$B35,'ACTIVATED LEADS '!$D:$D,'PARTNERS SUMMARY'!AN$3) -> 0 | AO35: =COUNTIFS('ACTIVATED LEADS '!$H:$H,$B35,'ACTIVATED LEADS '!$D:$D,'PARTNERS SUMMARY'!AO$3) -> 0 | ... DO35: =COUNTIFS('ACTIVATED LEADS '!$H:$H,$B35,'ACTIVATED LEADS '!$D:$D,'PARTNERS SUMMARY'!DO$3) -> 0
A36: Damaris Mainga | B36: CROWNET SOLUTIONS | E36: Thika road | F36: Nairobi | G36: =COUNTIF('SEPT DUMP '!$C:$C,'PARTNERS SUMMARY'!$B36) -> 0 | H36: =COUNTIFS('SEPT DUMP '!$C:$C,'PARTNERS SUMMARY'!$B36,'SEPT DUMP '!$O:$O,"Confirmed") -> 0 | I36: =COUNTIFS('SEPT DUMP '!$C:$C,'PARTNERS SUMMARY'!$B36,'SEPT DUMP '!$O:$O,"Rejected") -> 0 | J36: =COUNTIFS('SEPT DUMP '!$C:$C,'PARTNERS SUMMARY'!$B36,'SEPT DUMP '!$O:$O,"Unreachable") -> 0 | K36: =COUNTIFS('SEPT DUMP '!$C:$C,'PARTNERS SUMMARY'!$B36,'SEPT DUMP '!$O:$O,"Postponed(Update Y)") -> 0 | L36: =SUM(AH36:BK36) -> 0 | M36: =IFERROR(L36/G36,0) -> 0 | O36: =COUNTIF('OCT DUMP'!$D:$D,'PARTNERS SUMMARY'!$B36) -> 0 | P36: =COUNTIFS('OCT DUMP'!$D:$D,'PARTNERS SUMMARY'!$B36,'OCT DUMP'!Q:Q,"Prospect") -> 0 | Q36: =COUNTIFS('OCT DUMP'!$D:$D,'PARTNERS SUMMARY'!$B36,'OCT DUMP'!$Q:$Q,"Confirmed") -> 0 | R36: =COUNTIFS('OCT DUMP'!$D:$D,'PARTNERS SUMMARY'!$B36,'OCT DUMP'!$Q:$Q,"Rejected") -> 0 | S36: =COUNTIFS('OCT DUMP'!$D:$D,'PARTNERS SUMMARY'!$B36,'OCT DUMP'!$Q:$Q,"Unreachable") -> 0 | T36: =COUNTIFS('OCT DUMP'!$D:$D,'PARTNERS SUMMARY'!$B36,'OCT DUMP'!$Q:$Q,"Postponed(Update Y)") -> 0 | U36: =SUM(BL36:CP36) -> 0 | V36: =IFERROR(U36/O36,0) -> 0 | X36: =COUNTIF('NOV DUMP'!C:C,'PARTNERS SUMMARY'!$B36) -> 0 | Y36: =COUNTIFS('NOV DUMP'!$C:$C,'PARTNERS SUMMARY'!$B36,'NOV DUMP'!$S:$S,"Prospect") -> 0 | Z36: =COUNTIFS('NOV DUMP'!$C:$C,'PARTNERS SUMMARY'!$B36,'NOV DUMP'!$S:$S,"Confirmed") -> 0 | AA36: =COUNTIFS('NOV DUMP'!$C:$C,'PARTNERS SUMMARY'!$B36,'NOV DUMP'!$S:$S,"Rejected") -> 0 | AB36: =COUNTIFS('NOV DUMP'!$C:$C,'PARTNERS SUMMARY'!$B36,'NOV DUMP'!$S:$S,"Unreachable") -> 0 | AC36: =COUNTIFS('NOV DUMP'!$C:$C,'PARTNERS SUMMARY'!$B36,'NOV DUMP'!$S:$S,"Postponed(Update Y)") -> 0 | AD36: =SUM(CQ36:DT36) -> 0 | AE36: =COUNTIFS('ACTIVATED LEADS '!$H:$H,'PARTNERS SUMMARY'!$B36,'ACTIVATED LEADS '!$K:$K,'PARTNERS SUMMARY'!$AE$2,'ACTIVATED LEADS '!$C:$C,"16") -> 0 | AF36: =IFERROR(AD36/X36,0) -> 0 | AH36: =COUNTIFS('ACTIVATED LEADS '!$H:$H,$B36,'ACTIVATED LEADS '!$D:$D,'PARTNERS SUMMARY'!AH$3) -> 0 | AI36: =COUNTIFS('ACTIVATED LEADS '!$H:$H,$B36,'ACTIVATED LEADS '!$D:$D,'PARTNERS SUMMARY'!AI$3) -> 0 | AJ36: =COUNTIFS('ACTIVATED LEADS '!$H:$H,$B36,'ACTIVATED LEADS '!$D:$D,'PARTNERS SUMMARY'!AJ$3) -> 0 | AK36: =COUNTIFS('ACTIVATED LEADS '!$H:$H,$B36,'ACTIVATED LEADS '!$D:$D,'PARTNERS SUMMARY'!AK$3) -> 0 | AL36: =COUNTIFS('ACTIVATED LEADS '!$H:$H,$B36,'ACTIVATED LEADS '!$D:$D,'PARTNERS SUMMARY'!AL$3) -> 0 | AM36: =COUNTIFS('ACTIVATED LEADS '!$H:$H,$B36,'ACTIVATED LEADS '!$D:$D,'PARTNERS SUMMARY'!AM$3) -> 0 | AN36: =COUNTIFS('ACTIVATED LEADS '!$H:$H,$B36,'ACTIVATED LEADS '!$D:$D,'PARTNERS SUMMARY'!AN$3) -> 0 | AO36: =COUNTIFS('ACTIVATED LEADS '!$H:$H,$B36,'ACTIVATED LEADS '!$D:$D,'PARTNERS SUMMARY'!AO$3) -> 0 | ... DO36: =COUNTIFS('ACTIVATED LEADS '!$H:$H,$B36,'ACTIVATED LEADS '!$D:$D,'PARTNERS SUMMARY'!DO$3) -> 0
A37: Brian Odero | B37: VEEGITEK COMPUTERS | E37: Rongai | F37: Nairobi | G37: =COUNTIF('SEPT DUMP '!$C:$C,'PARTNERS SUMMARY'!$B37) -> 0 | H37: =COUNTIFS('SEPT DUMP '!$C:$C,'PARTNERS SUMMARY'!$B37,'SEPT DUMP '!$O:$O,"Confirmed") -> 0 | I37: =COUNTIFS('SEPT DUMP '!$C:$C,'PARTNERS SUMMARY'!$B37,'SEPT DUMP '!$O:$O,"Rejected") -> 0 | J37: =COUNTIFS('SEPT DUMP '!$C:$C,'PARTNERS SUMMARY'!$B37,'SEPT DUMP '!$O:$O,"Unreachable") -> 0 | K37: =COUNTIFS('SEPT DUMP '!$C:$C,'PARTNERS SUMMARY'!$B37,'SEPT DUMP '!$O:$O,"Postponed(Update Y)") -> 0 | L37: =SUM(AH37:BK37) -> 0 | M37: =IFERROR(L37/G37,0) -> 0 | O37: =COUNTIF('OCT DUMP'!$D:$D,'PARTNERS SUMMARY'!$B37) -> 0 | P37: =COUNTIFS('OCT DUMP'!$D:$D,'PARTNERS SUMMARY'!$B37,'OCT DUMP'!Q:Q,"Prospect") -> 0 | Q37: =COUNTIFS('OCT DUMP'!$D:$D,'PARTNERS SUMMARY'!$B37,'OCT DUMP'!$Q:$Q,"Confirmed") -> 0 | R37: =COUNTIFS('OCT DUMP'!$D:$D,'PARTNERS SUMMARY'!$B37,'OCT DUMP'!$Q:$Q,"Rejected") -> 0 | S37: =COUNTIFS('OCT DUMP'!$D:$D,'PARTNERS SUMMARY'!$B37,'OCT DUMP'!$Q:$Q,"Unreachable") -> 0 | T37: =COUNTIFS('OCT DUMP'!$D:$D,'PARTNERS SUMMARY'!$B37,'OCT DUMP'!$Q:$Q,"Postponed(Update Y)") -> 0 | U37: =SUM(BL37:CP37) -> 0 | V37: =IFERROR(U37/O37,0) -> 0 | X37: =COUNTIF('NOV DUMP'!C:C,'PARTNERS SUMMARY'!$B37) -> 0 | Y37: =COUNTIFS('NOV DUMP'!$C:$C,'PARTNERS SUMMARY'!$B37,'NOV DUMP'!$S:$S,"Prospect") -> 0 | Z37: =COUNTIFS('NOV DUMP'!$C:$C,'PARTNERS SUMMARY'!$B37,'NOV DUMP'!$S:$S,"Confirmed") -> 0 | AA37: =COUNTIFS('NOV DUMP'!$C:$C,'PARTNERS SUMMARY'!$B37,'NOV DUMP'!$S:$S,"Rejected") -> 0 | AB37: =COUNTIFS('NOV DUMP'!$C:$C,'PARTNERS SUMMARY'!$B37,'NOV DUMP'!$S:$S,"Unreachable") -> 0 | AC37: =COUNTIFS('NOV DUMP'!$C:$C,'PARTNERS SUMMARY'!$B37,'NOV DUMP'!$S:$S,"Postponed(Update Y)") -> 0 | AD37: =SUM(CQ37:DT37) -> 0 | AE37: =COUNTIFS('ACTIVATED LEADS '!$H:$H,'PARTNERS SUMMARY'!$B37,'ACTIVATED LEADS '!$K:$K,'PARTNERS SUMMARY'!$AE$2,'ACTIVATED LEADS '!$C:$C,"16") -> 0 | AF37: =IFERROR(AD37/X37,0) -> 0 | AH37: =COUNTIFS('ACTIVATED LEADS '!$H:$H,$B37,'ACTIVATED LEADS '!$D:$D,'PARTNERS SUMMARY'!AH$3) -> 0 | AI37: =COUNTIFS('ACTIVATED LEADS '!$H:$H,$B37,'ACTIVATED LEADS '!$D:$D,'PARTNERS SUMMARY'!AI$3) -> 0 | AJ37: =COUNTIFS('ACTIVATED LEADS '!$H:$H,$B37,'ACTIVATED LEADS '!$D:$D,'PARTNERS SUMMARY'!AJ$3) -> 0 | AK37: =COUNTIFS('ACTIVATED LEADS '!$H:$H,$B37,'ACTIVATED LEADS '!$D:$D,'PARTNERS SUMMARY'!AK$3) -> 0 | AL37: =COUNTIFS('ACTIVATED LEADS '!$H:$H,$B37,'ACTIVATED LEADS '!$D:$D,'PARTNERS SUMMARY'!AL$3) -> 0 | AM37: =COUNTIFS('ACTIVATED LEADS '!$H:$H,$B37,'ACTIVATED LEADS '!$D:$D,'PARTNERS SUMMARY'!AM$3) -> 0 | AN37: =COUNTIFS('ACTIVATED LEADS '!$H:$H,$B37,'ACTIVATED LEADS '!$D:$D,'PARTNERS SUMMARY'!AN$3) -> 0 | AO37: =COUNTIFS('ACTIVATED LEADS '!$H:$H,$B37,'ACTIVATED LEADS '!$D:$D,'PARTNERS SUMMARY'!AO$3) -> 0 | ... DO37: =COUNTIFS('ACTIVATED LEADS '!$H:$H,$B37,'ACTIVATED LEADS '!$D:$D,'PARTNERS SUMMARY'!DO$3) -> 0
A38: Betreace Chebet | B38: BLUESTRON SOLUTIONS LTD | E38: Njoro | F38: Rift | G38: =COUNTIF('SEPT DUMP '!$C:$C,'PARTNERS SUMMARY'!$B38) -> 0 | H38: =COUNTIFS('SEPT DUMP '!$C:$C,'PARTNERS SUMMARY'!$B38,'SEPT DUMP '!$O:$O,"Confirmed") -> 0 | I38: =COUNTIFS('SEPT DUMP '!$C:$C,'PARTNERS SUMMARY'!$B38,'SEPT DUMP '!$O:$O,"Rejected") -> 0 | J38: =COUNTIFS('SEPT DUMP '!$C:$C,'PARTNERS SUMMARY'!$B38,'SEPT DUMP '!$O:$O,"Unreachable") -> 0 | K38: =COUNTIFS('SEPT DUMP '!$C:$C,'PARTNERS SUMMARY'!$B38,'SEPT DUMP '!$O:$O,"Postponed(Update Y)") -> 0 | L38: =SUM(AH38:BK38) -> 0 | M38: =IFERROR(L38/G38,0) -> 0 | O38: =COUNTIF('OCT DUMP'!$D:$D,'PARTNERS SUMMARY'!$B38) -> 0 | P38: =COUNTIFS('OCT DUMP'!$D:$D,'PARTNERS SUMMARY'!$B38,'OCT DUMP'!Q:Q,"Prospect") -> 0 | Q38: =COUNTIFS('OCT DUMP'!$D:$D,'PARTNERS SUMMARY'!$B38,'OCT DUMP'!$Q:$Q,"Confirmed") -> 0 | R38: =COUNTIFS('OCT DUMP'!$D:$D,'PARTNERS SUMMARY'!$B38,'OCT DUMP'!$Q:$Q,"Rejected") -> 0 | S38: =COUNTIFS('OCT DUMP'!$D:$D,'PARTNERS SUMMARY'!$B38,'OCT DUMP'!$Q:$Q,"Unreachable") -> 0 | T38: =COUNTIFS('OCT DUMP'!$D:$D,'PARTNERS SUMMARY'!$B38,'OCT DUMP'!$Q:$Q,"Postponed(Update Y)") -> 0 | U38: =SUM(BL38:CP38) -> 0 | V38: =IFERROR(U38/O38,0) -> 0 | X38: =COUNTIF('NOV DUMP'!C:C,'PARTNERS SUMMARY'!$B38) -> 0 | Y38: =COUNTIFS('NOV DUMP'!$C:$C,'PARTNERS SUMMARY'!$B38,'NOV DUMP'!$S:$S,"Prospect") -> 0 | Z38: =COUNTIFS('NOV DUMP'!$C:$C,'PARTNERS SUMMARY'!$B38,'NOV DUMP'!$S:$S,"Confirmed") -> 0 | AA38: =COUNTIFS('NOV DUMP'!$C:$C,'PARTNERS SUMMARY'!$B38,'NOV DUMP'!$S:$S,"Rejected") -> 0 | AB38: =COUNTIFS('NOV DUMP'!$C:$C,'PARTNERS SUMMARY'!$B38,'NOV DUMP'!$S:$S,"Unreachable") -> 0 | AC38: =COUNTIFS('NOV DUMP'!$C:$C,'PARTNERS SUMMARY'!$B38,'NOV DUMP'!$S:$S,"Postponed(Update Y)") -> 0 | AD38: =SUM(CQ38:DT38) -> 0 | AE38: =COUNTIFS('ACTIVATED LEADS '!$H:$H,'PARTNERS SUMMARY'!$B38,'ACTIVATED LEADS '!$K:$K,'PARTNERS SUMMARY'!$AE$2,'ACTIVATED LEADS '!$C:$C,"16") -> 0 | AF38: =IFERROR(AD38/X38,0) -> 0 | AH38: =COUNTIFS('ACTIVATED LEADS '!$H:$H,$B38,'ACTIVATED LEADS '!$D:$D,'PARTNERS SUMMARY'!AH$3) -> 0 | AI38: =COUNTIFS('ACTIVATED LEADS '!$H:$H,$B38,'ACTIVATED LEADS '!$D:$D,'PARTNERS SUMMARY'!AI$3) -> 0 | AJ38: =COUNTIFS('ACTIVATED LEADS '!$H:$H,$B38,'ACTIVATED LEADS '!$D:$D,'PARTNERS SUMMARY'!AJ$3) -> 0 | AK38: =COUNTIFS('ACTIVATED LEADS '!$H:$H,$B38,'ACTIVATED LEADS '!$D:$D,'PARTNERS SUMMARY'!AK$3) -> 0 | AL38: =COUNTIFS('ACTIVATED LEADS '!$H:$H,$B38,'ACTIVATED LEADS '!$D:$D,'PARTNERS SUMMARY'!AL$3) -> 0 | AM38: =COUNTIFS('ACTIVATED LEADS '!$H:$H,$B38,'ACTIVATED LEADS '!$D:$D,'PARTNERS SUMMARY'!AM$3) -> 0 | AN38: =COUNTIFS('ACTIVATED LEADS '!$H:$H,$B38,'ACTIVATED LEADS '!$D:$D,'PARTNERS SUMMARY'!AN$3) -> 0 | AO38: =COUNTIFS('ACTIVATED LEADS '!$H:$H,$B38,'ACTIVATED LEADS '!$D:$D,'PARTNERS SUMMARY'!AO$3) -> 0 | ... DO38: =COUNTIFS('ACTIVATED LEADS '!$H:$H,$B38,'ACTIVATED LEADS '!$D:$D,'PARTNERS SUMMARY'!DO$3) -> 0
A39: Brian Odero | B39: Foresight TLC | C39: 783405468 | E39: milimani road | F39: Nairobi | G39: =COUNTIF('SEPT DUMP '!$C:$C,'PARTNERS SUMMARY'!$B39) -> 0 | H39: =COUNTIFS('SEPT DUMP '!$C:$C,'PARTNERS SUMMARY'!$B39,'SEPT DUMP '!$O:$O,"Confirmed") -> 0 | I39: =COUNTIFS('SEPT DUMP '!$C:$C,'PARTNERS SUMMARY'!$B39,'SEPT DUMP '!$O:$O,"Rejected") -> 0 | J39: =COUNTIFS('SEPT DUMP '!$C:$C,'PARTNERS SUMMARY'!$B39,'SEPT DUMP '!$O:$O,"Unreachable") -> 0 | K39: =COUNTIFS('SEPT DUMP '!$C:$C,'PARTNERS SUMMARY'!$B39,'SEPT DUMP '!$O:$O,"Postponed(Update Y)") -> 0 | L39: =SUM(AH39:BK39) -> 0 | M39: =IFERROR(L39/G39,0) -> 0 | O39: =COUNTIF('OCT DUMP'!$D:$D,'PARTNERS SUMMARY'!$B39) -> 0 | P39: =COUNTIFS('OCT DUMP'!$D:$D,'PARTNERS SUMMARY'!$B39,'OCT DUMP'!Q:Q,"Prospect") -> 0 | Q39: =COUNTIFS('OCT DUMP'!$D:$D,'PARTNERS SUMMARY'!$B39,'OCT DUMP'!$Q:$Q,"Confirmed") -> 0 | R39: =COUNTIFS('OCT DUMP'!$D:$D,'PARTNERS SUMMARY'!$B39,'OCT DUMP'!$Q:$Q,"Rejected") -> 0 | S39: =COUNTIFS('OCT DUMP'!$D:$D,'PARTNERS SUMMARY'!$B39,'OCT DUMP'!$Q:$Q,"Unreachable") -> 0 | T39: =COUNTIFS('OCT DUMP'!$D:$D,'PARTNERS SUMMARY'!$B39,'OCT DUMP'!$Q:$Q,"Postponed(Update Y)") -> 0 | U39: =SUM(BL39:CP39) -> 0 | V39: =IFERROR(U39/O39,0) -> 0 | X39: =COUNTIF('NOV DUMP'!C:C,'PARTNERS SUMMARY'!$B39) -> 0 | Y39: =COUNTIFS('NOV DUMP'!$C:$C,'PARTNERS SUMMARY'!$B39,'NOV DUMP'!$S:$S,"Prospect") -> 0 | Z39: =COUNTIFS('NOV DUMP'!$C:$C,'PARTNERS SUMMARY'!$B39,'NOV DUMP'!$S:$S,"Confirmed") -> 0 | AA39: =COUNTIFS('NOV DUMP'!$C:$C,'PARTNERS SUMMARY'!$B39,'NOV DUMP'!$S:$S,"Rejected") -> 0 | AB39: =COUNTIFS('NOV DUMP'!$C:$C,'PARTNERS SUMMARY'!$B39,'NOV DUMP'!$S:$S,"Unreachable") -> 0 | AC39: =COUNTIFS('NOV DUMP'!$C:$C,'PARTNERS SUMMARY'!$B39,'NOV DUMP'!$S:$S,"Postponed(Update Y)") -> 0 | AD39: =SUM(CQ39:DT39) -> 0 | AE39: =COUNTIFS('ACTIVATED LEADS '!$H:$H,'PARTNERS SUMMARY'!$B39,'ACTIVATED LEADS '!$K:$K,'PARTNERS SUMMARY'!$AE$2,'ACTIVATED LEADS '!$C:$C,"16") -> 0 | AF39: =IFERROR(AD39/X39,0) -> 0 | AH39: =COUNTIFS('ACTIVATED LEADS '!$H:$H,$B39,'ACTIVATED LEADS '!$D:$D,'PARTNERS SUMMARY'!AH$3) -> 0 | AI39: =COUNTIFS('ACTIVATED LEADS '!$H:$H,$B39,'ACTIVATED LEADS '!$D:$D,'PARTNERS SUMMARY'!AI$3) -> 0 | AJ39: =COUNTIFS('ACTIVATED LEADS '!$H:$H,$B39,'ACTIVATED LEADS '!$D:$D,'PARTNERS SUMMARY'!AJ$3) -> 0 | AK39: =COUNTIFS('ACTIVATED LEADS '!$H:$H,$B39,'ACTIVATED LEADS '!$D:$D,'PARTNERS SUMMARY'!AK$3) -> 0 | AL39: =COUNTIFS('ACTIVATED LEADS '!$H:$H,$B39,'ACTIVATED LEADS '!$D:$D,'PARTNERS SUMMARY'!AL$3) -> 0 | AM39: =COUNTIFS('ACTIVATED LEADS '!$H:$H,$B39,'ACTIVATED LEADS '!$D:$D,'PARTNERS SUMMARY'!AM$3) -> 0 | AN39: =COUNTIFS('ACTIVATED LEADS '!$H:$H,$B39,'ACTIVATED LEADS '!$D:$D,'PARTNERS SUMMARY'!AN$3) -> 0 | AO39: =COUNTIFS('ACTIVATED LEADS '!$H:$H,$B39,'ACTIVATED LEADS '!$D:$D,'PARTNERS SUMMARY'!AO$3) -> 0 | ... DO39: =COUNTIFS('ACTIVATED LEADS '!$H:$H,$B39,'ACTIVATED LEADS '!$D:$D,'PARTNERS SUMMARY'!DO$3) -> 0
A40: Brian Odero | B40: Q3M WANDA SOLUTIONS | C40: 784138677 | E40: Nairobi | F40: Nairobi | G40: =COUNTIF('SEPT DUMP '!$C:$C,'PARTNERS SUMMARY'!$B40) -> 0 | H40: =COUNTIFS('SEPT DUMP '!$C:$C,'PARTNERS SUMMARY'!$B40,'SEPT DUMP '!$O:$O,"Confirmed") -> 0 | I40: =COUNTIFS('SEPT DUMP '!$C:$C,'PARTNERS SUMMARY'!$B40,'SEPT DUMP '!$O:$O,"Rejected") -> 0 | J40: =COUNTIFS('SEPT DUMP '!$C:$C,'PARTNERS SUMMARY'!$B40,'SEPT DUMP '!$O:$O,"Unreachable") -> 0 | K40: =COUNTIFS('SEPT DUMP '!$C:$C,'PARTNERS SUMMARY'!$B40,'SEPT DUMP '!$O:$O,"Postponed(Update Y)") -> 0 | L40: =SUM(AH40:BK40) -> 0 | M40: =IFERROR(L40/G40,0) -> 0 | O40: =COUNTIF('OCT DUMP'!$D:$D,'PARTNERS SUMMARY'!$B40) -> 0 | P40: =COUNTIFS('OCT DUMP'!$D:$D,'PARTNERS SUMMARY'!$B40,'OCT DUMP'!Q:Q,"Prospect") -> 0 | Q40: =COUNTIFS('OCT DUMP'!$D:$D,'PARTNERS SUMMARY'!$B40,'OCT DUMP'!$Q:$Q,"Confirmed") -> 0 | R40: =COUNTIFS('OCT DUMP'!$D:$D,'PARTNERS SUMMARY'!$B40,'OCT DUMP'!$Q:$Q,"Rejected") -> 0 | S40: =COUNTIFS('OCT DUMP'!$D:$D,'PARTNERS SUMMARY'!$B40,'OCT DUMP'!$Q:$Q,"Unreachable") -> 0 | T40: =COUNTIFS('OCT DUMP'!$D:$D,'PARTNERS SUMMARY'!$B40,'OCT DUMP'!$Q:$Q,"Postponed(Update Y)") -> 0 | U40: =SUM(BL40:CP40) -> 0 | V40: =IFERROR(U40/O40,0) -> 0 | X40: =COUNTIF('NOV DUMP'!C:C,'PARTNERS SUMMARY'!$B40) -> 0 | Y40: =COUNTIFS('NOV DUMP'!$C:$C,'PARTNERS SUMMARY'!$B40,'NOV DUMP'!$S:$S,"Prospect") -> 0 | Z40: =COUNTIFS('NOV DUMP'!$C:$C,'PARTNERS SUMMARY'!$B40,'NOV DUMP'!$S:$S,"Confirmed") -> 0 | AA40: =COUNTIFS('NOV DUMP'!$C:$C,'PARTNERS SUMMARY'!$B40,'NOV DUMP'!$S:$S,"Rejected") -> 0 | AB40: =COUNTIFS('NOV DUMP'!$C:$C,'PARTNERS SUMMARY'!$B40,'NOV DUMP'!$S:$S,"Unreachable") -> 0 | AC40: =COUNTIFS('NOV DUMP'!$C:$C,'PARTNERS SUMMARY'!$B40,'NOV DUMP'!$S:$S,"Postponed(Update Y)") -> 0 | AD40: =SUM(CQ40:DT40) -> 0 | AE40: =COUNTIFS('ACTIVATED LEADS '!$H:$H,'PARTNERS SUMMARY'!$B40,'ACTIVATED LEADS '!$K:$K,'PARTNERS SUMMARY'!$AE$2,'ACTIVATED LEADS '!$C:$C,"16") -> 0 | AF40: =IFERROR(AD40/X40,0) -> 0 | AH40: =COUNTIFS('ACTIVATED LEADS '!$H:$H,$B40,'ACTIVATED LEADS '!$D:$D,'PARTNERS SUMMARY'!AH$3) -> 0 | AI40: =COUNTIFS('ACTIVATED LEADS '!$H:$H,$B40,'ACTIVATED LEADS '!$D:$D,'PARTNERS SUMMARY'!AI$3) -> 0 | AJ40: =COUNTIFS('ACTIVATED LEADS '!$H:$H,$B40,'ACTIVATED LEADS '!$D:$D,'PARTNERS SUMMARY'!AJ$3) -> 0 | AK40: =COUNTIFS('ACTIVATED LEADS '!$H:$H,$B40,'ACTIVATED LEADS '!$D:$D,'PARTNERS SUMMARY'!AK$3) -> 0 | AL40: =COUNTIFS('ACTIVATED LEADS '!$H:$H,$B40,'ACTIVATED LEADS '!$D:$D,'PARTNERS SUMMARY'!AL$3) -> 0 | AM40: =COUNTIFS('ACTIVATED LEADS '!$H:$H,$B40,'ACTIVATED LEADS '!$D:$D,'PARTNERS SUMMARY'!AM$3) -> 0 | AN40: =COUNTIFS('ACTIVATED LEADS '!$H:$H,$B40,'ACTIVATED LEADS '!$D:$D,'PARTNERS SUMMARY'!AN$3) -> 0 | AO40: =COUNTIFS('ACTIVATED LEADS '!$H:$H,$B40,'ACTIVATED LEADS '!$D:$D,'PARTNERS SUMMARY'!AO$3) -> 0 | ... DO40: =COUNTIFS('ACTIVATED LEADS '!$H:$H,$B40,'ACTIVATED LEADS '!$D:$D,'PARTNERS SUMMARY'!DO$3) -> 0
A41: Brian Odero | B41: LINKS DATA CENTRE LTD | C41: 789384832 | E41: Rongai | F41: Nairobi | G41: =COUNTIF('SEPT DUMP '!$C:$C,'PARTNERS SUMMARY'!$B41) -> 0 | H41: =COUNTIFS('SEPT DUMP '!$C:$C,'PARTNERS SUMMARY'!$B41,'SEPT DUMP '!$O:$O,"Confirmed") -> 0 | I41: =COUNTIFS('SEPT DUMP '!$C:$C,'PARTNERS SUMMARY'!$B41,'SEPT DUMP '!$O:$O,"Rejected") -> 0 | J41: =COUNTIFS('SEPT DUMP '!$C:$C,'PARTNERS SUMMARY'!$B41,'SEPT DUMP '!$O:$O,"Unreachable") -> 0 | K41: =COUNTIFS('SEPT DUMP '!$C:$C,'PARTNERS SUMMARY'!$B41,'SEPT DUMP '!$O:$O,"Postponed(Update Y)") -> 0 | L41: =SUM(AH41:BK41) -> 0 | M41: =IFERROR(L41/G41,0) -> 0 | O41: =COUNTIF('OCT DUMP'!$D:$D,'PARTNERS SUMMARY'!$B41) -> 0 | P41: =COUNTIFS('OCT DUMP'!$D:$D,'PARTNERS SUMMARY'!$B41,'OCT DUMP'!Q:Q,"Prospect") -> 0 | Q41: =COUNTIFS('OCT DUMP'!$D:$D,'PARTNERS SUMMARY'!$B41,'OCT DUMP'!$Q:$Q,"Confirmed") -> 0 | R41: =COUNTIFS('OCT DUMP'!$D:$D,'PARTNERS SUMMARY'!$B41,'OCT DUMP'!$Q:$Q,"Rejected") -> 0 | S41: =COUNTIFS('OCT DUMP'!$D:$D,'PARTNERS SUMMARY'!$B41,'OCT DUMP'!$Q:$Q,"Unreachable") -> 0 | T41: =COUNTIFS('OCT DUMP'!$D:$D,'PARTNERS SUMMARY'!$B41,'OCT DUMP'!$Q:$Q,"Postponed(Update Y)") -> 0 | U41: =SUM(BL41:CP41) -> 0 | V41: =IFERROR(U41/O41,0) -> 0 | X41: =COUNTIF('NOV DUMP'!C:C,'PARTNERS SUMMARY'!$B41) -> 0 | Y41: =COUNTIFS('NOV DUMP'!$C:$C,'PARTNERS SUMMARY'!$B41,'NOV DUMP'!$S:$S,"Prospect") -> 0 | Z41: =COUNTIFS('NOV DUMP'!$C:$C,'PARTNERS SUMMARY'!$B41,'NOV DUMP'!$S:$S,"Confirmed") -> 0 | AA41: =COUNTIFS('NOV DUMP'!$C:$C,'PARTNERS SUMMARY'!$B41,'NOV DUMP'!$S:$S,"Rejected") -> 0 | AB41: =COUNTIFS('NOV DUMP'!$C:$C,'PARTNERS SUMMARY'!$B41,'NOV DUMP'!$S:$S,"Unreachable") -> 0 | AC41: =COUNTIFS('NOV DUMP'!$C:$C,'PARTNERS SUMMARY'!$B41,'NOV DUMP'!$S:$S,"Postponed(Update Y)") -> 0 | AD41: =SUM(CQ41:DT41) -> 0 | AE41: =COUNTIFS('ACTIVATED LEADS '!$H:$H,'PARTNERS SUMMARY'!$B41,'ACTIVATED LEADS '!$K:$K,'PARTNERS SUMMARY'!$AE$2,'ACTIVATED LEADS '!$C:$C,"16") -> 0 | AF41: =IFERROR(AD41/X41,0) -> 0 | AH41: =COUNTIFS('ACTIVATED LEADS '!$H:$H,$B41,'ACTIVATED LEADS '!$D:$D,'PARTNERS SUMMARY'!AH$3) -> 0 | AI41: =COUNTIFS('ACTIVATED LEADS '!$H:$H,$B41,'ACTIVATED LEADS '!$D:$D,'PARTNERS SUMMARY'!AI$3) -> 0 | AJ41: =COUNTIFS('ACTIVATED LEADS '!$H:$H,$B41,'ACTIVATED LEADS '!$D:$D,'PARTNERS SUMMARY'!AJ$3) -> 0 | AK41: =COUNTIFS('ACTIVATED LEADS '!$H:$H,$B41,'ACTIVATED LEADS '!$D:$D,'PARTNERS SUMMARY'!AK$3) -> 0 | AL41: =COUNTIFS('ACTIVATED LEADS '!$H:$H,$B41,'ACTIVATED LEADS '!$D:$D,'PARTNERS SUMMARY'!AL$3) -> 0 | AM41: =COUNTIFS('ACTIVATED LEADS '!$H:$H,$B41,'ACTIVATED LEADS '!$D:$D,'PARTNERS SUMMARY'!AM$3) -> 0 | AN41: =COUNTIFS('ACTIVATED LEADS '!$H:$H,$B41,'ACTIVATED LEADS '!$D:$D,'PARTNERS SUMMARY'!AN$3) -> 0 | AO41: =COUNTIFS('ACTIVATED LEADS '!$H:$H,$B41,'ACTIVATED LEADS '!$D:$D,'PARTNERS SUMMARY'!AO$3) -> 0 | ... DO41: =COUNTIFS('ACTIVATED LEADS '!$H:$H,$B41,'ACTIVATED LEADS '!$D:$D,'PARTNERS SUMMARY'!DO$3) -> 0
A42: Mariana Hongo | B42: POWEX COMMUNICATIONS | C42: 737335244 | E42: Oyugis | F42: Western | G42: =COUNTIF('SEPT DUMP '!$C:$C,'PARTNERS SUMMARY'!$B42) -> 0 | H42: =COUNTIFS('SEPT DUMP '!$C:$C,'PARTNERS SUMMARY'!$B42,'SEPT DUMP '!$O:$O,"Confirmed") -> 0 | I42: =COUNTIFS('SEPT DUMP '!$C:$C,'PARTNERS SUMMARY'!$B42,'SEPT DUMP '!$O:$O,"Rejected") -> 0 | J42: =COUNTIFS('SEPT DUMP '!$C:$C,'PARTNERS SUMMARY'!$B42,'SEPT DUMP '!$O:$O,"Unreachable") -> 0 | K42: =COUNTIFS('SEPT DUMP '!$C:$C,'PARTNERS SUMMARY'!$B42,'SEPT DUMP '!$O:$O,"Postponed(Update Y)") -> 0 | L42: =SUM(AH42:BK42) -> 0 | M42: =IFERROR(L42/G42,0) -> 0 | O42: =COUNTIF('OCT DUMP'!$D:$D,'PARTNERS SUMMARY'!$B42) -> 0 | P42: =COUNTIFS('OCT DUMP'!$D:$D,'PARTNERS SUMMARY'!$B42,'OCT DUMP'!Q:Q,"Prospect") -> 0 | Q42: =COUNTIFS('OCT DUMP'!$D:$D,'PARTNERS SUMMARY'!$B42,'OCT DUMP'!$Q:$Q,"Confirmed") -> 0 | R42: =COUNTIFS('OCT DUMP'!$D:$D,'PARTNERS SUMMARY'!$B42,'OCT DUMP'!$Q:$Q,"Rejected") -> 0 | S42: =COUNTIFS('OCT DUMP'!$D:$D,'PARTNERS SUMMARY'!$B42,'OCT DUMP'!$Q:$Q,"Unreachable") -> 0 | T42: =COUNTIFS('OCT DUMP'!$D:$D,'PARTNERS SUMMARY'!$B42,'OCT DUMP'!$Q:$Q,"Postponed(Update Y)") -> 0 | U42: =SUM(BL42:CP42) -> 0 | V42: =IFERROR(U42/O42,0) -> 0 | X42: =COUNTIF('NOV DUMP'!C:C,'PARTNERS SUMMARY'!$B42) -> 8 | Y42: =COUNTIFS('NOV DUMP'!$C:$C,'PARTNERS SUMMARY'!$B42,'NOV DUMP'!$S:$S,"Prospect") -> 0 | Z42: =COUNTIFS('NOV DUMP'!$C:$C,'PARTNERS SUMMARY'!$B42,'NOV DUMP'!$S:$S,"Confirmed") -> 1 | AA42: =COUNTIFS('NOV DUMP'!$C:$C,'PARTNERS SUMMARY'!$B42,'NOV DUMP'!$S:$S,"Rejected") -> 0 | AB42: =COUNTIFS('NOV DUMP'!$C:$C,'PARTNERS SUMMARY'!$B42,'NOV DUMP'!$S:$S,"Unreachable") -> 0 | AC42: =COUNTIFS('NOV DUMP'!$C:$C,'PARTNERS SUMMARY'!$B42,'NOV DUMP'!$S:$S,"Postponed(Update Y)") -> 0 | AD42: =SUM(CQ42:DT42) -> 1 | AE42: =COUNTIFS('ACTIVATED LEADS '!$H:$H,'PARTNERS SUMMARY'!$B42,'ACTIVATED LEADS '!$K:$K,'PARTNERS SUMMARY'!$AE$2,'ACTIVATED LEADS '!$C:$C,"16") -> 0 | AF42: =IFERROR(AD42/X42,0) -> 0.125 | AH42: =COUNTIFS('ACTIVATED LEADS '!$H:$H,$B42,'ACTIVATED LEADS '!$D:$D,'PARTNERS SUMMARY'!AH$3) -> 0 | AI42: =COUNTIFS('ACTIVATED LEADS '!$H:$H,$B42,'ACTIVATED LEADS '!$D:$D,'PARTNERS SUMMARY'!AI$3) -> 0 | AJ42: =COUNTIFS('ACTIVATED LEADS '!$H:$H,$B42,'ACTIVATED LEADS '!$D:$D,'PARTNERS SUMMARY'!AJ$3) -> 0 | AK42: =COUNTIFS('ACTIVATED LEADS '!$H:$H,$B42,'ACTIVATED LEADS '!$D:$D,'PARTNERS SUMMARY'!AK$3) -> 0 | AL42: =COUNTIFS('ACTIVATED LEADS '!$H:$H,$B42,'ACTIVATED LEADS '!$D:$D,'PARTNERS SUMMARY'!AL$3) -> 0 | AM42: =COUNTIFS('ACTIVATED LEADS '!$H:$H,$B42,'ACTIVATED LEADS '!$D:$D,'PARTNERS SUMMARY'!AM$3) -> 0 | AN42: =COUNTIFS('ACTIVATED LEADS '!$H:$H,$B42,'ACTIVATED LEADS '!$D:$D,'PARTNERS SUMMARY'!AN$3) -> 0 | AO42: =COUNTIFS('ACTIVATED LEADS '!$H:$H,$B42,'ACTIVATED LEADS '!$D:$D,'PARTNERS SUMMARY'!AO$3) -> 0 | ... DO42: =COUNTIFS('ACTIVATED LEADS '!$H:$H,$B42,'ACTIVATED LEADS '!$D:$D,'PARTNERS SUMMARY'!DO$3) -> 0
A43: Betreace Chebet | B43: TOPSTAR ENTERPRISES | E43: Naivasha | F43: Rift | G43: =COUNTIF('SEPT DUMP '!$C:$C,'PARTNERS SUMMARY'!$B43) -> 0 | H43: =COUNTIFS('SEPT DUMP '!$C:$C,'PARTNERS SUMMARY'!$B43,'SEPT DUMP '!$O:$O,"Confirmed") -> 0 | I43: =COUNTIFS('SEPT DUMP '!$C:$C,'PARTNERS SUMMARY'!$B43,'SEPT DUMP '!$O:$O,"Rejected") -> 0 | J43: =COUNTIFS('SEPT DUMP '!$C:$C,'PARTNERS SUMMARY'!$B43,'SEPT DUMP '!$O:$O,"Unreachable") -> 0 | K43: =COUNTIFS('SEPT DUMP '!$C:$C,'PARTNERS SUMMARY'!$B43,'SEPT DUMP '!$O:$O,"Postponed(Update Y)") -> 0 | L43: =SUM(AH43:BK43) -> 0 | M43: =IFERROR(L43/G43,0) -> 0 | O43: =COUNTIF('OCT DUMP'!$D:$D,'PARTNERS SUMMARY'!$B43) -> 0 | P43: =COUNTIFS('OCT DUMP'!$D:$D,'PARTNERS SUMMARY'!$B43,'OCT DUMP'!Q:Q,"Prospect") -> 0 | Q43: =COUNTIFS('OCT DUMP'!$D:$D,'PARTNERS SUMMARY'!$B43,'OCT DUMP'!$Q:$Q,"Confirmed") -> 0 | R43: =COUNTIFS('OCT DUMP'!$D:$D,'PARTNERS SUMMARY'!$B43,'OCT DUMP'!$Q:$Q,"Rejected") -> 0 | S43: =COUNTIFS('OCT DUMP'!$D:$D,'PARTNERS SUMMARY'!$B43,'OCT DUMP'!$Q:$Q,"Unreachable") -> 0 | T43: =COUNTIFS('OCT DUMP'!$D:$D,'PARTNERS SUMMARY'!$B43,'OCT DUMP'!$Q:$Q,"Postponed(Update Y)") -> 0 | U43: =SUM(BL43:CP43) -> 0 | V43: =IFERROR(U43/O43,0) -> 0 | X43: =COUNTIF('NOV DUMP'!C:C,'PARTNERS SUMMARY'!$B43) -> 0 | Y43: =COUNTIFS('NOV DUMP'!$C:$C,'PARTNERS SUMMARY'!$B43,'NOV DUMP'!$S:$S,"Prospect") -> 0 | Z43: =COUNTIFS('NOV DUMP'!$C:$C,'PARTNERS SUMMARY'!$B43,'NOV DUMP'!$S:$S,"Confirmed") -> 0 | AA43: =COUNTIFS('NOV DUMP'!$C:$C,'PARTNERS SUMMARY'!$B43,'NOV DUMP'!$S:$S,"Rejected") -> 0 | AB43: =COUNTIFS('NOV DUMP'!$C:$C,'PARTNERS SUMMARY'!$B43,'NOV DUMP'!$S:$S,"Unreachable") -> 0 | AC43: =COUNTIFS('NOV DUMP'!$C:$C,'PARTNERS SUMMARY'!$B43,'NOV DUMP'!$S:$S,"Postponed(Update Y)") -> 0 | AD43: =SUM(CQ43:DT43) -> 0 | AE43: =COUNTIFS('ACTIVATED LEADS '!$H:$H,'PARTNERS SUMMARY'!$B43,'ACTIVATED LEADS '!$K:$K,'PARTNERS SUMMARY'!$AE$2,'ACTIVATED LEADS '!$C:$C,"16") -> 0 | AF43: =IFERROR(AD43/X43,0) -> 0 | AH43: =COUNTIFS('ACTIVATED LEADS '!$H:$H,$B43,'ACTIVATED LEADS '!$D:$D,'PARTNERS SUMMARY'!AH$3) -> 0 | AI43: =COUNTIFS('ACTIVATED LEADS '!$H:$H,$B43,'ACTIVATED LEADS '!$D:$D,'PARTNERS SUMMARY'!AI$3) -> 0 | AJ43: =COUNTIFS('ACTIVATED LEADS '!$H:$H,$B43,'ACTIVATED LEADS '!$D:$D,'PARTNERS SUMMARY'!AJ$3) -> 0 | AK43: =COUNTIFS('ACTIVATED LEADS '!$H:$H,$B43,'ACTIVATED LEADS '!$D:$D,'PARTNERS SUMMARY'!AK$3) -> 0 | AL43: =COUNTIFS('ACTIVATED LEADS '!$H:$H,$B43,'ACTIVATED LEADS '!$D:$D,'PARTNERS SUMMARY'!AL$3) -> 0 | AM43: =COUNTIFS('ACTIVATED LEADS '!$H:$H,$B43,'ACTIVATED LEADS '!$D:$D,'PARTNERS SUMMARY'!AM$3) -> 0 | AN43: =COUNTIFS('ACTIVATED LEADS '!$H:$H,$B43,'ACTIVATED LEADS '!$D:$D,'PARTNERS SUMMARY'!AN$3) -> 0 | AO43: =COUNTIFS('ACTIVATED LEADS '!$H:$H,$B43,'ACTIVATED LEADS '!$D:$D,'PARTNERS SUMMARY'!AO$3) -> 0 | ... DO43: =COUNTIFS('ACTIVATED LEADS '!$H:$H,$B43,'ACTIVATED LEADS '!$D:$D,'PARTNERS SUMMARY'!DO$3) -> 0
A44: Brian Odero | B44: KEYTAN HOLDING LIMITED | C44: 103622901 | E44: Mombasa | F44: Nairobi | G44: =COUNTIF('SEPT DUMP '!$C:$C,'PARTNERS SUMMARY'!$B44) -> 0 | H44: =COUNTIFS('SEPT DUMP '!$C:$C,'PARTNERS SUMMARY'!$B44,'SEPT DUMP '!$O:$O,"Confirmed") -> 0 | I44: =COUNTIFS('SEPT DUMP '!$C:$C,'PARTNERS SUMMARY'!$B44,'SEPT DUMP '!$O:$O,"Rejected") -> 0 | J44: =COUNTIFS('SEPT DUMP '!$C:$C,'PARTNERS SUMMARY'!$B44,'SEPT DUMP '!$O:$O,"Unreachable") -> 0 | K44: =COUNTIFS('SEPT DUMP '!$C:$C,'PARTNERS SUMMARY'!$B44,'SEPT DUMP '!$O:$O,"Postponed(Update Y)") -> 0 | L44: =SUM(AH44:BK44) -> 0 | M44: =IFERROR(L44/G44,0) -> 0 | O44: =COUNTIF('OCT DUMP'!$D:$D,'PARTNERS SUMMARY'!$B44) -> 0 | P44: =COUNTIFS('OCT DUMP'!$D:$D,'PARTNERS SUMMARY'!$B44,'OCT DUMP'!Q:Q,"Prospect") -> 0 | Q44: =COUNTIFS('OCT DUMP'!$D:$D,'PARTNERS SUMMARY'!$B44,'OCT DUMP'!$Q:$Q,"Confirmed") -> 0 | R44: =COUNTIFS('OCT DUMP'!$D:$D,'PARTNERS SUMMARY'!$B44,'OCT DUMP'!$Q:$Q,"Rejected") -> 0 | S44: =COUNTIFS('OCT DUMP'!$D:$D,'PARTNERS SUMMARY'!$B44,'OCT DUMP'!$Q:$Q,"Unreachable") -> 0 | T44: =COUNTIFS('OCT DUMP'!$D:$D,'PARTNERS SUMMARY'!$B44,'OCT DUMP'!$Q:$Q,"Postponed(Update Y)") -> 0 | U44: =SUM(BL44:CP44) -> 0 | V44: =IFERROR(U44/O44,0) -> 0 | X44: =COUNTIF('NOV DUMP'!C:C,'PARTNERS SUMMARY'!$B44) -> 1 | Y44: =COUNTIFS('NOV DUMP'!$C:$C,'PARTNERS SUMMARY'!$B44,'NOV DUMP'!$S:$S,"Prospect") -> 0 | Z44: =COUNTIFS('NOV DUMP'!$C:$C,'PARTNERS SUMMARY'!$B44,'NOV DUMP'!$S:$S,"Confirmed") -> 0 | AA44: =COUNTIFS('NOV DUMP'!$C:$C,'PARTNERS SUMMARY'!$B44,'NOV DUMP'!$S:$S,"Rejected") -> 0 | AB44: =COUNTIFS('NOV DUMP'!$C:$C,'PARTNERS SUMMARY'!$B44,'NOV DUMP'!$S:$S,"Unreachable") -> 0 | AC44: =COUNTIFS('NOV DUMP'!$C:$C,'PARTNERS SUMMARY'!$B44,'NOV DUMP'!$S:$S,"Postponed(Update Y)") -> 0 | AD44: =SUM(CQ44:DT44) -> 0 | AE44: =COUNTIFS('ACTIVATED LEADS '!$H:$H,'PARTNERS SUMMARY'!$B44,'ACTIVATED LEADS '!$K:$K,'PARTNERS SUMMARY'!$AE$2,'ACTIVATED LEADS '!$C:$C,"16") -> 0 | AF44: =IFERROR(AD44/X44,0) -> 0 | AH44: =COUNTIFS('ACTIVATED LEADS '!$H:$H,$B44,'ACTIVATED LEADS '!$D:$D,'PARTNERS SUMMARY'!AH$3) -> 0 | AI44: =COUNTIFS('ACTIVATED LEADS '!$H:$H,$B44,'ACTIVATED LEADS '!$D:$D,'PARTNERS SUMMARY'!AI$3) -> 0 | AJ44: =COUNTIFS('ACTIVATED LEADS '!$H:$H,$B44,'ACTIVATED LEADS '!$D:$D,'PARTNERS SUMMARY'!AJ$3) -> 0 | AK44: =COUNTIFS('ACTIVATED LEADS '!$H:$H,$B44,'ACTIVATED LEADS '!$D:$D,'PARTNERS SUMMARY'!AK$3) -> 0 | AL44: =COUNTIFS('ACTIVATED LEADS '!$H:$H,$B44,'ACTIVATED LEADS '!$D:$D,'PARTNERS SUMMARY'!AL$3) -> 0 | AM44: =COUNTIFS('ACTIVATED LEADS '!$H:$H,$B44,'ACTIVATED LEADS '!$D:$D,'PARTNERS SUMMARY'!AM$3) -> 0 | AN44: =COUNTIFS('ACTIVATED LEADS '!$H:$H,$B44,'ACTIVATED LEADS '!$D:$D,'PARTNERS SUMMARY'!AN$3) -> 0 | AO44: =COUNTIFS('ACTIVATED LEADS '!$H:$H,$B44,'ACTIVATED LEADS '!$D:$D,'PARTNERS SUMMARY'!AO$3) -> 0 | ... DO44: =COUNTIFS('ACTIVATED LEADS '!$H:$H,$B44,'ACTIVATED LEADS '!$D:$D,'PARTNERS SUMMARY'!DO$3) -> 0
A45: Mariana Hongo | B45: RIEDLA ENTERPRISES LIMITED | C45: 755686393 | E45: Kisumu | F45: Western | G45: =COUNTIF('SEPT DUMP '!$C:$C,'PARTNERS SUMMARY'!$B45) -> 0 | H45: =COUNTIFS('SEPT DUMP '!$C:$C,'PARTNERS SUMMARY'!$B45,'SEPT DUMP '!$O:$O,"Confirmed") -> 0 | I45: =COUNTIFS('SEPT DUMP '!$C:$C,'PARTNERS SUMMARY'!$B45,'SEPT DUMP '!$O:$O,"Rejected") -> 0 | J45: =COUNTIFS('SEPT DUMP '!$C:$C,'PARTNERS SUMMARY'!$B45,'SEPT DUMP '!$O:$O,"Unreachable") -> 0 | K45: =COUNTIFS('SEPT DUMP '!$C:$C,'PARTNERS SUMMARY'!$B45,'SEPT DUMP '!$O:$O,"Postponed(Update Y)") -> 0 | L45: =SUM(AH45:BK45) -> 0 | M45: =IFERROR(L45/G45,0) -> 0 | O45: =COUNTIF('OCT DUMP'!$D:$D,'PARTNERS SUMMARY'!$B45) -> 1 | P45: =COUNTIFS('OCT DUMP'!$D:$D,'PARTNERS SUMMARY'!$B45,'OCT DUMP'!Q:Q,"Prospect") -> 0 | Q45: =COUNTIFS('OCT DUMP'!$D:$D,'PARTNERS SUMMARY'!$B45,'OCT DUMP'!$Q:$Q,"Confirmed") -> 1 | R45: =COUNTIFS('OCT DUMP'!$D:$D,'PARTNERS SUMMARY'!$B45,'OCT DUMP'!$Q:$Q,"Rejected") -> 0 | S45: =COUNTIFS('OCT DUMP'!$D:$D,'PARTNERS SUMMARY'!$B45,'OCT DUMP'!$Q:$Q,"Unreachable") -> 0 | T45: =COUNTIFS('OCT DUMP'!$D:$D,'PARTNERS SUMMARY'!$B45,'OCT DUMP'!$Q:$Q,"Postponed(Update Y)") -> 0 | U45: =SUM(BL45:CP45) -> 1 | V45: =IFERROR(U45/O45,0) -> 1 | X45: =COUNTIF('NOV DUMP'!C:C,'PARTNERS SUMMARY'!$B45) -> 0 | Y45: =COUNTIFS('NOV DUMP'!$C:$C,'PARTNERS SUMMARY'!$B45,'NOV DUMP'!$S:$S,"Prospect") -> 0 | Z45: =COUNTIFS('NOV DUMP'!$C:$C,'PARTNERS SUMMARY'!$B45,'NOV DUMP'!$S:$S,"Confirmed") -> 0 | AA45: =COUNTIFS('NOV DUMP'!$C:$C,'PARTNERS SUMMARY'!$B45,'NOV DUMP'!$S:$S,"Rejected") -> 0 | AB45: =COUNTIFS('NOV DUMP'!$C:$C,'PARTNERS SUMMARY'!$B45,'NOV DUMP'!$S:$S,"Unreachable") -> 0 | AC45: =COUNTIFS('NOV DUMP'!$C:$C,'PARTNERS SUMMARY'!$B45,'NOV DUMP'!$S:$S,"Postponed(Update Y)") -> 0 | AD45: =SUM(CQ45:DT45) -> 0 | AE45: =COUNTIFS('ACTIVATED LEADS '!$H:$H,'PARTNERS SUMMARY'!$B45,'ACTIVATED LEADS '!$K:$K,'PARTNERS SUMMARY'!$AE$2,'ACTIVATED LEADS '!$C:$C,"16") -> 0 | AF45: =IFERROR(AD45/X45,0) -> 0 | AH45: =COUNTIFS('ACTIVATED LEADS '!$H:$H,$B45,'ACTIVATED LEADS '!$D:$D,'PARTNERS SUMMARY'!AH$3) -> 0 | AI45: =COUNTIFS('ACTIVATED LEADS '!$H:$H,$B45,'ACTIVATED LEADS '!$D:$D,'PARTNERS SUMMARY'!AI$3) -> 0 | AJ45: =COUNTIFS('ACTIVATED LEADS '!$H:$H,$B45,'ACTIVATED LEADS '!$D:$D,'PARTNERS SUMMARY'!AJ$3) -> 0 | AK45: =COUNTIFS('ACTIVATED LEADS '!$H:$H,$B45,'ACTIVATED LEADS '!$D:$D,'PARTNERS SUMMARY'!AK$3) -> 0 | AL45: =COUNTIFS('ACTIVATED LEADS '!$H:$H,$B45,'ACTIVATED LEADS '!$D:$D,'PARTNERS SUMMARY'!AL$3) -> 0 | AM45: =COUNTIFS('ACTIVATED LEADS '!$H:$H,$B45,'ACTIVATED LEADS '!$D:$D,'PARTNERS SUMMARY'!AM$3) -> 0 | AN45: =COUNTIFS('ACTIVATED LEADS '!$H:$H,$B45,'ACTIVATED LEADS '!$D:$D,'PARTNERS SUMMARY'!AN$3) -> 0 | AO45: =COUNTIFS('ACTIVATED LEADS '!$H:$H,$B45,'ACTIVATED LEADS '!$D:$D,'PARTNERS SUMMARY'!AO$3) -> 0 | ... DO45: =COUNTIFS('ACTIVATED LEADS '!$H:$H,$B45,'ACTIVATED LEADS '!$D:$D,'PARTNERS SUMMARY'!DO$3) -> 0
A46: Damaris Mainga | B46: POLO MARKETING COMPANY | C46: 789230701 | E46: NAIROBI TOWN | F46: Nairobi | G46: =COUNTIF('SEPT DUMP '!$C:$C,'PARTNERS SUMMARY'!$B46) -> 0 | H46: =COUNTIFS('SEPT DUMP '!$C:$C,'PARTNERS SUMMARY'!$B46,'SEPT DUMP '!$O:$O,"Confirmed") -> 0 | I46: =COUNTIFS('SEPT DUMP '!$C:$C,'PARTNERS SUMMARY'!$B46,'SEPT DUMP '!$O:$O,"Rejected") -> 0 | J46: =COUNTIFS('SEPT DUMP '!$C:$C,'PARTNERS SUMMARY'!$B46,'SEPT DUMP '!$O:$O,"Unreachable") -> 0 | K46: =COUNTIFS('SEPT DUMP '!$C:$C,'PARTNERS SUMMARY'!$B46,'SEPT DUMP '!$O:$O,"Postponed(Update Y)") -> 0 | L46: =SUM(AH46:BK46) -> 0 | M46: =IFERROR(L46/G46,0) -> 0 | O46: =COUNTIF('OCT DUMP'!$D:$D,'PARTNERS SUMMARY'!$B46) -> 0 | P46: =COUNTIFS('OCT DUMP'!$D:$D,'PARTNERS SUMMARY'!$B46,'OCT DUMP'!Q:Q,"Prospect") -> 0 | Q46: =COUNTIFS('OCT DUMP'!$D:$D,'PARTNERS SUMMARY'!$B46,'OCT DUMP'!$Q:$Q,"Confirmed") -> 0 | R46: =COUNTIFS('OCT DUMP'!$D:$D,'PARTNERS SUMMARY'!$B46,'OCT DUMP'!$Q:$Q,"Rejected") -> 0 | S46: =COUNTIFS('OCT DUMP'!$D:$D,'PARTNERS SUMMARY'!$B46,'OCT DUMP'!$Q:$Q,"Unreachable") -> 0 | T46: =COUNTIFS('OCT DUMP'!$D:$D,'PARTNERS SUMMARY'!$B46,'OCT DUMP'!$Q:$Q,"Postponed(Update Y)") -> 0 | U46: =SUM(BL46:CP46) -> 0 | V46: =IFERROR(U46/O46,0) -> 0 | X46: =COUNTIF('NOV DUMP'!C:C,'PARTNERS SUMMARY'!$B46) -> 0 | Y46: =COUNTIFS('NOV DUMP'!$C:$C,'PARTNERS SUMMARY'!$B46,'NOV DUMP'!$S:$S,"Prospect") -> 0 | Z46: =COUNTIFS('NOV DUMP'!$C:$C,'PARTNERS SUMMARY'!$B46,'NOV DUMP'!$S:$S,"Confirmed") -> 0 | AA46: =COUNTIFS('NOV DUMP'!$C:$C,'PARTNERS SUMMARY'!$B46,'NOV DUMP'!$S:$S,"Rejected") -> 0 | AB46: =COUNTIFS('NOV DUMP'!$C:$C,'PARTNERS SUMMARY'!$B46,'NOV DUMP'!$S:$S,"Unreachable") -> 0 | AC46: =COUNTIFS('NOV DUMP'!$C:$C,'PARTNERS SUMMARY'!$B46,'NOV DUMP'!$S:$S,"Postponed(Update Y)") -> 0 | AD46: =SUM(CQ46:DT46) -> 0 | AE46: =COUNTIFS('ACTIVATED LEADS '!$H:$H,'PARTNERS SUMMARY'!$B46,'ACTIVATED LEADS '!$K:$K,'PARTNERS SUMMARY'!$AE$2,'ACTIVATED LEADS '!$C:$C,"16") -> 0 | AF46: =IFERROR(AD46/X46,0) -> 0 | AH46: =COUNTIFS('ACTIVATED LEADS '!$H:$H,$B46,'ACTIVATED LEADS '!$D:$D,'PARTNERS SUMMARY'!AH$3) -> 0 | AI46: =COUNTIFS('ACTIVATED LEADS '!$H:$H,$B46,'ACTIVATED LEADS '!$D:$D,'PARTNERS SUMMARY'!AI$3) -> 0 | AJ46: =COUNTIFS('ACTIVATED LEADS '!$H:$H,$B46,'ACTIVATED LEADS '!$D:$D,'PARTNERS SUMMARY'!AJ$3) -> 0 | AK46: =COUNTIFS('ACTIVATED LEADS '!$H:$H,$B46,'ACTIVATED LEADS '!$D:$D,'PARTNERS SUMMARY'!AK$3) -> 0 | AL46: =COUNTIFS('ACTIVATED LEADS '!$H:$H,$B46,'ACTIVATED LEADS '!$D:$D,'PARTNERS SUMMARY'!AL$3) -> 0 | AM46: =COUNTIFS('ACTIVATED LEADS '!$H:$H,$B46,'ACTIVATED LEADS '!$D:$D,'PARTNERS SUMMARY'!AM$3) -> 0 | AN46: =COUNTIFS('ACTIVATED LEADS '!$H:$H,$B46,'ACTIVATED LEADS '!$D:$D,'PARTNERS SUMMARY'!AN$3) -> 0 | AO46: =COUNTIFS('ACTIVATED LEADS '!$H:$H,$B46,'ACTIVATED LEADS '!$D:$D,'PARTNERS SUMMARY'!AO$3) -> 0 | ... DO46: =COUNTIFS('ACTIVATED LEADS '!$H:$H,$B46,'ACTIVATED LEADS '!$D:$D,'PARTNERS SUMMARY'!DO$3) -> 0
A47: Betreace Chebet | B47: WAMEER WHOLESALERS AND DISTRIBUTORS LTD | C47: 780072088 | E47: Nakuru Town | F47: Rift | G47: =COUNTIF('SEPT DUMP '!$C:$C,'PARTNERS SUMMARY'!$B47) -> 0 | H47: =COUNTIFS('SEPT DUMP '!$C:$C,'PARTNERS SUMMARY'!$B47,'SEPT DUMP '!$O:$O,"Confirmed") -> 0 | I47: =COUNTIFS('SEPT DUMP '!$C:$C,'PARTNERS SUMMARY'!$B47,'SEPT DUMP '!$O:$O,"Rejected") -> 0 | J47: =COUNTIFS('SEPT DUMP '!$C:$C,'PARTNERS SUMMARY'!$B47,'SEPT DUMP '!$O:$O,"Unreachable") -> 0 | K47: =COUNTIFS('SEPT DUMP '!$C:$C,'PARTNERS SUMMARY'!$B47,'SEPT DUMP '!$O:$O,"Postponed(Update Y)") -> 0 | L47: =SUM(AH47:BK47) -> 0 | M47: =IFERROR(L47/G47,0) -> 0 | O47: =COUNTIF('OCT DUMP'!$D:$D,'PARTNERS SUMMARY'!$B47) -> 3 | P47: =COUNTIFS('OCT DUMP'!$D:$D,'PARTNERS SUMMARY'!$B47,'OCT DUMP'!Q:Q,"Prospect") -> 0 | Q47: =COUNTIFS('OCT DUMP'!$D:$D,'PARTNERS SUMMARY'!$B47,'OCT DUMP'!$Q:$Q,"Confirmed") -> 2 | R47: =COUNTIFS('OCT DUMP'!$D:$D,'PARTNERS SUMMARY'!$B47,'OCT DUMP'!$Q:$Q,"Rejected") -> 0 | S47: =COUNTIFS('OCT DUMP'!$D:$D,'PARTNERS SUMMARY'!$B47,'OCT DUMP'!$Q:$Q,"Unreachable") -> 0 | T47: =COUNTIFS('OCT DUMP'!$D:$D,'PARTNERS SUMMARY'!$B47,'OCT DUMP'!$Q:$Q,"Postponed(Update Y)") -> 1 | U47: =SUM(BL47:CP47) -> 1 | V47: =IFERROR(U47/O47,0) -> 0.33333333 | X47: =COUNTIF('NOV DUMP'!C:C,'PARTNERS SUMMARY'!$B47) -> 8 | Y47: =COUNTIFS('NOV DUMP'!$C:$C,'PARTNERS SUMMARY'!$B47,'NOV DUMP'!$S:$S,"Prospect") -> 0 | Z47: =COUNTIFS('NOV DUMP'!$C:$C,'PARTNERS SUMMARY'!$B47,'NOV DUMP'!$S:$S,"Confirmed") -> 1 | AA47: =COUNTIFS('NOV DUMP'!$C:$C,'PARTNERS SUMMARY'!$B47,'NOV DUMP'!$S:$S,"Rejected") -> 0 | AB47: =COUNTIFS('NOV DUMP'!$C:$C,'PARTNERS SUMMARY'!$B47,'NOV DUMP'!$S:$S,"Unreachable") -> 0 | AC47: =COUNTIFS('NOV DUMP'!$C:$C,'PARTNERS SUMMARY'!$B47,'NOV DUMP'!$S:$S,"Postponed(Update Y)") -> 0 | AD47: =SUM(CQ47:DT47) -> 0 | AE47: =COUNTIFS('ACTIVATED LEADS '!$H:$H,'PARTNERS SUMMARY'!$B47,'ACTIVATED LEADS '!$K:$K,'PARTNERS SUMMARY'!$AE$2,'ACTIVATED LEADS '!$C:$C,"16") -> 0 | AF47: =IFERROR(AD47/X47,0) -> 0 | AH47: =COUNTIFS('ACTIVATED LEADS '!$H:$H,$B47,'ACTIVATED LEADS '!$D:$D,'PARTNERS SUMMARY'!AH$3) -> 0 | AI47: =COUNTIFS('ACTIVATED LEADS '!$H:$H,$B47,'ACTIVATED LEADS '!$D:$D,'PARTNERS SUMMARY'!AI$3) -> 0 | AJ47: =COUNTIFS('ACTIVATED LEADS '!$H:$H,$B47,'ACTIVATED LEADS '!$D:$D,'PARTNERS SUMMARY'!AJ$3) -> 0 | AK47: =COUNTIFS('ACTIVATED LEADS '!$H:$H,$B47,'ACTIVATED LEADS '!$D:$D,'PARTNERS SUMMARY'!AK$3) -> 0 | AL47: =COUNTIFS('ACTIVATED LEADS '!$H:$H,$B47,'ACTIVATED LEADS '!$D:$D,'PARTNERS SUMMARY'!AL$3) -> 0 | AM47: =COUNTIFS('ACTIVATED LEADS '!$H:$H,$B47,'ACTIVATED LEADS '!$D:$D,'PARTNERS SUMMARY'!AM$3) -> 0 | AN47: =COUNTIFS('ACTIVATED LEADS '!$H:$H,$B47,'ACTIVATED LEADS '!$D:$D,'PARTNERS SUMMARY'!AN$3) -> 0 | AO47: =COUNTIFS('ACTIVATED LEADS '!$H:$H,$B47,'ACTIVATED LEADS '!$D:$D,'PARTNERS SUMMARY'!AO$3) -> 0 | ... DO47: =COUNTIFS('ACTIVATED LEADS '!$H:$H,$B47,'ACTIVATED LEADS '!$D:$D,'PARTNERS SUMMARY'!DO$3) -> 0
A48: Salome Sule | B48: HEULAN ENTERPRISES | C48: 734945535 | E48: Mombasa | F48: Coast | G48: =COUNTIF('SEPT DUMP '!$C:$C,'PARTNERS SUMMARY'!$B48) -> 0 | H48: =COUNTIFS('SEPT DUMP '!$C:$C,'PARTNERS SUMMARY'!$B48,'SEPT DUMP '!$O:$O,"Confirmed") -> 0 | I48: =COUNTIFS('SEPT DUMP '!$C:$C,'PARTNERS SUMMARY'!$B48,'SEPT DUMP '!$O:$O,"Rejected") -> 0 | J48: =COUNTIFS('SEPT DUMP '!$C:$C,'PARTNERS SUMMARY'!$B48,'SEPT DUMP '!$O:$O,"Unreachable") -> 0 | K48: =COUNTIFS('SEPT DUMP '!$C:$C,'PARTNERS SUMMARY'!$B48,'SEPT DUMP '!$O:$O,"Postponed(Update Y)") -> 0 | L48: =SUM(AH48:BK48) -> 0 | M48: =IFERROR(L48/G48,0) -> 0 | O48: =COUNTIF('OCT DUMP'!$D:$D,'PARTNERS SUMMARY'!$B48) -> 0 | P48: =COUNTIFS('OCT DUMP'!$D:$D,'PARTNERS SUMMARY'!$B48,'OCT DUMP'!Q:Q,"Prospect") -> 0 | Q48: =COUNTIFS('OCT DUMP'!$D:$D,'PARTNERS SUMMARY'!$B48,'OCT DUMP'!$Q:$Q,"Confirmed") -> 0 | R48: =COUNTIFS('OCT DUMP'!$D:$D,'PARTNERS SUMMARY'!$B48,'OCT DUMP'!$Q:$Q,"Rejected") -> 0 | S48: =COUNTIFS('OCT DUMP'!$D:$D,'PARTNERS SUMMARY'!$B48,'OCT DUMP'!$Q:$Q,"Unreachable") -> 0 | T48: =COUNTIFS('OCT DUMP'!$D:$D,'PARTNERS SUMMARY'!$B48,'OCT DUMP'!$Q:$Q,"Postponed(Update Y)") -> 0 | U48: =SUM(BL48:CP48) -> 0 | V48: =IFERROR(U48/O48,0) -> 0 | X48: =COUNTIF('NOV DUMP'!C:C,'PARTNERS SUMMARY'!$B48) -> 0 | Y48: =COUNTIFS('NOV DUMP'!$C:$C,'PARTNERS SUMMARY'!$B48,'NOV DUMP'!$S:$S,"Prospect") -> 0 | Z48: =COUNTIFS('NOV DUMP'!$C:$C,'PARTNERS SUMMARY'!$B48,'NOV DUMP'!$S:$S,"Confirmed") -> 0 | AA48: =COUNTIFS('NOV DUMP'!$C:$C,'PARTNERS SUMMARY'!$B48,'NOV DUMP'!$S:$S,"Rejected") -> 0 | AB48: =COUNTIFS('NOV DUMP'!$C:$C,'PARTNERS SUMMARY'!$B48,'NOV DUMP'!$S:$S,"Unreachable") -> 0 | AC48: =COUNTIFS('NOV DUMP'!$C:$C,'PARTNERS SUMMARY'!$B48,'NOV DUMP'!$S:$S,"Postponed(Update Y)") -> 0 | AD48: =SUM(CQ48:DT48) -> 0 | AE48: =COUNTIFS('ACTIVATED LEADS '!$H:$H,'PARTNERS SUMMARY'!$B48,'ACTIVATED LEADS '!$K:$K,'PARTNERS SUMMARY'!$AE$2,'ACTIVATED LEADS '!$C:$C,"16") -> 0 | AF48: =IFERROR(AD48/X48,0) -> 0 | AH48: =COUNTIFS('ACTIVATED LEADS '!$H:$H,$B48,'ACTIVATED LEADS '!$D:$D,'PARTNERS SUMMARY'!AH$3) -> 0 | AI48: =COUNTIFS('ACTIVATED LEADS '!$H:$H,$B48,'ACTIVATED LEADS '!$D:$D,'PARTNERS SUMMARY'!AI$3) -> 0 | AJ48: =COUNTIFS('ACTIVATED LEADS '!$H:$H,$B48,'ACTIVATED LEADS '!$D:$D,'PARTNERS SUMMARY'!AJ$3) -> 0 | AK48: =COUNTIFS('ACTIVATED LEADS '!$H:$H,$B48,'ACTIVATED LEADS '!$D:$D,'PARTNERS SUMMARY'!AK$3) -> 0 | AL48: =COUNTIFS('ACTIVATED LEADS '!$H:$H,$B48,'ACTIVATED LEADS '!$D:$D,'PARTNERS SUMMARY'!AL$3) -> 0 | AM48: =COUNTIFS('ACTIVATED LEADS '!$H:$H,$B48,'ACTIVATED LEADS '!$D:$D,'PARTNERS SUMMARY'!AM$3) -> 0 | AN48: =COUNTIFS('ACTIVATED LEADS '!$H:$H,$B48,'ACTIVATED LEADS '!$D:$D,'PARTNERS SUMMARY'!AN$3) -> 0 | AO48: =COUNTIFS('ACTIVATED LEADS '!$H:$H,$B48,'ACTIVATED LEADS '!$D:$D,'PARTNERS SUMMARY'!AO$3) -> 0 | ... DO48: =COUNTIFS('ACTIVATED LEADS '!$H:$H,$B48,'ACTIVATED LEADS '!$D:$D,'PARTNERS SUMMARY'!DO$3) -> 0
A49: Brian Odero | B49: PRONET DIGITAL SOLUTIONS LTD | C49: 753021646 | E49: kiambu | F49: Nairobi | G49: =COUNTIF('SEPT DUMP '!$C:$C,'PARTNERS SUMMARY'!$B49) -> 0 | H49: =COUNTIFS('SEPT DUMP '!$C:$C,'PARTNERS SUMMARY'!$B49,'SEPT DUMP '!$O:$O,"Confirmed") -> 0 | I49: =COUNTIFS('SEPT DUMP '!$C:$C,'PARTNERS SUMMARY'!$B49,'SEPT DUMP '!$O:$O,"Rejected") -> 0 | J49: =COUNTIFS('SEPT DUMP '!$C:$C,'PARTNERS SUMMARY'!$B49,'SEPT DUMP '!$O:$O,"Unreachable") -> 0 | K49: =COUNTIFS('SEPT DUMP '!$C:$C,'PARTNERS SUMMARY'!$B49,'SEPT DUMP '!$O:$O,"Postponed(Update Y)") -> 0 | L49: =SUM(AH49:BK49) -> 0 | M49: =IFERROR(L49/G49,0) -> 0 | O49: =COUNTIF('OCT DUMP'!$D:$D,'PARTNERS SUMMARY'!$B49) -> 0 | P49: =COUNTIFS('OCT DUMP'!$D:$D,'PARTNERS SUMMARY'!$B49,'OCT DUMP'!Q:Q,"Prospect") -> 0 | Q49: =COUNTIFS('OCT DUMP'!$D:$D,'PARTNERS SUMMARY'!$B49,'OCT DUMP'!$Q:$Q,"Confirmed") -> 0 | R49: =COUNTIFS('OCT DUMP'!$D:$D,'PARTNERS SUMMARY'!$B49,'OCT DUMP'!$Q:$Q,"Rejected") -> 0 | S49: =COUNTIFS('OCT DUMP'!$D:$D,'PARTNERS SUMMARY'!$B49,'OCT DUMP'!$Q:$Q,"Unreachable") -> 0 | T49: =COUNTIFS('OCT DUMP'!$D:$D,'PARTNERS SUMMARY'!$B49,'OCT DUMP'!$Q:$Q,"Postponed(Update Y)") -> 0 | U49: =SUM(BL49:CP49) -> 0 | V49: =IFERROR(U49/O49,0) -> 0 | X49: =COUNTIF('NOV DUMP'!C:C,'PARTNERS SUMMARY'!$B49) -> 0 | Y49: =COUNTIFS('NOV DUMP'!$C:$C,'PARTNERS SUMMARY'!$B49,'NOV DUMP'!$S:$S,"Prospect") -> 0 | Z49: =COUNTIFS('NOV DUMP'!$C:$C,'PARTNERS SUMMARY'!$B49,'NOV DUMP'!$S:$S,"Confirmed") -> 0 | AA49: =COUNTIFS('NOV DUMP'!$C:$C,'PARTNERS SUMMARY'!$B49,'NOV DUMP'!$S:$S,"Rejected") -> 0 | AB49: =COUNTIFS('NOV DUMP'!$C:$C,'PARTNERS SUMMARY'!$B49,'NOV DUMP'!$S:$S,"Unreachable") -> 0 | AC49: =COUNTIFS('NOV DUMP'!$C:$C,'PARTNERS SUMMARY'!$B49,'NOV DUMP'!$S:$S,"Postponed(Update Y)") -> 0 | AD49: =SUM(CQ49:DT49) -> 0 | AE49: =COUNTIFS('ACTIVATED LEADS '!$H:$H,'PARTNERS SUMMARY'!$B49,'ACTIVATED LEADS '!$K:$K,'PARTNERS SUMMARY'!$AE$2,'ACTIVATED LEADS '!$C:$C,"16") -> 0 | AF49: =IFERROR(AD49/X49,0) -> 0 | AH49: =COUNTIFS('ACTIVATED LEADS '!$H:$H,$B49,'ACTIVATED LEADS '!$D:$D,'PARTNERS SUMMARY'!AH$3) -> 0 | AI49: =COUNTIFS('ACTIVATED LEADS '!$H:$H,$B49,'ACTIVATED LEADS '!$D:$D,'PARTNERS SUMMARY'!AI$3) -> 0 | AJ49: =COUNTIFS('ACTIVATED LEADS '!$H:$H,$B49,'ACTIVATED LEADS '!$D:$D,'PARTNERS SUMMARY'!AJ$3) -> 0 | AK49: =COUNTIFS('ACTIVATED LEADS '!$H:$H,$B49,'ACTIVATED LEADS '!$D:$D,'PARTNERS SUMMARY'!AK$3) -> 0 | AL49: =COUNTIFS('ACTIVATED LEADS '!$H:$H,$B49,'ACTIVATED LEADS '!$D:$D,'PARTNERS SUMMARY'!AL$3) -> 0 | AM49: =COUNTIFS('ACTIVATED LEADS '!$H:$H,$B49,'ACTIVATED LEADS '!$D:$D,'PARTNERS SUMMARY'!AM$3) -> 0 | AN49: =COUNTIFS('ACTIVATED LEADS '!$H:$H,$B49,'ACTIVATED LEADS '!$D:$D,'PARTNERS SUMMARY'!AN$3) -> 0 | AO49: =COUNTIFS('ACTIVATED LEADS '!$H:$H,$B49,'ACTIVATED LEADS '!$D:$D,'PARTNERS SUMMARY'!AO$3) -> 0 | ... DO49: =COUNTIFS('ACTIVATED LEADS '!$H:$H,$B49,'ACTIVATED LEADS '!$D:$D,'PARTNERS SUMMARY'!DO$3) -> 0
A50: Daniel Kiragu | B50: CAKANE COMMUNICATION | C50: 102140011 | E50: Samburu | F50: Mountain | G50: =COUNTIF('SEPT DUMP '!$C:$C,'PARTNERS SUMMARY'!$B50) -> 0 | H50: =COUNTIFS('SEPT DUMP '!$C:$C,'PARTNERS SUMMARY'!$B50,'SEPT DUMP '!$O:$O,"Confirmed") -> 0 | I50: =COUNTIFS('SEPT DUMP '!$C:$C,'PARTNERS SUMMARY'!$B50,'SEPT DUMP '!$O:$O,"Rejected") -> 0 | J50: =COUNTIFS('SEPT DUMP '!$C:$C,'PARTNERS SUMMARY'!$B50,'SEPT DUMP '!$O:$O,"Unreachable") -> 0 | K50: =COUNTIFS('SEPT DUMP '!$C:$C,'PARTNERS SUMMARY'!$B50,'SEPT DUMP '!$O:$O,"Postponed(Update Y)") -> 0 | L50: =SUM(AH50:BK50) -> 0 | M50: =IFERROR(L50/G50,0) -> 0 | O50: =COUNTIF('OCT DUMP'!$D:$D,'PARTNERS SUMMARY'!$B50) -> 0 | P50: =COUNTIFS('OCT DUMP'!$D:$D,'PARTNERS SUMMARY'!$B50,'OCT DUMP'!Q:Q,"Prospect") -> 0 | Q50: =COUNTIFS('OCT DUMP'!$D:$D,'PARTNERS SUMMARY'!$B50,'OCT DUMP'!$Q:$Q,"Confirmed") -> 0 | R50: =COUNTIFS('OCT DUMP'!$D:$D,'PARTNERS SUMMARY'!$B50,'OCT DUMP'!$Q:$Q,"Rejected") -> 0 | S50: =COUNTIFS('OCT DUMP'!$D:$D,'PARTNERS SUMMARY'!$B50,'OCT DUMP'!$Q:$Q,"Unreachable") -> 0 | T50: =COUNTIFS('OCT DUMP'!$D:$D,'PARTNERS SUMMARY'!$B50,'OCT DUMP'!$Q:$Q,"Postponed(Update Y)") -> 0 | U50: =SUM(BL50:CP50) -> 0 | V50: =IFERROR(U50/O50,0) -> 0 | X50: =COUNTIF('NOV DUMP'!C:C,'PARTNERS SUMMARY'!$B50) -> 0 | Y50: =COUNTIFS('NOV DUMP'!$C:$C,'PARTNERS SUMMARY'!$B50,'NOV DUMP'!$S:$S,"Prospect") -> 0 | Z50: =COUNTIFS('NOV DUMP'!$C:$C,'PARTNERS SUMMARY'!$B50,'NOV DUMP'!$S:$S,"Confirmed") -> 0 | AA50: =COUNTIFS('NOV DUMP'!$C:$C,'PARTNERS SUMMARY'!$B50,'NOV DUMP'!$S:$S,"Rejected") -> 0 | AB50: =COUNTIFS('NOV DUMP'!$C:$C,'PARTNERS SUMMARY'!$B50,'NOV DUMP'!$S:$S,"Unreachable") -> 0 | AC50: =COUNTIFS('NOV DUMP'!$C:$C,'PARTNERS SUMMARY'!$B50,'NOV DUMP'!$S:$S,"Postponed(Update Y)") -> 0 | AD50: =SUM(CQ50:DT50) -> 0 | AE50: =COUNTIFS('ACTIVATED LEADS '!$H:$H,'PARTNERS SUMMARY'!$B50,'ACTIVATED LEADS '!$K:$K,'PARTNERS SUMMARY'!$AE$2,'ACTIVATED LEADS '!$C:$C,"16") -> 0 | AF50: =IFERROR(AD50/X50,0) -> 0 | AH50: =COUNTIFS('ACTIVATED LEADS '!$H:$H,$B50,'ACTIVATED LEADS '!$D:$D,'PARTNERS SUMMARY'!AH$3) -> 0 | AI50: =COUNTIFS('ACTIVATED LEADS '!$H:$H,$B50,'ACTIVATED LEADS '!$D:$D,'PARTNERS SUMMARY'!AI$3) -> 0 | AJ50: =COUNTIFS('ACTIVATED LEADS '!$H:$H,$B50,'ACTIVATED LEADS '!$D:$D,'PARTNERS SUMMARY'!AJ$3) -> 0 | AK50: =COUNTIFS('ACTIVATED LEADS '!$H:$H,$B50,'ACTIVATED LEADS '!$D:$D,'PARTNERS SUMMARY'!AK$3) -> 0 | AL50: =COUNTIFS('ACTIVATED LEADS '!$H:$H,$B50,'ACTIVATED LEADS '!$D:$D,'PARTNERS SUMMARY'!AL$3) -> 0 | AM50: =COUNTIFS('ACTIVATED LEADS '!$H:$H,$B50,'ACTIVATED LEADS '!$D:$D,'PARTNERS SUMMARY'!AM$3) -> 0 | AN50: =COUNTIFS('ACTIVATED LEADS '!$H:$H,$B50,'ACTIVATED LEADS '!$D:$D,'PARTNERS SUMMARY'!AN$3) -> 0 | AO50: =COUNTIFS('ACTIVATED LEADS '!$H:$H,$B50,'ACTIVATED LEADS '!$D:$D,'PARTNERS SUMMARY'!AO$3) -> 0 | ... DO50: =COUNTIFS('ACTIVATED LEADS '!$H:$H,$B50,'ACTIVATED LEADS '!$D:$D,'PARTNERS SUMMARY'!DO$3) -> 0
A51: Damaris Mainga | B51: GUZZER TECHNOLOGIES | C51: 752213225 | F51: Nairobi | G51: =COUNTIF('SEPT DUMP '!$C:$C,'PARTNERS SUMMARY'!$B51) -> 0 | H51: =COUNTIFS('SEPT DUMP '!$C:$C,'PARTNERS SUMMARY'!$B51,'SEPT DUMP '!$O:$O,"Confirmed") -> 0 | I51: =COUNTIFS('SEPT DUMP '!$C:$C,'PARTNERS SUMMARY'!$B51,'SEPT DUMP '!$O:$O,"Rejected") -> 0 | J51: =COUNTIFS('SEPT DUMP '!$C:$C,'PARTNERS SUMMARY'!$B51,'SEPT DUMP '!$O:$O,"Unreachable") -> 0 | K51: =COUNTIFS('SEPT DUMP '!$C:$C,'PARTNERS SUMMARY'!$B51,'SEPT DUMP '!$O:$O,"Postponed(Update Y)") -> 0 | L51: =SUM(AH51:BK51) -> 0 | M51: =IFERROR(L51/G51,0) -> 0 | O51: =COUNTIF('OCT DUMP'!$D:$D,'PARTNERS SUMMARY'!$B51) -> 0 | P51: =COUNTIFS('OCT DUMP'!$D:$D,'PARTNERS SUMMARY'!$B51,'OCT DUMP'!Q:Q,"Prospect") -> 0 | Q51: =COUNTIFS('OCT DUMP'!$D:$D,'PARTNERS SUMMARY'!$B51,'OCT DUMP'!$Q:$Q,"Confirmed") -> 0 | R51: =COUNTIFS('OCT DUMP'!$D:$D,'PARTNERS SUMMARY'!$B51,'OCT DUMP'!$Q:$Q,"Rejected") -> 0 | S51: =COUNTIFS('OCT DUMP'!$D:$D,'PARTNERS SUMMARY'!$B51,'OCT DUMP'!$Q:$Q,"Unreachable") -> 0 | T51: =COUNTIFS('OCT DUMP'!$D:$D,'PARTNERS SUMMARY'!$B51,'OCT DUMP'!$Q:$Q,"Postponed(Update Y)") -> 0 | U51: =SUM(BL51:CP51) -> 0 | V51: =IFERROR(U51/O51,0) -> 0 | X51: =COUNTIF('NOV DUMP'!C:C,'PARTNERS SUMMARY'!$B51) -> 0 | Y51: =COUNTIFS('NOV DUMP'!$C:$C,'PARTNERS SUMMARY'!$B51,'NOV DUMP'!$S:$S,"Prospect") -> 0 | Z51: =COUNTIFS('NOV DUMP'!$C:$C,'PARTNERS SUMMARY'!$B51,'NOV DUMP'!$S:$S,"Confirmed") -> 0 | AA51: =COUNTIFS('NOV DUMP'!$C:$C,'PARTNERS SUMMARY'!$B51,'NOV DUMP'!$S:$S,"Rejected") -> 0 | AB51: =COUNTIFS('NOV DUMP'!$C:$C,'PARTNERS SUMMARY'!$B51,'NOV DUMP'!$S:$S,"Unreachable") -> 0 | AC51: =COUNTIFS('NOV DUMP'!$C:$C,'PARTNERS SUMMARY'!$B51,'NOV DUMP'!$S:$S,"Postponed(Update Y)") -> 0 | AD51: =SUM(CQ51:DT51) -> 0 | AE51: =COUNTIFS('ACTIVATED LEADS '!$H:$H,'PARTNERS SUMMARY'!$B51,'ACTIVATED LEADS '!$K:$K,'PARTNERS SUMMARY'!$AE$2,'ACTIVATED LEADS '!$C:$C,"16") -> 0 | AF51: =IFERROR(AD51/X51,0) -> 0 | AH51: =COUNTIFS('ACTIVATED LEADS '!$H:$H,$B51,'ACTIVATED LEADS '!$D:$D,'PARTNERS SUMMARY'!AH$3) -> 0 | AI51: =COUNTIFS('ACTIVATED LEADS '!$H:$H,$B51,'ACTIVATED LEADS '!$D:$D,'PARTNERS SUMMARY'!AI$3) -> 0 | AJ51: =COUNTIFS('ACTIVATED LEADS '!$H:$H,$B51,'ACTIVATED LEADS '!$D:$D,'PARTNERS SUMMARY'!AJ$3) -> 0 | AK51: =COUNTIFS('ACTIVATED LEADS '!$H:$H,$B51,'ACTIVATED LEADS '!$D:$D,'PARTNERS SUMMARY'!AK$3) -> 0 | AL51: =COUNTIFS('ACTIVATED LEADS '!$H:$H,$B51,'ACTIVATED LEADS '!$D:$D,'PARTNERS SUMMARY'!AL$3) -> 0 | AM51: =COUNTIFS('ACTIVATED LEADS '!$H:$H,$B51,'ACTIVATED LEADS '!$D:$D,'PARTNERS SUMMARY'!AM$3) -> 0 | AN51: =COUNTIFS('ACTIVATED LEADS '!$H:$H,$B51,'ACTIVATED LEADS '!$D:$D,'PARTNERS SUMMARY'!AN$3) -> 0 | AO51: =COUNTIFS('ACTIVATED LEADS '!$H:$H,$B51,'ACTIVATED LEADS '!$D:$D,'PARTNERS SUMMARY'!AO$3) -> 0 | ... DO51: =COUNTIFS('ACTIVATED LEADS '!$H:$H,$B51,'ACTIVATED LEADS '!$D:$D,'PARTNERS SUMMARY'!DO$3) -> 0
A52: Betreace Chebet | B52: BAZZTECH NETWORKS | C52: 762822580 | E52: Nakuru Town | F52: Rift | G52: =COUNTIF('SEPT DUMP '!$C:$C,'PARTNERS SUMMARY'!$B52) -> 0 | H52: =COUNTIFS('SEPT DUMP '!$C:$C,'PARTNERS SUMMARY'!$B52,'SEPT DUMP '!$O:$O,"Confirmed") -> 0 | I52: =COUNTIFS('SEPT DUMP '!$C:$C,'PARTNERS SUMMARY'!$B52,'SEPT DUMP '!$O:$O,"Rejected") -> 0 | J52: =COUNTIFS('SEPT DUMP '!$C:$C,'PARTNERS SUMMARY'!$B52,'SEPT DUMP '!$O:$O,"Unreachable") -> 0 | K52: =COUNTIFS('SEPT DUMP '!$C:$C,'PARTNERS SUMMARY'!$B52,'SEPT DUMP '!$O:$O,"Postponed(Update Y)") -> 0 | L52: =SUM(AH52:BK52) -> 0 | M52: =IFERROR(L52/G52,0) -> 0 | O52: =COUNTIF('OCT DUMP'!$D:$D,'PARTNERS SUMMARY'!$B52) -> 0 | P52: =COUNTIFS('OCT DUMP'!$D:$D,'PARTNERS SUMMARY'!$B52,'OCT DUMP'!Q:Q,"Prospect") -> 0 | Q52: =COUNTIFS('OCT DUMP'!$D:$D,'PARTNERS SUMMARY'!$B52,'OCT DUMP'!$Q:$Q,"Confirmed") -> 0 | R52: =COUNTIFS('OCT DUMP'!$D:$D,'PARTNERS SUMMARY'!$B52,'OCT DUMP'!$Q:$Q,"Rejected") -> 0 | S52: =COUNTIFS('OCT DUMP'!$D:$D,'PARTNERS SUMMARY'!$B52,'OCT DUMP'!$Q:$Q,"Unreachable") -> 0 | T52: =COUNTIFS('OCT DUMP'!$D:$D,'PARTNERS SUMMARY'!$B52,'OCT DUMP'!$Q:$Q,"Postponed(Update Y)") -> 0 | U52: =SUM(BL52:CP52) -> 0 | V52: =IFERROR(U52/O52,0) -> 0 | X52: =COUNTIF('NOV DUMP'!C:C,'PARTNERS SUMMARY'!$B52) -> 2 | Y52: =COUNTIFS('NOV DUMP'!$C:$C,'PARTNERS SUMMARY'!$B52,'NOV DUMP'!$S:$S,"Prospect") -> 0 | Z52: =COUNTIFS('NOV DUMP'!$C:$C,'PARTNERS SUMMARY'!$B52,'NOV DUMP'!$S:$S,"Confirmed") -> 1 | AA52: =COUNTIFS('NOV DUMP'!$C:$C,'PARTNERS SUMMARY'!$B52,'NOV DUMP'!$S:$S,"Rejected") -> 0 | AB52: =COUNTIFS('NOV DUMP'!$C:$C,'PARTNERS SUMMARY'!$B52,'NOV DUMP'!$S:$S,"Unreachable") -> 0 | AC52: =COUNTIFS('NOV DUMP'!$C:$C,'PARTNERS SUMMARY'!$B52,'NOV DUMP'!$S:$S,"Postponed(Update Y)") -> 0 | AD52: =SUM(CQ52:DT52) -> 1 | AE52: =COUNTIFS('ACTIVATED LEADS '!$H:$H,'PARTNERS SUMMARY'!$B52,'ACTIVATED LEADS '!$K:$K,'PARTNERS SUMMARY'!$AE$2,'ACTIVATED LEADS '!$C:$C,"16") -> 1 | AF52: =IFERROR(AD52/X52,0) -> 0.5 | AH52: =COUNTIFS('ACTIVATED LEADS '!$H:$H,$B52,'ACTIVATED LEADS '!$D:$D,'PARTNERS SUMMARY'!AH$3) -> 0 | AI52: =COUNTIFS('ACTIVATED LEADS '!$H:$H,$B52,'ACTIVATED LEADS '!$D:$D,'PARTNERS SUMMARY'!AI$3) -> 0 | AJ52: =COUNTIFS('ACTIVATED LEADS '!$H:$H,$B52,'ACTIVATED LEADS '!$D:$D,'PARTNERS SUMMARY'!AJ$3) -> 0 | AK52: =COUNTIFS('ACTIVATED LEADS '!$H:$H,$B52,'ACTIVATED LEADS '!$D:$D,'PARTNERS SUMMARY'!AK$3) -> 0 | AL52: =COUNTIFS('ACTIVATED LEADS '!$H:$H,$B52,'ACTIVATED LEADS '!$D:$D,'PARTNERS SUMMARY'!AL$3) -> 0 | AM52: =COUNTIFS('ACTIVATED LEADS '!$H:$H,$B52,'ACTIVATED LEADS '!$D:$D,'PARTNERS SUMMARY'!AM$3) -> 0 | AN52: =COUNTIFS('ACTIVATED LEADS '!$H:$H,$B52,'ACTIVATED LEADS '!$D:$D,'PARTNERS SUMMARY'!AN$3) -> 0 | AO52: =COUNTIFS('ACTIVATED LEADS '!$H:$H,$B52,'ACTIVATED LEADS '!$D:$D,'PARTNERS SUMMARY'!AO$3) -> 0 | ... DO52: =COUNTIFS('ACTIVATED LEADS '!$H:$H,$B52,'ACTIVATED LEADS '!$D:$D,'PARTNERS SUMMARY'!DO$3) -> 0
A53: Betreace Chebet | B53: KAFITI ENTERPRISES | C53: 762309130 | E53: Nakuru Town | F53: Rift | G53: =COUNTIF('SEPT DUMP '!$C:$C,'PARTNERS SUMMARY'!$B53) -> 0 | H53: =COUNTIFS('SEPT DUMP '!$C:$C,'PARTNERS SUMMARY'!$B53,'SEPT DUMP '!$O:$O,"Confirmed") -> 0 | I53: =COUNTIFS('SEPT DUMP '!$C:$C,'PARTNERS SUMMARY'!$B53,'SEPT DUMP '!$O:$O,"Rejected") -> 0 | J53: =COUNTIFS('SEPT DUMP '!$C:$C,'PARTNERS SUMMARY'!$B53,'SEPT DUMP '!$O:$O,"Unreachable") -> 0 | K53: =COUNTIFS('SEPT DUMP '!$C:$C,'PARTNERS SUMMARY'!$B53,'SEPT DUMP '!$O:$O,"Postponed(Update Y)") -> 0 | L53: =SUM(AH53:BK53) -> 0 | M53: =IFERROR(L53/G53,0) -> 0 | O53: =COUNTIF('OCT DUMP'!$D:$D,'PARTNERS SUMMARY'!$B53) -> 0 | P53: =COUNTIFS('OCT DUMP'!$D:$D,'PARTNERS SUMMARY'!$B53,'OCT DUMP'!Q:Q,"Prospect") -> 0 | Q53: =COUNTIFS('OCT DUMP'!$D:$D,'PARTNERS SUMMARY'!$B53,'OCT DUMP'!$Q:$Q,"Confirmed") -> 0 | R53: =COUNTIFS('OCT DUMP'!$D:$D,'PARTNERS SUMMARY'!$B53,'OCT DUMP'!$Q:$Q,"Rejected") -> 0 | S53: =COUNTIFS('OCT DUMP'!$D:$D,'PARTNERS SUMMARY'!$B53,'OCT DUMP'!$Q:$Q,"Unreachable") -> 0 | T53: =COUNTIFS('OCT DUMP'!$D:$D,'PARTNERS SUMMARY'!$B53,'OCT DUMP'!$Q:$Q,"Postponed(Update Y)") -> 0 | U53: =SUM(BL53:CP53) -> 0 | V53: =IFERROR(U53/O53,0) -> 0 | X53: =COUNTIF('NOV DUMP'!C:C,'PARTNERS SUMMARY'!$B53) -> 0 | Y53: =COUNTIFS('NOV DUMP'!$C:$C,'PARTNERS SUMMARY'!$B53,'NOV DUMP'!$S:$S,"Prospect") -> 0 | Z53: =COUNTIFS('NOV DUMP'!$C:$C,'PARTNERS SUMMARY'!$B53,'NOV DUMP'!$S:$S,"Confirmed") -> 0 | AA53: =COUNTIFS('NOV DUMP'!$C:$C,'PARTNERS SUMMARY'!$B53,'NOV DUMP'!$S:$S,"Rejected") -> 0 | AB53: =COUNTIFS('NOV DUMP'!$C:$C,'PARTNERS SUMMARY'!$B53,'NOV DUMP'!$S:$S,"Unreachable") -> 0 | AC53: =COUNTIFS('NOV DUMP'!$C:$C,'PARTNERS SUMMARY'!$B53,'NOV DUMP'!$S:$S,"Postponed(Update Y)") -> 0 | AD53: =SUM(CQ53:DT53) -> 0 | AE53: =COUNTIFS('ACTIVATED LEADS '!$H:$H,'PARTNERS SUMMARY'!$B53,'ACTIVATED LEADS '!$K:$K,'PARTNERS SUMMARY'!$AE$2,'ACTIVATED LEADS '!$C:$C,"16") -> 0 | AF53: =IFERROR(AD53/X53,0) -> 0 | AH53: =COUNTIFS('ACTIVATED LEADS '!$H:$H,$B53,'ACTIVATED LEADS '!$D:$D,'PARTNERS SUMMARY'!AH$3) -> 0 | AI53: =COUNTIFS('ACTIVATED LEADS '!$H:$H,$B53,'ACTIVATED LEADS '!$D:$D,'PARTNERS SUMMARY'!AI$3) -> 0 | AJ53: =COUNTIFS('ACTIVATED LEADS '!$H:$H,$B53,'ACTIVATED LEADS '!$D:$D,'PARTNERS SUMMARY'!AJ$3) -> 0 | AK53: =COUNTIFS('ACTIVATED LEADS '!$H:$H,$B53,'ACTIVATED LEADS '!$D:$D,'PARTNERS SUMMARY'!AK$3) -> 0 | AL53: =COUNTIFS('ACTIVATED LEADS '!$H:$H,$B53,'ACTIVATED LEADS '!$D:$D,'PARTNERS SUMMARY'!AL$3) -> 0 | AM53: =COUNTIFS('ACTIVATED LEADS '!$H:$H,$B53,'ACTIVATED LEADS '!$D:$D,'PARTNERS SUMMARY'!AM$3) -> 0 | AN53: =COUNTIFS('ACTIVATED LEADS '!$H:$H,$B53,'ACTIVATED LEADS '!$D:$D,'PARTNERS SUMMARY'!AN$3) -> 0 | AO53: =COUNTIFS('ACTIVATED LEADS '!$H:$H,$B53,'ACTIVATED LEADS '!$D:$D,'PARTNERS SUMMARY'!AO$3) -> 0 | ... DO53: =COUNTIFS('ACTIVATED LEADS '!$H:$H,$B53,'ACTIVATED LEADS '!$D:$D,'PARTNERS SUMMARY'!DO$3) -> 0
A54: Damaris Mainga | B54: BLUROK AFRICA LTD | C54: 101128131 | E54: Two rivers | F54: Nairobi | G54: =COUNTIF('SEPT DUMP '!$C:$C,'PARTNERS SUMMARY'!$B54) -> 0 | H54: =COUNTIFS('SEPT DUMP '!$C:$C,'PARTNERS SUMMARY'!$B54,'SEPT DUMP '!$O:$O,"Confirmed") -> 0 | I54: =COUNTIFS('SEPT DUMP '!$C:$C,'PARTNERS SUMMARY'!$B54,'SEPT DUMP '!$O:$O,"Rejected") -> 0 | J54: =COUNTIFS('SEPT DUMP '!$C:$C,'PARTNERS SUMMARY'!$B54,'SEPT DUMP '!$O:$O,"Unreachable") -> 0 | K54: =COUNTIFS('SEPT DUMP '!$C:$C,'PARTNERS SUMMARY'!$B54,'SEPT DUMP '!$O:$O,"Postponed(Update Y)") -> 0 | L54: =SUM(AH54:BK54) -> 0 | M54: =IFERROR(L54/G54,0) -> 0 | O54: =COUNTIF('OCT DUMP'!$D:$D,'PARTNERS SUMMARY'!$B54) -> 0 | P54: =COUNTIFS('OCT DUMP'!$D:$D,'PARTNERS SUMMARY'!$B54,'OCT DUMP'!Q:Q,"Prospect") -> 0 | Q54: =COUNTIFS('OCT DUMP'!$D:$D,'PARTNERS SUMMARY'!$B54,'OCT DUMP'!$Q:$Q,"Confirmed") -> 0 | R54: =COUNTIFS('OCT DUMP'!$D:$D,'PARTNERS SUMMARY'!$B54,'OCT DUMP'!$Q:$Q,"Rejected") -> 0 | S54: =COUNTIFS('OCT DUMP'!$D:$D,'PARTNERS SUMMARY'!$B54,'OCT DUMP'!$Q:$Q,"Unreachable") -> 0 | T54: =COUNTIFS('OCT DUMP'!$D:$D,'PARTNERS SUMMARY'!$B54,'OCT DUMP'!$Q:$Q,"Postponed(Update Y)") -> 0 | U54: =SUM(BL54:CP54) -> 0 | V54: =IFERROR(U54/O54,0) -> 0 | X54: =COUNTIF('NOV DUMP'!C:C,'PARTNERS SUMMARY'!$B54) -> 0 | Y54: =COUNTIFS('NOV DUMP'!$C:$C,'PARTNERS SUMMARY'!$B54,'NOV DUMP'!$S:$S,"Prospect") -> 0 | Z54: =COUNTIFS('NOV DUMP'!$C:$C,'PARTNERS SUMMARY'!$B54,'NOV DUMP'!$S:$S,"Confirmed") -> 0 | AA54: =COUNTIFS('NOV DUMP'!$C:$C,'PARTNERS SUMMARY'!$B54,'NOV DUMP'!$S:$S,"Rejected") -> 0 | AB54: =COUNTIFS('NOV DUMP'!$C:$C,'PARTNERS SUMMARY'!$B54,'NOV DUMP'!$S:$S,"Unreachable") -> 0 | AC54: =COUNTIFS('NOV DUMP'!$C:$C,'PARTNERS SUMMARY'!$B54,'NOV DUMP'!$S:$S,"Postponed(Update Y)") -> 0 | AD54: =SUM(CQ54:DT54) -> 0 | AE54: =COUNTIFS('ACTIVATED LEADS '!$H:$H,'PARTNERS SUMMARY'!$B54,'ACTIVATED LEADS '!$K:$K,'PARTNERS SUMMARY'!$AE$2,'ACTIVATED LEADS '!$C:$C,"16") -> 0 | AF54: =IFERROR(AD54/X54,0) -> 0 | AH54: =COUNTIFS('ACTIVATED LEADS '!$H:$H,$B54,'ACTIVATED LEADS '!$D:$D,'PARTNERS SUMMARY'!AH$3) -> 0 | AI54: =COUNTIFS('ACTIVATED LEADS '!$H:$H,$B54,'ACTIVATED LEADS '!$D:$D,'PARTNERS SUMMARY'!AI$3) -> 0 | AJ54: =COUNTIFS('ACTIVATED LEADS '!$H:$H,$B54,'ACTIVATED LEADS '!$D:$D,'PARTNERS SUMMARY'!AJ$3) -> 0 | AK54: =COUNTIFS('ACTIVATED LEADS '!$H:$H,$B54,'ACTIVATED LEADS '!$D:$D,'PARTNERS SUMMARY'!AK$3) -> 0 | AL54: =COUNTIFS('ACTIVATED LEADS '!$H:$H,$B54,'ACTIVATED LEADS '!$D:$D,'PARTNERS SUMMARY'!AL$3) -> 0 | AM54: =COUNTIFS('ACTIVATED LEADS '!$H:$H,$B54,'ACTIVATED LEADS '!$D:$D,'PARTNERS SUMMARY'!AM$3) -> 0 | AN54: =COUNTIFS('ACTIVATED LEADS '!$H:$H,$B54,'ACTIVATED LEADS '!$D:$D,'PARTNERS SUMMARY'!AN$3) -> 0 | AO54: =COUNTIFS('ACTIVATED LEADS '!$H:$H,$B54,'ACTIVATED LEADS '!$D:$D,'PARTNERS SUMMARY'!AO$3) -> 0 | ... DO54: =COUNTIFS('ACTIVATED LEADS '!$H:$H,$B54,'ACTIVATED LEADS '!$D:$D,'PARTNERS SUMMARY'!DO$3) -> 0
A55: Mariana Hongo | B55: STRENGTH HEIGHTS | C55: 755961229 | E55: Kisumu | F55: Western | G55: =COUNTIF('SEPT DUMP '!$C:$C,'PARTNERS SUMMARY'!$B55) -> 0 | H55: =COUNTIFS('SEPT DUMP '!$C:$C,'PARTNERS SUMMARY'!$B55,'SEPT DUMP '!$O:$O,"Confirmed") -> 0 | I55: =COUNTIFS('SEPT DUMP '!$C:$C,'PARTNERS SUMMARY'!$B55,'SEPT DUMP '!$O:$O,"Rejected") -> 0 | J55: =COUNTIFS('SEPT DUMP '!$C:$C,'PARTNERS SUMMARY'!$B55,'SEPT DUMP '!$O:$O,"Unreachable") -> 0 | K55: =COUNTIFS('SEPT DUMP '!$C:$C,'PARTNERS SUMMARY'!$B55,'SEPT DUMP '!$O:$O,"Postponed(Update Y)") -> 0 | L55: =SUM(AH55:BK55) -> 0 | M55: =IFERROR(L55/G55,0) -> 0 | O55: =COUNTIF('OCT DUMP'!$D:$D,'PARTNERS SUMMARY'!$B55) -> 0 | P55: =COUNTIFS('OCT DUMP'!$D:$D,'PARTNERS SUMMARY'!$B55,'OCT DUMP'!Q:Q,"Prospect") -> 0 | Q55: =COUNTIFS('OCT DUMP'!$D:$D,'PARTNERS SUMMARY'!$B55,'OCT DUMP'!$Q:$Q,"Confirmed") -> 0 | R55: =COUNTIFS('OCT DUMP'!$D:$D,'PARTNERS SUMMARY'!$B55,'OCT DUMP'!$Q:$Q,"Rejected") -> 0 | S55: =COUNTIFS('OCT DUMP'!$D:$D,'PARTNERS SUMMARY'!$B55,'OCT DUMP'!$Q:$Q,"Unreachable") -> 0 | T55: =COUNTIFS('OCT DUMP'!$D:$D,'PARTNERS SUMMARY'!$B55,'OCT DUMP'!$Q:$Q,"Postponed(Update Y)") -> 0 | U55: =SUM(BL55:CP55) -> 0 | V55: =IFERROR(U55/O55,0) -> 0 | X55: =COUNTIF('NOV DUMP'!C:C,'PARTNERS SUMMARY'!$B55) -> 0 | Y55: =COUNTIFS('NOV DUMP'!$C:$C,'PARTNERS SUMMARY'!$B55,'NOV DUMP'!$S:$S,"Prospect") -> 0 | Z55: =COUNTIFS('NOV DUMP'!$C:$C,'PARTNERS SUMMARY'!$B55,'NOV DUMP'!$S:$S,"Confirmed") -> 0 | AA55: =COUNTIFS('NOV DUMP'!$C:$C,'PARTNERS SUMMARY'!$B55,'NOV DUMP'!$S:$S,"Rejected") -> 0 | AB55: =COUNTIFS('NOV DUMP'!$C:$C,'PARTNERS SUMMARY'!$B55,'NOV DUMP'!$S:$S,"Unreachable") -> 0 | AC55: =COUNTIFS('NOV DUMP'!$C:$C,'PARTNERS SUMMARY'!$B55,'NOV DUMP'!$S:$S,"Postponed(Update Y)") -> 0 | AD55: =SUM(CQ55:DT55) -> 0 | AE55: =COUNTIFS('ACTIVATED LEADS '!$H:$H,'PARTNERS SUMMARY'!$B55,'ACTIVATED LEADS '!$K:$K,'PARTNERS SUMMARY'!$AE$2,'ACTIVATED LEADS '!$C:$C,"16") -> 0 | AF55: =IFERROR(AD55/X55,0) -> 0 | AH55: =COUNTIFS('ACTIVATED LEADS '!$H:$H,$B55,'ACTIVATED LEADS '!$D:$D,'PARTNERS SUMMARY'!AH$3) -> 0 | AI55: =COUNTIFS('ACTIVATED LEADS '!$H:$H,$B55,'ACTIVATED LEADS '!$D:$D,'PARTNERS SUMMARY'!AI$3) -> 0 | AJ55: =COUNTIFS('ACTIVATED LEADS '!$H:$H,$B55,'ACTIVATED LEADS '!$D:$D,'PARTNERS SUMMARY'!AJ$3) -> 0 | AK55: =COUNTIFS('ACTIVATED LEADS '!$H:$H,$B55,'ACTIVATED LEADS '!$D:$D,'PARTNERS SUMMARY'!AK$3) -> 0 | AL55: =COUNTIFS('ACTIVATED LEADS '!$H:$H,$B55,'ACTIVATED LEADS '!$D:$D,'PARTNERS SUMMARY'!AL$3) -> 0 | AM55: =COUNTIFS('ACTIVATED LEADS '!$H:$H,$B55,'ACTIVATED LEADS '!$D:$D,'PARTNERS SUMMARY'!AM$3) -> 0 | AN55: =COUNTIFS('ACTIVATED LEADS '!$H:$H,$B55,'ACTIVATED LEADS '!$D:$D,'PARTNERS SUMMARY'!AN$3) -> 0 | AO55: =COUNTIFS('ACTIVATED LEADS '!$H:$H,$B55,'ACTIVATED LEADS '!$D:$D,'PARTNERS SUMMARY'!AO$3) -> 0 | ... DO55: =COUNTIFS('ACTIVATED LEADS '!$H:$H,$B55,'ACTIVATED LEADS '!$D:$D,'PARTNERS SUMMARY'!DO$3) -> 0
A56: Damaris Mainga | B56: EVENT CREST LIMITED | C56: 739762105 | E56: KIAMBU RD | F56: Nairobi | G56: =COUNTIF('SEPT DUMP '!$C:$C,'PARTNERS SUMMARY'!$B56) -> 0 | H56: =COUNTIFS('SEPT DUMP '!$C:$C,'PARTNERS SUMMARY'!$B56,'SEPT DUMP '!$O:$O,"Confirmed") -> 0 | I56: =COUNTIFS('SEPT DUMP '!$C:$C,'PARTNERS SUMMARY'!$B56,'SEPT DUMP '!$O:$O,"Rejected") -> 0 | J56: =COUNTIFS('SEPT DUMP '!$C:$C,'PARTNERS SUMMARY'!$B56,'SEPT DUMP '!$O:$O,"Unreachable") -> 0 | K56: =COUNTIFS('SEPT DUMP '!$C:$C,'PARTNERS SUMMARY'!$B56,'SEPT DUMP '!$O:$O,"Postponed(Update Y)") -> 0 | L56: =SUM(AH56:BK56) -> 0 | M56: =IFERROR(L56/G56,0) -> 0 | O56: =COUNTIF('OCT DUMP'!$D:$D,'PARTNERS SUMMARY'!$B56) -> 14 | P56: =COUNTIFS('OCT DUMP'!$D:$D,'PARTNERS SUMMARY'!$B56,'OCT DUMP'!Q:Q,"Prospect") -> 0 | Q56: =COUNTIFS('OCT DUMP'!$D:$D,'PARTNERS SUMMARY'!$B56,'OCT DUMP'!$Q:$Q,"Confirmed") -> 5 | R56: =COUNTIFS('OCT DUMP'!$D:$D,'PARTNERS SUMMARY'!$B56,'OCT DUMP'!$Q:$Q,"Rejected") -> 0 | S56: =COUNTIFS('OCT DUMP'!$D:$D,'PARTNERS SUMMARY'!$B56,'OCT DUMP'!$Q:$Q,"Unreachable") -> 8 | T56: =COUNTIFS('OCT DUMP'!$D:$D,'PARTNERS SUMMARY'!$B56,'OCT DUMP'!$Q:$Q,"Postponed(Update Y)") -> 1 | U56: =SUM(BL56:CP56) -> 1 | V56: =IFERROR(U56/O56,0) -> 0.071428571 | X56: =COUNTIF('NOV DUMP'!C:C,'PARTNERS SUMMARY'!$B56) -> 19 | Y56: =COUNTIFS('NOV DUMP'!$C:$C,'PARTNERS SUMMARY'!$B56,'NOV DUMP'!$S:$S,"Prospect") -> 0 | Z56: =COUNTIFS('NOV DUMP'!$C:$C,'PARTNERS SUMMARY'!$B56,'NOV DUMP'!$S:$S,"Confirmed") -> 4 | AA56: =COUNTIFS('NOV DUMP'!$C:$C,'PARTNERS SUMMARY'!$B56,'NOV DUMP'!$S:$S,"Rejected") -> 1 | AB56: =COUNTIFS('NOV DUMP'!$C:$C,'PARTNERS SUMMARY'!$B56,'NOV DUMP'!$S:$S,"Unreachable") -> 0 | AC56: =COUNTIFS('NOV DUMP'!$C:$C,'PARTNERS SUMMARY'!$B56,'NOV DUMP'!$S:$S,"Postponed(Update Y)") -> 0 | AD56: =SUM(CQ56:DT56) -> 6 | AE56: =COUNTIFS('ACTIVATED LEADS '!$H:$H,'PARTNERS SUMMARY'!$B56,'ACTIVATED LEADS '!$K:$K,'PARTNERS SUMMARY'!$AE$2,'ACTIVATED LEADS '!$C:$C,"16") -> 3 | AF56: =IFERROR(AD56/X56,0) -> 0.31578947 | AH56: =COUNTIFS('ACTIVATED LEADS '!$H:$H,$B56,'ACTIVATED LEADS '!$D:$D,'PARTNERS SUMMARY'!AH$3) -> 0 | AI56: =COUNTIFS('ACTIVATED LEADS '!$H:$H,$B56,'ACTIVATED LEADS '!$D:$D,'PARTNERS SUMMARY'!AI$3) -> 0 | AJ56: =COUNTIFS('ACTIVATED LEADS '!$H:$H,$B56,'ACTIVATED LEADS '!$D:$D,'PARTNERS SUMMARY'!AJ$3) -> 0 | AK56: =COUNTIFS('ACTIVATED LEADS '!$H:$H,$B56,'ACTIVATED LEADS '!$D:$D,'PARTNERS SUMMARY'!AK$3) -> 0 | AL56: =COUNTIFS('ACTIVATED LEADS '!$H:$H,$B56,'ACTIVATED LEADS '!$D:$D,'PARTNERS SUMMARY'!AL$3) -> 0 | AM56: =COUNTIFS('ACTIVATED LEADS '!$H:$H,$B56,'ACTIVATED LEADS '!$D:$D,'PARTNERS SUMMARY'!AM$3) -> 0 | AN56: =COUNTIFS('ACTIVATED LEADS '!$H:$H,$B56,'ACTIVATED LEADS '!$D:$D,'PARTNERS SUMMARY'!AN$3) -> 0 | AO56: =COUNTIFS('ACTIVATED LEADS '!$H:$H,$B56,'ACTIVATED LEADS '!$D:$D,'PARTNERS SUMMARY'!AO$3) -> 0 | ... DO56: =COUNTIFS('ACTIVATED LEADS '!$H:$H,$B56,'ACTIVATED LEADS '!$D:$D,'PARTNERS SUMMARY'!DO$3) -> 1
A57: Damaris Mainga | B57: KZ TECHNOLOGIES LTD | C57: 789986900 | E57: NextGEN Mall | F57: Nairobi | G57: =COUNTIF('SEPT DUMP '!$C:$C,'PARTNERS SUMMARY'!$B57) -> 0 | H57: =COUNTIFS('SEPT DUMP '!$C:$C,'PARTNERS SUMMARY'!$B57,'SEPT DUMP '!$O:$O,"Confirmed") -> 0 | I57: =COUNTIFS('SEPT DUMP '!$C:$C,'PARTNERS SUMMARY'!$B57,'SEPT DUMP '!$O:$O,"Rejected") -> 0 | J57: =COUNTIFS('SEPT DUMP '!$C:$C,'PARTNERS SUMMARY'!$B57,'SEPT DUMP '!$O:$O,"Unreachable") -> 0 | K57: =COUNTIFS('SEPT DUMP '!$C:$C,'PARTNERS SUMMARY'!$B57,'SEPT DUMP '!$O:$O,"Postponed(Update Y)") -> 0 | L57: =SUM(AH57:BK57) -> 0 | M57: =IFERROR(L57/G57,0) -> 0 | O57: =COUNTIF('OCT DUMP'!$D:$D,'PARTNERS SUMMARY'!$B57) -> 0 | P57: =COUNTIFS('OCT DUMP'!$D:$D,'PARTNERS SUMMARY'!$B57,'OCT DUMP'!Q:Q,"Prospect") -> 0 | Q57: =COUNTIFS('OCT DUMP'!$D:$D,'PARTNERS SUMMARY'!$B57,'OCT DUMP'!$Q:$Q,"Confirmed") -> 0 | R57: =COUNTIFS('OCT DUMP'!$D:$D,'PARTNERS SUMMARY'!$B57,'OCT DUMP'!$Q:$Q,"Rejected") -> 0 | S57: =COUNTIFS('OCT DUMP'!$D:$D,'PARTNERS SUMMARY'!$B57,'OCT DUMP'!$Q:$Q,"Unreachable") -> 0 | T57: =COUNTIFS('OCT DUMP'!$D:$D,'PARTNERS SUMMARY'!$B57,'OCT DUMP'!$Q:$Q,"Postponed(Update Y)") -> 0 | U57: =SUM(BL57:CP57) -> 0 | V57: =IFERROR(U57/O57,0) -> 0 | X57: =COUNTIF('NOV DUMP'!C:C,'PARTNERS SUMMARY'!$B57) -> 0 | Y57: =COUNTIFS('NOV DUMP'!$C:$C,'PARTNERS SUMMARY'!$B57,'NOV DUMP'!$S:$S,"Prospect") -> 0 | Z57: =COUNTIFS('NOV DUMP'!$C:$C,'PARTNERS SUMMARY'!$B57,'NOV DUMP'!$S:$S,"Confirmed") -> 0 | AA57: =COUNTIFS('NOV DUMP'!$C:$C,'PARTNERS SUMMARY'!$B57,'NOV DUMP'!$S:$S,"Rejected") -> 0 | AB57: =COUNTIFS('NOV DUMP'!$C:$C,'PARTNERS SUMMARY'!$B57,'NOV DUMP'!$S:$S,"Unreachable") -> 0 | AC57: =COUNTIFS('NOV DUMP'!$C:$C,'PARTNERS SUMMARY'!$B57,'NOV DUMP'!$S:$S,"Postponed(Update Y)") -> 0 | AD57: =SUM(CQ57:DT57) -> 0 | AE57: =COUNTIFS('ACTIVATED LEADS '!$H:$H,'PARTNERS SUMMARY'!$B57,'ACTIVATED LEADS '!$K:$K,'PARTNERS SUMMARY'!$AE$2,'ACTIVATED LEADS '!$C:$C,"16") -> 0 | AF57: =IFERROR(AD57/X57,0) -> 0 | AH57: =COUNTIFS('ACTIVATED LEADS '!$H:$H,$B57,'ACTIVATED LEADS '!$D:$D,'PARTNERS SUMMARY'!AH$3) -> 0 | AI57: =COUNTIFS('ACTIVATED LEADS '!$H:$H,$B57,'ACTIVATED LEADS '!$D:$D,'PARTNERS SUMMARY'!AI$3) -> 0 | AJ57: =COUNTIFS('ACTIVATED LEADS '!$H:$H,$B57,'ACTIVATED LEADS '!$D:$D,'PARTNERS SUMMARY'!AJ$3) -> 0 | AK57: =COUNTIFS('ACTIVATED LEADS '!$H:$H,$B57,'ACTIVATED LEADS '!$D:$D,'PARTNERS SUMMARY'!AK$3) -> 0 | AL57: =COUNTIFS('ACTIVATED LEADS '!$H:$H,$B57,'ACTIVATED LEADS '!$D:$D,'PARTNERS SUMMARY'!AL$3) -> 0 | AM57: =COUNTIFS('ACTIVATED LEADS '!$H:$H,$B57,'ACTIVATED LEADS '!$D:$D,'PARTNERS SUMMARY'!AM$3) -> 0 | AN57: =COUNTIFS('ACTIVATED LEADS '!$H:$H,$B57,'ACTIVATED LEADS '!$D:$D,'PARTNERS SUMMARY'!AN$3) -> 0 | AO57: =COUNTIFS('ACTIVATED LEADS '!$H:$H,$B57,'ACTIVATED LEADS '!$D:$D,'PARTNERS SUMMARY'!AO$3) -> 0 | ... DO57: =COUNTIFS('ACTIVATED LEADS '!$H:$H,$B57,'ACTIVATED LEADS '!$D:$D,'PARTNERS SUMMARY'!DO$3) -> 0
A58: Damaris Mainga | B58: MUTISH SOLUTIONS | C58: 734354959 | E58: MACHAKOS JUNCTION | F58: Nairobi | G58: =COUNTIF('SEPT DUMP '!$C:$C,'PARTNERS SUMMARY'!$B58) -> 0 | H58: =COUNTIFS('SEPT DUMP '!$C:$C,'PARTNERS SUMMARY'!$B58,'SEPT DUMP '!$O:$O,"Confirmed") -> 0 | I58: =COUNTIFS('SEPT DUMP '!$C:$C,'PARTNERS SUMMARY'!$B58,'SEPT DUMP '!$O:$O,"Rejected") -> 0 | J58: =COUNTIFS('SEPT DUMP '!$C:$C,'PARTNERS SUMMARY'!$B58,'SEPT DUMP '!$O:$O,"Unreachable") -> 0 | K58: =COUNTIFS('SEPT DUMP '!$C:$C,'PARTNERS SUMMARY'!$B58,'SEPT DUMP '!$O:$O,"Postponed(Update Y)") -> 0 | L58: =SUM(AH58:BK58) -> 0 | M58: =IFERROR(L58/G58,0) -> 0 | O58: =COUNTIF('OCT DUMP'!$D:$D,'PARTNERS SUMMARY'!$B58) -> 0 | P58: =COUNTIFS('OCT DUMP'!$D:$D,'PARTNERS SUMMARY'!$B58,'OCT DUMP'!Q:Q,"Prospect") -> 0 | Q58: =COUNTIFS('OCT DUMP'!$D:$D,'PARTNERS SUMMARY'!$B58,'OCT DUMP'!$Q:$Q,"Confirmed") -> 0 | R58: =COUNTIFS('OCT DUMP'!$D:$D,'PARTNERS SUMMARY'!$B58,'OCT DUMP'!$Q:$Q,"Rejected") -> 0 | S58: =COUNTIFS('OCT DUMP'!$D:$D,'PARTNERS SUMMARY'!$B58,'OCT DUMP'!$Q:$Q,"Unreachable") -> 0 | T58: =COUNTIFS('OCT DUMP'!$D:$D,'PARTNERS SUMMARY'!$B58,'OCT DUMP'!$Q:$Q,"Postponed(Update Y)") -> 0 | U58: =SUM(BL58:CP58) -> 0 | V58: =IFERROR(U58/O58,0) -> 0 | X58: =COUNTIF('NOV DUMP'!C:C,'PARTNERS SUMMARY'!$B58) -> 0 | Y58: =COUNTIFS('NOV DUMP'!$C:$C,'PARTNERS SUMMARY'!$B58,'NOV DUMP'!$S:$S,"Prospect") -> 0 | Z58: =COUNTIFS('NOV DUMP'!$C:$C,'PARTNERS SUMMARY'!$B58,'NOV DUMP'!$S:$S,"Confirmed") -> 0 | AA58: =COUNTIFS('NOV DUMP'!$C:$C,'PARTNERS SUMMARY'!$B58,'NOV DUMP'!$S:$S,"Rejected") -> 0 | AB58: =COUNTIFS('NOV DUMP'!$C:$C,'PARTNERS SUMMARY'!$B58,'NOV DUMP'!$S:$S,"Unreachable") -> 0 | AC58: =COUNTIFS('NOV DUMP'!$C:$C,'PARTNERS SUMMARY'!$B58,'NOV DUMP'!$S:$S,"Postponed(Update Y)") -> 0 | AD58: =SUM(CQ58:DT58) -> 0 | AE58: =COUNTIFS('ACTIVATED LEADS '!$H:$H,'PARTNERS SUMMARY'!$B58,'ACTIVATED LEADS '!$K:$K,'PARTNERS SUMMARY'!$AE$2,'ACTIVATED LEADS '!$C:$C,"16") -> 0 | AF58: =IFERROR(AD58/X58,0) -> 0 | AH58: =COUNTIFS('ACTIVATED LEADS '!$H:$H,$B58,'ACTIVATED LEADS '!$D:$D,'PARTNERS SUMMARY'!AH$3) -> 0 | AI58: =COUNTIFS('ACTIVATED LEADS '!$H:$H,$B58,'ACTIVATED LEADS '!$D:$D,'PARTNERS SUMMARY'!AI$3) -> 0 | AJ58: =COUNTIFS('ACTIVATED LEADS '!$H:$H,$B58,'ACTIVATED LEADS '!$D:$D,'PARTNERS SUMMARY'!AJ$3) -> 0 | AK58: =COUNTIFS('ACTIVATED LEADS '!$H:$H,$B58,'ACTIVATED LEADS '!$D:$D,'PARTNERS SUMMARY'!AK$3) -> 0 | AL58: =COUNTIFS('ACTIVATED LEADS '!$H:$H,$B58,'ACTIVATED LEADS '!$D:$D,'PARTNERS SUMMARY'!AL$3) -> 0 | AM58: =COUNTIFS('ACTIVATED LEADS '!$H:$H,$B58,'ACTIVATED LEADS '!$D:$D,'PARTNERS SUMMARY'!AM$3) -> 0 | AN58: =COUNTIFS('ACTIVATED LEADS '!$H:$H,$B58,'ACTIVATED LEADS '!$D:$D,'PARTNERS SUMMARY'!AN$3) -> 0 | AO58: =COUNTIFS('ACTIVATED LEADS '!$H:$H,$B58,'ACTIVATED LEADS '!$D:$D,'PARTNERS SUMMARY'!AO$3) -> 0 | ... DO58: =COUNTIFS('ACTIVATED LEADS '!$H:$H,$B58,'ACTIVATED LEADS '!$D:$D,'PARTNERS SUMMARY'!DO$3) -> 0
A59: Betreace Chebet | B59: KEROMATT COMMUNICATION LIMITED | C59: 789099195 | E59: kisii | F59: Rift | G59: =COUNTIF('SEPT DUMP '!$C:$C,'PARTNERS SUMMARY'!$B59) -> 0 | H59: =COUNTIFS('SEPT DUMP '!$C:$C,'PARTNERS SUMMARY'!$B59,'SEPT DUMP '!$O:$O,"Confirmed") -> 0 | I59: =COUNTIFS('SEPT DUMP '!$C:$C,'PARTNERS SUMMARY'!$B59,'SEPT DUMP '!$O:$O,"Rejected") -> 0 | J59: =COUNTIFS('SEPT DUMP '!$C:$C,'PARTNERS SUMMARY'!$B59,'SEPT DUMP '!$O:$O,"Unreachable") -> 0 | K59: =COUNTIFS('SEPT DUMP '!$C:$C,'PARTNERS SUMMARY'!$B59,'SEPT DUMP '!$O:$O,"Postponed(Update Y)") -> 0 | L59: =SUM(AH59:BK59) -> 0 | M59: =IFERROR(L59/G59,0) -> 0 | O59: =COUNTIF('OCT DUMP'!$D:$D,'PARTNERS SUMMARY'!$B59) -> 15 | P59: =COUNTIFS('OCT DUMP'!$D:$D,'PARTNERS SUMMARY'!$B59,'OCT DUMP'!Q:Q,"Prospect") -> 0 | Q59: =COUNTIFS('OCT DUMP'!$D:$D,'PARTNERS SUMMARY'!$B59,'OCT DUMP'!$Q:$Q,"Confirmed") -> 12 | R59: =COUNTIFS('OCT DUMP'!$D:$D,'PARTNERS SUMMARY'!$B59,'OCT DUMP'!$Q:$Q,"Rejected") -> 1 | S59: =COUNTIFS('OCT DUMP'!$D:$D,'PARTNERS SUMMARY'!$B59,'OCT DUMP'!$Q:$Q,"Unreachable") -> 2 | T59: =COUNTIFS('OCT DUMP'!$D:$D,'PARTNERS SUMMARY'!$B59,'OCT DUMP'!$Q:$Q,"Postponed(Update Y)") -> 0 | U59: =SUM(BL59:CP59) -> 4 | V59: =IFERROR(U59/O59,0) -> 0.26666667 | X59: =COUNTIF('NOV DUMP'!C:C,'PARTNERS SUMMARY'!$B59) -> 45 | Y59: =COUNTIFS('NOV DUMP'!$C:$C,'PARTNERS SUMMARY'!$B59,'NOV DUMP'!$S:$S,"Prospect") -> 0 | Z59: =COUNTIFS('NOV DUMP'!$C:$C,'PARTNERS SUMMARY'!$B59,'NOV DUMP'!$S:$S,"Confirmed") -> 9 | AA59: =COUNTIFS('NOV DUMP'!$C:$C,'PARTNERS SUMMARY'!$B59,'NOV DUMP'!$S:$S,"Rejected") -> 5 | AB59: =COUNTIFS('NOV DUMP'!$C:$C,'PARTNERS SUMMARY'!$B59,'NOV DUMP'!$S:$S,"Unreachable") -> 0 | AC59: =COUNTIFS('NOV DUMP'!$C:$C,'PARTNERS SUMMARY'!$B59,'NOV DUMP'!$S:$S,"Postponed(Update Y)") -> 0 | AD59: =SUM(CQ59:DT59) -> 26 | AE59: =COUNTIFS('ACTIVATED LEADS '!$H:$H,'PARTNERS SUMMARY'!$B59,'ACTIVATED LEADS '!$K:$K,'PARTNERS SUMMARY'!$AE$2,'ACTIVATED LEADS '!$C:$C,"16") -> 7 | AF59: =IFERROR(AD59/X59,0) -> 0.57777778 | AH59: =COUNTIFS('ACTIVATED LEADS '!$H:$H,$B59,'ACTIVATED LEADS '!$D:$D,'PARTNERS SUMMARY'!AH$3) -> 0 | AI59: =COUNTIFS('ACTIVATED LEADS '!$H:$H,$B59,'ACTIVATED LEADS '!$D:$D,'PARTNERS SUMMARY'!AI$3) -> 0 | AJ59: =COUNTIFS('ACTIVATED LEADS '!$H:$H,$B59,'ACTIVATED LEADS '!$D:$D,'PARTNERS SUMMARY'!AJ$3) -> 0 | AK59: =COUNTIFS('ACTIVATED LEADS '!$H:$H,$B59,'ACTIVATED LEADS '!$D:$D,'PARTNERS SUMMARY'!AK$3) -> 0 | AL59: =COUNTIFS('ACTIVATED LEADS '!$H:$H,$B59,'ACTIVATED LEADS '!$D:$D,'PARTNERS SUMMARY'!AL$3) -> 0 | AM59: =COUNTIFS('ACTIVATED LEADS '!$H:$H,$B59,'ACTIVATED LEADS '!$D:$D,'PARTNERS SUMMARY'!AM$3) -> 0 | AN59: =COUNTIFS('ACTIVATED LEADS '!$H:$H,$B59,'ACTIVATED LEADS '!$D:$D,'PARTNERS SUMMARY'!AN$3) -> 0 | AO59: =COUNTIFS('ACTIVATED LEADS '!$H:$H,$B59,'ACTIVATED LEADS '!$D:$D,'PARTNERS SUMMARY'!AO$3) -> 0 | ... DO59: =COUNTIFS('ACTIVATED LEADS '!$H:$H,$B59,'ACTIVATED LEADS '!$D:$D,'PARTNERS SUMMARY'!DO$3) -> 0
A60: Brian Odero | B60: TIME COP TRADING CORPORATION | C60: 105503432 | E60: KITENGELA | F60: Nairobi | G60: =COUNTIF('SEPT DUMP '!$C:$C,'PARTNERS SUMMARY'!$B60) -> 0 | H60: =COUNTIFS('SEPT DUMP '!$C:$C,'PARTNERS SUMMARY'!$B60,'SEPT DUMP '!$O:$O,"Confirmed") -> 0 | I60: =COUNTIFS('SEPT DUMP '!$C:$C,'PARTNERS SUMMARY'!$B60,'SEPT DUMP '!$O:$O,"Rejected") -> 0 | J60: =COUNTIFS('SEPT DUMP '!$C:$C,'PARTNERS SUMMARY'!$B60,'SEPT DUMP '!$O:$O,"Unreachable") -> 0 | K60: =COUNTIFS('SEPT DUMP '!$C:$C,'PARTNERS SUMMARY'!$B60,'SEPT DUMP '!$O:$O,"Postponed(Update Y)") -> 0 | L60: =SUM(AH60:BK60) -> 0 | M60: =IFERROR(L60/G60,0) -> 0 | O60: =COUNTIF('OCT DUMP'!$D:$D,'PARTNERS SUMMARY'!$B60) -> 0 | P60: =COUNTIFS('OCT DUMP'!$D:$D,'PARTNERS SUMMARY'!$B60,'OCT DUMP'!Q:Q,"Prospect") -> 0 | Q60: =COUNTIFS('OCT DUMP'!$D:$D,'PARTNERS SUMMARY'!$B60,'OCT DUMP'!$Q:$Q,"Confirmed") -> 0 | R60: =COUNTIFS('OCT DUMP'!$D:$D,'PARTNERS SUMMARY'!$B60,'OCT DUMP'!$Q:$Q,"Rejected") -> 0 | S60: =COUNTIFS('OCT DUMP'!$D:$D,'PARTNERS SUMMARY'!$B60,'OCT DUMP'!$Q:$Q,"Unreachable") -> 0 | T60: =COUNTIFS('OCT DUMP'!$D:$D,'PARTNERS SUMMARY'!$B60,'OCT DUMP'!$Q:$Q,"Postponed(Update Y)") -> 0 | U60: =SUM(BL60:CP60) -> 0 | V60: =IFERROR(U60/O60,0) -> 0 | X60: =COUNTIF('NOV DUMP'!C:C,'PARTNERS SUMMARY'!$B60) -> 0 | Y60: =COUNTIFS('NOV DUMP'!$C:$C,'PARTNERS SUMMARY'!$B60,'NOV DUMP'!$S:$S,"Prospect") -> 0 | Z60: =COUNTIFS('NOV DUMP'!$C:$C,'PARTNERS SUMMARY'!$B60,'NOV DUMP'!$S:$S,"Confirmed") -> 0 | AA60: =COUNTIFS('NOV DUMP'!$C:$C,'PARTNERS SUMMARY'!$B60,'NOV DUMP'!$S:$S,"Rejected") -> 0 | AB60: =COUNTIFS('NOV DUMP'!$C:$C,'PARTNERS SUMMARY'!$B60,'NOV DUMP'!$S:$S,"Unreachable") -> 0 | AC60: =COUNTIFS('NOV DUMP'!$C:$C,'PARTNERS SUMMARY'!$B60,'NOV DUMP'!$S:$S,"Postponed(Update Y)") -> 0 | AD60: =SUM(CQ60:DT60) -> 0 | AE60: =COUNTIFS('ACTIVATED LEADS '!$H:$H,'PARTNERS SUMMARY'!$B60,'ACTIVATED LEADS '!$K:$K,'PARTNERS SUMMARY'!$AE$2,'ACTIVATED LEADS '!$C:$C,"16") -> 0 | AF60: =IFERROR(AD60/X60,0) -> 0 | AH60: =COUNTIFS('ACTIVATED LEADS '!$H:$H,$B60,'ACTIVATED LEADS '!$D:$D,'PARTNERS SUMMARY'!AH$3) -> 0 | AI60: =COUNTIFS('ACTIVATED LEADS '!$H:$H,$B60,'ACTIVATED LEADS '!$D:$D,'PARTNERS SUMMARY'!AI$3) -> 0 | AJ60: =COUNTIFS('ACTIVATED LEADS '!$H:$H,$B60,'ACTIVATED LEADS '!$D:$D,'PARTNERS SUMMARY'!AJ$3) -> 0 | AK60: =COUNTIFS('ACTIVATED LEADS '!$H:$H,$B60,'ACTIVATED LEADS '!$D:$D,'PARTNERS SUMMARY'!AK$3) -> 0 | AL60: =COUNTIFS('ACTIVATED LEADS '!$H:$H,$B60,'ACTIVATED LEADS '!$D:$D,'PARTNERS SUMMARY'!AL$3) -> 0 | AM60: =COUNTIFS('ACTIVATED LEADS '!$H:$H,$B60,'ACTIVATED LEADS '!$D:$D,'PARTNERS SUMMARY'!AM$3) -> 0 | AN60: =COUNTIFS('ACTIVATED LEADS '!$H:$H,$B60,'ACTIVATED LEADS '!$D:$D,'PARTNERS SUMMARY'!AN$3) -> 0 | AO60: =COUNTIFS('ACTIVATED LEADS '!$H:$H,$B60,'ACTIVATED LEADS '!$D:$D,'PARTNERS SUMMARY'!AO$3) -> 0 | ... DO60: =COUNTIFS('ACTIVATED LEADS '!$H:$H,$B60,'ACTIVATED LEADS '!$D:$D,'PARTNERS SUMMARY'!DO$3) -> 0
A61: Brian Odero | B61: THEMARS CONSULTANTS NETWORK SERV | E61: Ruai | F61: Nairobi | G61: =COUNTIF('SEPT DUMP '!$C:$C,'PARTNERS SUMMARY'!$B61) -> 0 | H61: =COUNTIFS('SEPT DUMP '!$C:$C,'PARTNERS SUMMARY'!$B61,'SEPT DUMP '!$O:$O,"Confirmed") -> 0 | I61: =COUNTIFS('SEPT DUMP '!$C:$C,'PARTNERS SUMMARY'!$B61,'SEPT DUMP '!$O:$O,"Rejected") -> 0 | J61: =COUNTIFS('SEPT DUMP '!$C:$C,'PARTNERS SUMMARY'!$B61,'SEPT DUMP '!$O:$O,"Unreachable") -> 0 | K61: =COUNTIFS('SEPT DUMP '!$C:$C,'PARTNERS SUMMARY'!$B61,'SEPT DUMP '!$O:$O,"Postponed(Update Y)") -> 0 | L61: =SUM(AH61:BK61) -> 0 | M61: =IFERROR(L61/G61,0) -> 0 | O61: =COUNTIF('OCT DUMP'!$D:$D,'PARTNERS SUMMARY'!$B61) -> 0 | P61: =COUNTIFS('OCT DUMP'!$D:$D,'PARTNERS SUMMARY'!$B61,'OCT DUMP'!Q:Q,"Prospect") -> 0 | Q61: =COUNTIFS('OCT DUMP'!$D:$D,'PARTNERS SUMMARY'!$B61,'OCT DUMP'!$Q:$Q,"Confirmed") -> 0 | R61: =COUNTIFS('OCT DUMP'!$D:$D,'PARTNERS SUMMARY'!$B61,'OCT DUMP'!$Q:$Q,"Rejected") -> 0 | S61: =COUNTIFS('OCT DUMP'!$D:$D,'PARTNERS SUMMARY'!$B61,'OCT DUMP'!$Q:$Q,"Unreachable") -> 0 | T61: =COUNTIFS('OCT DUMP'!$D:$D,'PARTNERS SUMMARY'!$B61,'OCT DUMP'!$Q:$Q,"Postponed(Update Y)") -> 0 | U61: =SUM(BL61:CP61) -> 0 | V61: =IFERROR(U61/O61,0) -> 0 | X61: =COUNTIF('NOV DUMP'!C:C,'PARTNERS SUMMARY'!$B61) -> 0 | Y61: =COUNTIFS('NOV DUMP'!$C:$C,'PARTNERS SUMMARY'!$B61,'NOV DUMP'!$S:$S,"Prospect") -> 0 | Z61: =COUNTIFS('NOV DUMP'!$C:$C,'PARTNERS SUMMARY'!$B61,'NOV DUMP'!$S:$S,"Confirmed") -> 0 | AA61: =COUNTIFS('NOV DUMP'!$C:$C,'PARTNERS SUMMARY'!$B61,'NOV DUMP'!$S:$S,"Rejected") -> 0 | AB61: =COUNTIFS('NOV DUMP'!$C:$C,'PARTNERS SUMMARY'!$B61,'NOV DUMP'!$S:$S,"Unreachable") -> 0 | AC61: =COUNTIFS('NOV DUMP'!$C:$C,'PARTNERS SUMMARY'!$B61,'NOV DUMP'!$S:$S,"Postponed(Update Y)") -> 0 | AD61: =SUM(CQ61:DT61) -> 0 | AE61: =COUNTIFS('ACTIVATED LEADS '!$H:$H,'PARTNERS SUMMARY'!$B61,'ACTIVATED LEADS '!$K:$K,'PARTNERS SUMMARY'!$AE$2,'ACTIVATED LEADS '!$C:$C,"16") -> 0 | AF61: =IFERROR(AD61/X61,0) -> 0 | AH61: =COUNTIFS('ACTIVATED LEADS '!$H:$H,$B61,'ACTIVATED LEADS '!$D:$D,'PARTNERS SUMMARY'!AH$3) -> 0 | AI61: =COUNTIFS('ACTIVATED LEADS '!$H:$H,$B61,'ACTIVATED LEADS '!$D:$D,'PARTNERS SUMMARY'!AI$3) -> 0 | AJ61: =COUNTIFS('ACTIVATED LEADS '!$H:$H,$B61,'ACTIVATED LEADS '!$D:$D,'PARTNERS SUMMARY'!AJ$3) -> 0 | AK61: =COUNTIFS('ACTIVATED LEADS '!$H:$H,$B61,'ACTIVATED LEADS '!$D:$D,'PARTNERS SUMMARY'!AK$3) -> 0 | AL61: =COUNTIFS('ACTIVATED LEADS '!$H:$H,$B61,'ACTIVATED LEADS '!$D:$D,'PARTNERS SUMMARY'!AL$3) -> 0 | AM61: =COUNTIFS('ACTIVATED LEADS '!$H:$H,$B61,'ACTIVATED LEADS '!$D:$D,'PARTNERS SUMMARY'!AM$3) -> 0 | AN61: =COUNTIFS('ACTIVATED LEADS '!$H:$H,$B61,'ACTIVATED LEADS '!$D:$D,'PARTNERS SUMMARY'!AN$3) -> 0 | AO61: =COUNTIFS('ACTIVATED LEADS '!$H:$H,$B61,'ACTIVATED LEADS '!$D:$D,'PARTNERS SUMMARY'!AO$3) -> 0 | ... DO61: =COUNTIFS('ACTIVATED LEADS '!$H:$H,$B61,'ACTIVATED LEADS '!$D:$D,'PARTNERS SUMMARY'!DO$3) -> 0
A62: Brian Odero | B62: JAYPHONES PROPERTIES | C62: 102903062 | E62: Nyahururu | F62: Nairobi | G62: =COUNTIF('SEPT DUMP '!$C:$C,'PARTNERS SUMMARY'!$B62) -> 0 | H62: =COUNTIFS('SEPT DUMP '!$C:$C,'PARTNERS SUMMARY'!$B62,'SEPT DUMP '!$O:$O,"Confirmed") -> 0 | I62: =COUNTIFS('SEPT DUMP '!$C:$C,'PARTNERS SUMMARY'!$B62,'SEPT DUMP '!$O:$O,"Rejected") -> 0 | J62: =COUNTIFS('SEPT DUMP '!$C:$C,'PARTNERS SUMMARY'!$B62,'SEPT DUMP '!$O:$O,"Unreachable") -> 0 | K62: =COUNTIFS('SEPT DUMP '!$C:$C,'PARTNERS SUMMARY'!$B62,'SEPT DUMP '!$O:$O,"Postponed(Update Y)") -> 0 | L62: =SUM(AH62:BK62) -> 0 | M62: =IFERROR(L62/G62,0) -> 0 | O62: =COUNTIF('OCT DUMP'!$D:$D,'PARTNERS SUMMARY'!$B62) -> 0 | P62: =COUNTIFS('OCT DUMP'!$D:$D,'PARTNERS SUMMARY'!$B62,'OCT DUMP'!Q:Q,"Prospect") -> 0 | Q62: =COUNTIFS('OCT DUMP'!$D:$D,'PARTNERS SUMMARY'!$B62,'OCT DUMP'!$Q:$Q,"Confirmed") -> 0 | R62: =COUNTIFS('OCT DUMP'!$D:$D,'PARTNERS SUMMARY'!$B62,'OCT DUMP'!$Q:$Q,"Rejected") -> 0 | S62: =COUNTIFS('OCT DUMP'!$D:$D,'PARTNERS SUMMARY'!$B62,'OCT DUMP'!$Q:$Q,"Unreachable") -> 0 | T62: =COUNTIFS('OCT DUMP'!$D:$D,'PARTNERS SUMMARY'!$B62,'OCT DUMP'!$Q:$Q,"Postponed(Update Y)") -> 0 | U62: =SUM(BL62:CP62) -> 0 | V62: =IFERROR(U62/O62,0) -> 0 | X62: =COUNTIF('NOV DUMP'!C:C,'PARTNERS SUMMARY'!$B62) -> 0 | Y62: =COUNTIFS('NOV DUMP'!$C:$C,'PARTNERS SUMMARY'!$B62,'NOV DUMP'!$S:$S,"Prospect") -> 0 | Z62: =COUNTIFS('NOV DUMP'!$C:$C,'PARTNERS SUMMARY'!$B62,'NOV DUMP'!$S:$S,"Confirmed") -> 0 | AA62: =COUNTIFS('NOV DUMP'!$C:$C,'PARTNERS SUMMARY'!$B62,'NOV DUMP'!$S:$S,"Rejected") -> 0 | AB62: =COUNTIFS('NOV DUMP'!$C:$C,'PARTNERS SUMMARY'!$B62,'NOV DUMP'!$S:$S,"Unreachable") -> 0 | AC62: =COUNTIFS('NOV DUMP'!$C:$C,'PARTNERS SUMMARY'!$B62,'NOV DUMP'!$S:$S,"Postponed(Update Y)") -> 0 | AD62: =SUM(CQ62:DT62) -> 0 | AE62: =COUNTIFS('ACTIVATED LEADS '!$H:$H,'PARTNERS SUMMARY'!$B62,'ACTIVATED LEADS '!$K:$K,'PARTNERS SUMMARY'!$AE$2,'ACTIVATED LEADS '!$C:$C,"16") -> 0 | AF62: =IFERROR(AD62/X62,0) -> 0 | AH62: =COUNTIFS('ACTIVATED LEADS '!$H:$H,$B62,'ACTIVATED LEADS '!$D:$D,'PARTNERS SUMMARY'!AH$3) -> 0 | AI62: =COUNTIFS('ACTIVATED LEADS '!$H:$H,$B62,'ACTIVATED LEADS '!$D:$D,'PARTNERS SUMMARY'!AI$3) -> 0 | AJ62: =COUNTIFS('ACTIVATED LEADS '!$H:$H,$B62,'ACTIVATED LEADS '!$D:$D,'PARTNERS SUMMARY'!AJ$3) -> 0 | AK62: =COUNTIFS('ACTIVATED LEADS '!$H:$H,$B62,'ACTIVATED LEADS '!$D:$D,'PARTNERS SUMMARY'!AK$3) -> 0 | AL62: =COUNTIFS('ACTIVATED LEADS '!$H:$H,$B62,'ACTIVATED LEADS '!$D:$D,'PARTNERS SUMMARY'!AL$3) -> 0 | AM62: =COUNTIFS('ACTIVATED LEADS '!$H:$H,$B62,'ACTIVATED LEADS '!$D:$D,'PARTNERS SUMMARY'!AM$3) -> 0 | AN62: =COUNTIFS('ACTIVATED LEADS '!$H:$H,$B62,'ACTIVATED LEADS '!$D:$D,'PARTNERS SUMMARY'!AN$3) -> 0 | AO62: =COUNTIFS('ACTIVATED LEADS '!$H:$H,$B62,'ACTIVATED LEADS '!$D:$D,'PARTNERS SUMMARY'!AO$3) -> 0 | ... DO62: =COUNTIFS('ACTIVATED LEADS '!$H:$H,$B62,'ACTIVATED LEADS '!$D:$D,'PARTNERS SUMMARY'!DO$3) -> 0
A63: Damaris Mainga | B63: YIREH NETWORKS | C63: 107126683 | E63: Wahiyaki way | F63: Nairobi | G63: =COUNTIF('SEPT DUMP '!$C:$C,'PARTNERS SUMMARY'!$B63) -> 0 | H63: =COUNTIFS('SEPT DUMP '!$C:$C,'PARTNERS SUMMARY'!$B63,'SEPT DUMP '!$O:$O,"Confirmed") -> 0 | I63: =COUNTIFS('SEPT DUMP '!$C:$C,'PARTNERS SUMMARY'!$B63,'SEPT DUMP '!$O:$O,"Rejected") -> 0 | J63: =COUNTIFS('SEPT DUMP '!$C:$C,'PARTNERS SUMMARY'!$B63,'SEPT DUMP '!$O:$O,"Unreachable") -> 0 | K63: =COUNTIFS('SEPT DUMP '!$C:$C,'PARTNERS SUMMARY'!$B63,'SEPT DUMP '!$O:$O,"Postponed(Update Y)") -> 0 | L63: =SUM(AH63:BK63) -> 0 | M63: =IFERROR(L63/G63,0) -> 0 | O63: =COUNTIF('OCT DUMP'!$D:$D,'PARTNERS SUMMARY'!$B63) -> 0 | P63: =COUNTIFS('OCT DUMP'!$D:$D,'PARTNERS SUMMARY'!$B63,'OCT DUMP'!Q:Q,"Prospect") -> 0 | Q63: =COUNTIFS('OCT DUMP'!$D:$D,'PARTNERS SUMMARY'!$B63,'OCT DUMP'!$Q:$Q,"Confirmed") -> 0 | R63: =COUNTIFS('OCT DUMP'!$D:$D,'PARTNERS SUMMARY'!$B63,'OCT DUMP'!$Q:$Q,"Rejected") -> 0 | S63: =COUNTIFS('OCT DUMP'!$D:$D,'PARTNERS SUMMARY'!$B63,'OCT DUMP'!$Q:$Q,"Unreachable") -> 0 | T63: =COUNTIFS('OCT DUMP'!$D:$D,'PARTNERS SUMMARY'!$B63,'OCT DUMP'!$Q:$Q,"Postponed(Update Y)") -> 0 | U63: =SUM(BL63:CP63) -> 0 | V63: =IFERROR(U63/O63,0) -> 0 | X63: =COUNTIF('NOV DUMP'!C:C,'PARTNERS SUMMARY'!$B63) -> 1 | Y63: =COUNTIFS('NOV DUMP'!$C:$C,'PARTNERS SUMMARY'!$B63,'NOV DUMP'!$S:$S,"Prospect") -> 0 | Z63: =COUNTIFS('NOV DUMP'!$C:$C,'PARTNERS SUMMARY'!$B63,'NOV DUMP'!$S:$S,"Confirmed") -> 0 | AA63: =COUNTIFS('NOV DUMP'!$C:$C,'PARTNERS SUMMARY'!$B63,'NOV DUMP'!$S:$S,"Rejected") -> 0 | AB63: =COUNTIFS('NOV DUMP'!$C:$C,'PARTNERS SUMMARY'!$B63,'NOV DUMP'!$S:$S,"Unreachable") -> 0 | AC63: =COUNTIFS('NOV DUMP'!$C:$C,'PARTNERS SUMMARY'!$B63,'NOV DUMP'!$S:$S,"Postponed(Update Y)") -> 0 | AD63: =SUM(CQ63:DT63) -> 0 | AE63: =COUNTIFS('ACTIVATED LEADS '!$H:$H,'PARTNERS SUMMARY'!$B63,'ACTIVATED LEADS '!$K:$K,'PARTNERS SUMMARY'!$AE$2,'ACTIVATED LEADS '!$C:$C,"16") -> 0 | AF63: =IFERROR(AD63/X63,0) -> 0 | AH63: =COUNTIFS('ACTIVATED LEADS '!$H:$H,$B63,'ACTIVATED LEADS '!$D:$D,'PARTNERS SUMMARY'!AH$3) -> 0 | AI63: =COUNTIFS('ACTIVATED LEADS '!$H:$H,$B63,'ACTIVATED LEADS '!$D:$D,'PARTNERS SUMMARY'!AI$3) -> 0 | AJ63: =COUNTIFS('ACTIVATED LEADS '!$H:$H,$B63,'ACTIVATED LEADS '!$D:$D,'PARTNERS SUMMARY'!AJ$3) -> 0 | AK63: =COUNTIFS('ACTIVATED LEADS '!$H:$H,$B63,'ACTIVATED LEADS '!$D:$D,'PARTNERS SUMMARY'!AK$3) -> 0 | AL63: =COUNTIFS('ACTIVATED LEADS '!$H:$H,$B63,'ACTIVATED LEADS '!$D:$D,'PARTNERS SUMMARY'!AL$3) -> 0 | AM63: =COUNTIFS('ACTIVATED LEADS '!$H:$H,$B63,'ACTIVATED LEADS '!$D:$D,'PARTNERS SUMMARY'!AM$3) -> 0 | AN63: =COUNTIFS('ACTIVATED LEADS '!$H:$H,$B63,'ACTIVATED LEADS '!$D:$D,'PARTNERS SUMMARY'!AN$3) -> 0 | AO63: =COUNTIFS('ACTIVATED LEADS '!$H:$H,$B63,'ACTIVATED LEADS '!$D:$D,'PARTNERS SUMMARY'!AO$3) -> 0 | ... DO63: =COUNTIFS('ACTIVATED LEADS '!$H:$H,$B63,'ACTIVATED LEADS '!$D:$D,'PARTNERS SUMMARY'!DO$3) -> 0
A64: Damaris Mainga | B64: TVI TECHNOLOGIES | C64: 739553962 | E64: Nairobi CBD | F64: Nairobi | G64: =COUNTIF('SEPT DUMP '!$C:$C,'PARTNERS SUMMARY'!$B64) -> 0 | H64: =COUNTIFS('SEPT DUMP '!$C:$C,'PARTNERS SUMMARY'!$B64,'SEPT DUMP '!$O:$O,"Confirmed") -> 0 | I64: =COUNTIFS('SEPT DUMP '!$C:$C,'PARTNERS SUMMARY'!$B64,'SEPT DUMP '!$O:$O,"Rejected") -> 0 | J64: =COUNTIFS('SEPT DUMP '!$C:$C,'PARTNERS SUMMARY'!$B64,'SEPT DUMP '!$O:$O,"Unreachable") -> 0 | K64: =COUNTIFS('SEPT DUMP '!$C:$C,'PARTNERS SUMMARY'!$B64,'SEPT DUMP '!$O:$O,"Postponed(Update Y)") -> 0 | L64: =SUM(AH64:BK64) -> 0 | M64: =IFERROR(L64/G64,0) -> 0 | O64: =COUNTIF('OCT DUMP'!$D:$D,'PARTNERS SUMMARY'!$B64) -> 0 | P64: =COUNTIFS('OCT DUMP'!$D:$D,'PARTNERS SUMMARY'!$B64,'OCT DUMP'!Q:Q,"Prospect") -> 0 | Q64: =COUNTIFS('OCT DUMP'!$D:$D,'PARTNERS SUMMARY'!$B64,'OCT DUMP'!$Q:$Q,"Confirmed") -> 0 | R64: =COUNTIFS('OCT DUMP'!$D:$D,'PARTNERS SUMMARY'!$B64,'OCT DUMP'!$Q:$Q,"Rejected") -> 0 | S64: =COUNTIFS('OCT DUMP'!$D:$D,'PARTNERS SUMMARY'!$B64,'OCT DUMP'!$Q:$Q,"Unreachable") -> 0 | T64: =COUNTIFS('OCT DUMP'!$D:$D,'PARTNERS SUMMARY'!$B64,'OCT DUMP'!$Q:$Q,"Postponed(Update Y)") -> 0 | U64: =SUM(BL64:CP64) -> 0 | V64: =IFERROR(U64/O64,0) -> 0 | X64: =COUNTIF('NOV DUMP'!C:C,'PARTNERS SUMMARY'!$B64) -> 0 | Y64: =COUNTIFS('NOV DUMP'!$C:$C,'PARTNERS SUMMARY'!$B64,'NOV DUMP'!$S:$S,"Prospect") -> 0 | Z64: =COUNTIFS('NOV DUMP'!$C:$C,'PARTNERS SUMMARY'!$B64,'NOV DUMP'!$S:$S,"Confirmed") -> 0 | AA64: =COUNTIFS('NOV DUMP'!$C:$C,'PARTNERS SUMMARY'!$B64,'NOV DUMP'!$S:$S,"Rejected") -> 0 | AB64: =COUNTIFS('NOV DUMP'!$C:$C,'PARTNERS SUMMARY'!$B64,'NOV DUMP'!$S:$S,"Unreachable") -> 0 | AC64: =COUNTIFS('NOV DUMP'!$C:$C,'PARTNERS SUMMARY'!$B64,'NOV DUMP'!$S:$S,"Postponed(Update Y)") -> 0 | AD64: =SUM(CQ64:DT64) -> 0 | AE64: =COUNTIFS('ACTIVATED LEADS '!$H:$H,'PARTNERS SUMMARY'!$B64,'ACTIVATED LEADS '!$K:$K,'PARTNERS SUMMARY'!$AE$2,'ACTIVATED LEADS '!$C:$C,"16") -> 0 | AF64: =IFERROR(AD64/X64,0) -> 0 | AH64: =COUNTIFS('ACTIVATED LEADS '!$H:$H,$B64,'ACTIVATED LEADS '!$D:$D,'PARTNERS SUMMARY'!AH$3) -> 0 | AI64: =COUNTIFS('ACTIVATED LEADS '!$H:$H,$B64,'ACTIVATED LEADS '!$D:$D,'PARTNERS SUMMARY'!AI$3) -> 0 | AJ64: =COUNTIFS('ACTIVATED LEADS '!$H:$H,$B64,'ACTIVATED LEADS '!$D:$D,'PARTNERS SUMMARY'!AJ$3) -> 0 | AK64: =COUNTIFS('ACTIVATED LEADS '!$H:$H,$B64,'ACTIVATED LEADS '!$D:$D,'PARTNERS SUMMARY'!AK$3) -> 0 | AL64: =COUNTIFS('ACTIVATED LEADS '!$H:$H,$B64,'ACTIVATED LEADS '!$D:$D,'PARTNERS SUMMARY'!AL$3) -> 0 | AM64: =COUNTIFS('ACTIVATED LEADS '!$H:$H,$B64,'ACTIVATED LEADS '!$D:$D,'PARTNERS SUMMARY'!AM$3) -> 0 | AN64: =COUNTIFS('ACTIVATED LEADS '!$H:$H,$B64,'ACTIVATED LEADS '!$D:$D,'PARTNERS SUMMARY'!AN$3) -> 0 | AO64: =COUNTIFS('ACTIVATED LEADS '!$H:$H,$B64,'ACTIVATED LEADS '!$D:$D,'PARTNERS SUMMARY'!AO$3) -> 0 | ... DO64: =COUNTIFS('ACTIVATED LEADS '!$H:$H,$B64,'ACTIVATED LEADS '!$D:$D,'PARTNERS SUMMARY'!DO$3) -> 0
A65: Brian Odero | B65: PARIX KENYA | C65: 756554995 | E65: Nairobi | F65: Nairobi | G65: =COUNTIF('SEPT DUMP '!$C:$C,'PARTNERS SUMMARY'!$B65) -> 0 | H65: =COUNTIFS('SEPT DUMP '!$C:$C,'PARTNERS SUMMARY'!$B65,'SEPT DUMP '!$O:$O,"Confirmed") -> 0 | I65: =COUNTIFS('SEPT DUMP '!$C:$C,'PARTNERS SUMMARY'!$B65,'SEPT DUMP '!$O:$O,"Rejected") -> 0 | J65: =COUNTIFS('SEPT DUMP '!$C:$C,'PARTNERS SUMMARY'!$B65,'SEPT DUMP '!$O:$O,"Unreachable") -> 0 | K65: =COUNTIFS('SEPT DUMP '!$C:$C,'PARTNERS SUMMARY'!$B65,'SEPT DUMP '!$O:$O,"Postponed(Update Y)") -> 0 | L65: =SUM(AH65:BK65) -> 0 | M65: =IFERROR(L65/G65,0) -> 0 | O65: =COUNTIF('OCT DUMP'!$D:$D,'PARTNERS SUMMARY'!$B65) -> 0 | P65: =COUNTIFS('OCT DUMP'!$D:$D,'PARTNERS SUMMARY'!$B65,'OCT DUMP'!Q:Q,"Prospect") -> 0 | Q65: =COUNTIFS('OCT DUMP'!$D:$D,'PARTNERS SUMMARY'!$B65,'OCT DUMP'!$Q:$Q,"Confirmed") -> 0 | R65: =COUNTIFS('OCT DUMP'!$D:$D,'PARTNERS SUMMARY'!$B65,'OCT DUMP'!$Q:$Q,"Rejected") -> 0 | S65: =COUNTIFS('OCT DUMP'!$D:$D,'PARTNERS SUMMARY'!$B65,'OCT DUMP'!$Q:$Q,"Unreachable") -> 0 | T65: =COUNTIFS('OCT DUMP'!$D:$D,'PARTNERS SUMMARY'!$B65,'OCT DUMP'!$Q:$Q,"Postponed(Update Y)") -> 0 | U65: =SUM(BL65:CP65) -> 0 | V65: =IFERROR(U65/O65,0) -> 0 | X65: =COUNTIF('NOV DUMP'!C:C,'PARTNERS SUMMARY'!$B65) -> 0 | Y65: =COUNTIFS('NOV DUMP'!$C:$C,'PARTNERS SUMMARY'!$B65,'NOV DUMP'!$S:$S,"Prospect") -> 0 | Z65: =COUNTIFS('NOV DUMP'!$C:$C,'PARTNERS SUMMARY'!$B65,'NOV DUMP'!$S:$S,"Confirmed") -> 0 | AA65: =COUNTIFS('NOV DUMP'!$C:$C,'PARTNERS SUMMARY'!$B65,'NOV DUMP'!$S:$S,"Rejected") -> 0 | AB65: =COUNTIFS('NOV DUMP'!$C:$C,'PARTNERS SUMMARY'!$B65,'NOV DUMP'!$S:$S,"Unreachable") -> 0 | AC65: =COUNTIFS('NOV DUMP'!$C:$C,'PARTNERS SUMMARY'!$B65,'NOV DUMP'!$S:$S,"Postponed(Update Y)") -> 0 | AD65: =SUM(CQ65:DT65) -> 0 | AE65: =COUNTIFS('ACTIVATED LEADS '!$H:$H,'PARTNERS SUMMARY'!$B65,'ACTIVATED LEADS '!$K:$K,'PARTNERS SUMMARY'!$AE$2,'ACTIVATED LEADS '!$C:$C,"16") -> 0 | AF65: =IFERROR(AD65/X65,0) -> 0 | AH65: =COUNTIFS('ACTIVATED LEADS '!$H:$H,$B65,'ACTIVATED LEADS '!$D:$D,'PARTNERS SUMMARY'!AH$3) -> 0 | AI65: =COUNTIFS('ACTIVATED LEADS '!$H:$H,$B65,'ACTIVATED LEADS '!$D:$D,'PARTNERS SUMMARY'!AI$3) -> 0 | AJ65: =COUNTIFS('ACTIVATED LEADS '!$H:$H,$B65,'ACTIVATED LEADS '!$D:$D,'PARTNERS SUMMARY'!AJ$3) -> 0 | AK65: =COUNTIFS('ACTIVATED LEADS '!$H:$H,$B65,'ACTIVATED LEADS '!$D:$D,'PARTNERS SUMMARY'!AK$3) -> 0 | AL65: =COUNTIFS('ACTIVATED LEADS '!$H:$H,$B65,'ACTIVATED LEADS '!$D:$D,'PARTNERS SUMMARY'!AL$3) -> 0 | AM65: =COUNTIFS('ACTIVATED LEADS '!$H:$H,$B65,'ACTIVATED LEADS '!$D:$D,'PARTNERS SUMMARY'!AM$3) -> 0 | AN65: =COUNTIFS('ACTIVATED LEADS '!$H:$H,$B65,'ACTIVATED LEADS '!$D:$D,'PARTNERS SUMMARY'!AN$3) -> 0 | AO65: =COUNTIFS('ACTIVATED LEADS '!$H:$H,$B65,'ACTIVATED LEADS '!$D:$D,'PARTNERS SUMMARY'!AO$3) -> 0 | ... DO65: =COUNTIFS('ACTIVATED LEADS '!$H:$H,$B65,'ACTIVATED LEADS '!$D:$D,'PARTNERS SUMMARY'!DO$3) -> 0
A66: Mariana Hongo | B66: Techvisory Ltd | C66: 780003666 | E66: Nairobi | F66: Western | G66: =COUNTIF('SEPT DUMP '!$C:$C,'PARTNERS SUMMARY'!$B66) -> 0 | H66: =COUNTIFS('SEPT DUMP '!$C:$C,'PARTNERS SUMMARY'!$B66,'SEPT DUMP '!$O:$O,"Confirmed") -> 0 | I66: =COUNTIFS('SEPT DUMP '!$C:$C,'PARTNERS SUMMARY'!$B66,'SEPT DUMP '!$O:$O,"Rejected") -> 0 | J66: =COUNTIFS('SEPT DUMP '!$C:$C,'PARTNERS SUMMARY'!$B66,'SEPT DUMP '!$O:$O,"Unreachable") -> 0 | K66: =COUNTIFS('SEPT DUMP '!$C:$C,'PARTNERS SUMMARY'!$B66,'SEPT DUMP '!$O:$O,"Postponed(Update Y)") -> 0 | L66: =SUM(AH66:BK66) -> 0 | M66: =IFERROR(L66/G66,0) -> 0 | O66: =COUNTIF('OCT DUMP'!$D:$D,'PARTNERS SUMMARY'!$B66) -> 0 | P66: =COUNTIFS('OCT DUMP'!$D:$D,'PARTNERS SUMMARY'!$B66,'OCT DUMP'!Q:Q,"Prospect") -> 0 | Q66: =COUNTIFS('OCT DUMP'!$D:$D,'PARTNERS SUMMARY'!$B66,'OCT DUMP'!$Q:$Q,"Confirmed") -> 0 | R66: =COUNTIFS('OCT DUMP'!$D:$D,'PARTNERS SUMMARY'!$B66,'OCT DUMP'!$Q:$Q,"Rejected") -> 0 | S66: =COUNTIFS('OCT DUMP'!$D:$D,'PARTNERS SUMMARY'!$B66,'OCT DUMP'!$Q:$Q,"Unreachable") -> 0 | T66: =COUNTIFS('OCT DUMP'!$D:$D,'PARTNERS SUMMARY'!$B66,'OCT DUMP'!$Q:$Q,"Postponed(Update Y)") -> 0 | U66: =SUM(BL66:CP66) -> 0 | V66: =IFERROR(U66/O66,0) -> 0 | X66: =COUNTIF('NOV DUMP'!C:C,'PARTNERS SUMMARY'!$B66) -> 0 | Y66: =COUNTIFS('NOV DUMP'!$C:$C,'PARTNERS SUMMARY'!$B66,'NOV DUMP'!$S:$S,"Prospect") -> 0 | Z66: =COUNTIFS('NOV DUMP'!$C:$C,'PARTNERS SUMMARY'!$B66,'NOV DUMP'!$S:$S,"Confirmed") -> 0 | AA66: =COUNTIFS('NOV DUMP'!$C:$C,'PARTNERS SUMMARY'!$B66,'NOV DUMP'!$S:$S,"Rejected") -> 0 | AB66: =COUNTIFS('NOV DUMP'!$C:$C,'PARTNERS SUMMARY'!$B66,'NOV DUMP'!$S:$S,"Unreachable") -> 0 | AC66: =COUNTIFS('NOV DUMP'!$C:$C,'PARTNERS SUMMARY'!$B66,'NOV DUMP'!$S:$S,"Postponed(Update Y)") -> 0 | AD66: =SUM(CQ66:DT66) -> 0 | AE66: =COUNTIFS('ACTIVATED LEADS '!$H:$H,'PARTNERS SUMMARY'!$B66,'ACTIVATED LEADS '!$K:$K,'PARTNERS SUMMARY'!$AE$2,'ACTIVATED LEADS '!$C:$C,"16") -> 0 | AF66: =IFERROR(AD66/X66,0) -> 0 | AH66: =COUNTIFS('ACTIVATED LEADS '!$H:$H,$B66,'ACTIVATED LEADS '!$D:$D,'PARTNERS SUMMARY'!AH$3) -> 0 | AI66: =COUNTIFS('ACTIVATED LEADS '!$H:$H,$B66,'ACTIVATED LEADS '!$D:$D,'PARTNERS SUMMARY'!AI$3) -> 0 | AJ66: =COUNTIFS('ACTIVATED LEADS '!$H:$H,$B66,'ACTIVATED LEADS '!$D:$D,'PARTNERS SUMMARY'!AJ$3) -> 0 | AK66: =COUNTIFS('ACTIVATED LEADS '!$H:$H,$B66,'ACTIVATED LEADS '!$D:$D,'PARTNERS SUMMARY'!AK$3) -> 0 | AL66: =COUNTIFS('ACTIVATED LEADS '!$H:$H,$B66,'ACTIVATED LEADS '!$D:$D,'PARTNERS SUMMARY'!AL$3) -> 0 | AM66: =COUNTIFS('ACTIVATED LEADS '!$H:$H,$B66,'ACTIVATED LEADS '!$D:$D,'PARTNERS SUMMARY'!AM$3) -> 0 | AN66: =COUNTIFS('ACTIVATED LEADS '!$H:$H,$B66,'ACTIVATED LEADS '!$D:$D,'PARTNERS SUMMARY'!AN$3) -> 0 | AO66: =COUNTIFS('ACTIVATED LEADS '!$H:$H,$B66,'ACTIVATED LEADS '!$D:$D,'PARTNERS SUMMARY'!AO$3) -> 0 | ... DO66: =COUNTIFS('ACTIVATED LEADS '!$H:$H,$B66,'ACTIVATED LEADS '!$D:$D,'PARTNERS SUMMARY'!DO$3) -> 0
A67: Damaris Mainga | B67: SPRINKVILLE NETWORKS LIMITED | C67: 783316180 | E67: Thika rd.Garden Estate | F67: Nairobi | G67: =COUNTIF('SEPT DUMP '!$C:$C,'PARTNERS SUMMARY'!$B67) -> 0 | H67: =COUNTIFS('SEPT DUMP '!$C:$C,'PARTNERS SUMMARY'!$B67,'SEPT DUMP '!$O:$O,"Confirmed") -> 0 | I67: =COUNTIFS('SEPT DUMP '!$C:$C,'PARTNERS SUMMARY'!$B67,'SEPT DUMP '!$O:$O,"Rejected") -> 0 | J67: =COUNTIFS('SEPT DUMP '!$C:$C,'PARTNERS SUMMARY'!$B67,'SEPT DUMP '!$O:$O,"Unreachable") -> 0 | K67: =COUNTIFS('SEPT DUMP '!$C:$C,'PARTNERS SUMMARY'!$B67,'SEPT DUMP '!$O:$O,"Postponed(Update Y)") -> 0 | L67: =SUM(AH67:BK67) -> 0 | M67: =IFERROR(L67/G67,0) -> 0 | O67: =COUNTIF('OCT DUMP'!$D:$D,'PARTNERS SUMMARY'!$B67) -> 0 | P67: =COUNTIFS('OCT DUMP'!$D:$D,'PARTNERS SUMMARY'!$B67,'OCT DUMP'!Q:Q,"Prospect") -> 0 | Q67: =COUNTIFS('OCT DUMP'!$D:$D,'PARTNERS SUMMARY'!$B67,'OCT DUMP'!$Q:$Q,"Confirmed") -> 0 | R67: =COUNTIFS('OCT DUMP'!$D:$D,'PARTNERS SUMMARY'!$B67,'OCT DUMP'!$Q:$Q,"Rejected") -> 0 | S67: =COUNTIFS('OCT DUMP'!$D:$D,'PARTNERS SUMMARY'!$B67,'OCT DUMP'!$Q:$Q,"Unreachable") -> 0 | T67: =COUNTIFS('OCT DUMP'!$D:$D,'PARTNERS SUMMARY'!$B67,'OCT DUMP'!$Q:$Q,"Postponed(Update Y)") -> 0 | U67: =SUM(BL67:CP67) -> 0 | V67: =IFERROR(U67/O67,0) -> 0 | X67: =COUNTIF('NOV DUMP'!C:C,'PARTNERS SUMMARY'!$B67) -> 0 | Y67: =COUNTIFS('NOV DUMP'!$C:$C,'PARTNERS SUMMARY'!$B67,'NOV DUMP'!$S:$S,"Prospect") -> 0 | Z67: =COUNTIFS('NOV DUMP'!$C:$C,'PARTNERS SUMMARY'!$B67,'NOV DUMP'!$S:$S,"Confirmed") -> 0 | AA67: =COUNTIFS('NOV DUMP'!$C:$C,'PARTNERS SUMMARY'!$B67,'NOV DUMP'!$S:$S,"Rejected") -> 0 | AB67: =COUNTIFS('NOV DUMP'!$C:$C,'PARTNERS SUMMARY'!$B67,'NOV DUMP'!$S:$S,"Unreachable") -> 0 | AC67: =COUNTIFS('NOV DUMP'!$C:$C,'PARTNERS SUMMARY'!$B67,'NOV DUMP'!$S:$S,"Postponed(Update Y)") -> 0 | AD67: =SUM(CQ67:DT67) -> 0 | AE67: =COUNTIFS('ACTIVATED LEADS '!$H:$H,'PARTNERS SUMMARY'!$B67,'ACTIVATED LEADS '!$K:$K,'PARTNERS SUMMARY'!$AE$2,'ACTIVATED LEADS '!$C:$C,"16") -> 0 | AF67: =IFERROR(AD67/X67,0) -> 0 | AH67: =COUNTIFS('ACTIVATED LEADS '!$H:$H,$B67,'ACTIVATED LEADS '!$D:$D,'PARTNERS SUMMARY'!AH$3) -> 0 | AI67: =COUNTIFS('ACTIVATED LEADS '!$H:$H,$B67,'ACTIVATED LEADS '!$D:$D,'PARTNERS SUMMARY'!AI$3) -> 0 | AJ67: =COUNTIFS('ACTIVATED LEADS '!$H:$H,$B67,'ACTIVATED LEADS '!$D:$D,'PARTNERS SUMMARY'!AJ$3) -> 0 | AK67: =COUNTIFS('ACTIVATED LEADS '!$H:$H,$B67,'ACTIVATED LEADS '!$D:$D,'PARTNERS SUMMARY'!AK$3) -> 0 | AL67: =COUNTIFS('ACTIVATED LEADS '!$H:$H,$B67,'ACTIVATED LEADS '!$D:$D,'PARTNERS SUMMARY'!AL$3) -> 0 | AM67: =COUNTIFS('ACTIVATED LEADS '!$H:$H,$B67,'ACTIVATED LEADS '!$D:$D,'PARTNERS SUMMARY'!AM$3) -> 0 | AN67: =COUNTIFS('ACTIVATED LEADS '!$H:$H,$B67,'ACTIVATED LEADS '!$D:$D,'PARTNERS SUMMARY'!AN$3) -> 0 | AO67: =COUNTIFS('ACTIVATED LEADS '!$H:$H,$B67,'ACTIVATED LEADS '!$D:$D,'PARTNERS SUMMARY'!AO$3) -> 0 | ... DO67: =COUNTIFS('ACTIVATED LEADS '!$H:$H,$B67,'ACTIVATED LEADS '!$D:$D,'PARTNERS SUMMARY'!DO$3) -> 0
A68: Brian Odero | B68: WAM APPLICATIONS | C68: 753543015 | E68: Kahawa west | F68: Nairobi | G68: =COUNTIF('SEPT DUMP '!$C:$C,'PARTNERS SUMMARY'!$B68) -> 0 | H68: =COUNTIFS('SEPT DUMP '!$C:$C,'PARTNERS SUMMARY'!$B68,'SEPT DUMP '!$O:$O,"Confirmed") -> 0 | I68: =COUNTIFS('SEPT DUMP '!$C:$C,'PARTNERS SUMMARY'!$B68,'SEPT DUMP '!$O:$O,"Rejected") -> 0 | J68: =COUNTIFS('SEPT DUMP '!$C:$C,'PARTNERS SUMMARY'!$B68,'SEPT DUMP '!$O:$O,"Unreachable") -> 0 | K68: =COUNTIFS('SEPT DUMP '!$C:$C,'PARTNERS SUMMARY'!$B68,'SEPT DUMP '!$O:$O,"Postponed(Update Y)") -> 0 | L68: =SUM(AH68:BK68) -> 0 | M68: =IFERROR(L68/G68,0) -> 0 | O68: =COUNTIF('OCT DUMP'!$D:$D,'PARTNERS SUMMARY'!$B68) -> 0 | P68: =COUNTIFS('OCT DUMP'!$D:$D,'PARTNERS SUMMARY'!$B68,'OCT DUMP'!Q:Q,"Prospect") -> 0 | Q68: =COUNTIFS('OCT DUMP'!$D:$D,'PARTNERS SUMMARY'!$B68,'OCT DUMP'!$Q:$Q,"Confirmed") -> 0 | R68: =COUNTIFS('OCT DUMP'!$D:$D,'PARTNERS SUMMARY'!$B68,'OCT DUMP'!$Q:$Q,"Rejected") -> 0 | S68: =COUNTIFS('OCT DUMP'!$D:$D,'PARTNERS SUMMARY'!$B68,'OCT DUMP'!$Q:$Q,"Unreachable") -> 0 | T68: =COUNTIFS('OCT DUMP'!$D:$D,'PARTNERS SUMMARY'!$B68,'OCT DUMP'!$Q:$Q,"Postponed(Update Y)") -> 0 | U68: =SUM(BL68:CP68) -> 0 | V68: =IFERROR(U68/O68,0) -> 0 | X68: =COUNTIF('NOV DUMP'!C:C,'PARTNERS SUMMARY'!$B68) -> 6 | Y68: =COUNTIFS('NOV DUMP'!$C:$C,'PARTNERS SUMMARY'!$B68,'NOV DUMP'!$S:$S,"Prospect") -> 0 | Z68: =COUNTIFS('NOV DUMP'!$C:$C,'PARTNERS SUMMARY'!$B68,'NOV DUMP'!$S:$S,"Confirmed") -> 0 | AA68: =COUNTIFS('NOV DUMP'!$C:$C,'PARTNERS SUMMARY'!$B68,'NOV DUMP'!$S:$S,"Rejected") -> 0 | AB68: =COUNTIFS('NOV DUMP'!$C:$C,'PARTNERS SUMMARY'!$B68,'NOV DUMP'!$S:$S,"Unreachable") -> 0 | AC68: =COUNTIFS('NOV DUMP'!$C:$C,'PARTNERS SUMMARY'!$B68,'NOV DUMP'!$S:$S,"Postponed(Update Y)") -> 0 | AD68: =SUM(CQ68:DT68) -> 0 | AE68: =COUNTIFS('ACTIVATED LEADS '!$H:$H,'PARTNERS SUMMARY'!$B68,'ACTIVATED LEADS '!$K:$K,'PARTNERS SUMMARY'!$AE$2,'ACTIVATED LEADS '!$C:$C,"16") -> 0 | AF68: =IFERROR(AD68/X68,0) -> 0 | AH68: =COUNTIFS('ACTIVATED LEADS '!$H:$H,$B68,'ACTIVATED LEADS '!$D:$D,'PARTNERS SUMMARY'!AH$3) -> 0 | AI68: =COUNTIFS('ACTIVATED LEADS '!$H:$H,$B68,'ACTIVATED LEADS '!$D:$D,'PARTNERS SUMMARY'!AI$3) -> 0 | AJ68: =COUNTIFS('ACTIVATED LEADS '!$H:$H,$B68,'ACTIVATED LEADS '!$D:$D,'PARTNERS SUMMARY'!AJ$3) -> 0 | AK68: =COUNTIFS('ACTIVATED LEADS '!$H:$H,$B68,'ACTIVATED LEADS '!$D:$D,'PARTNERS SUMMARY'!AK$3) -> 0 | AL68: =COUNTIFS('ACTIVATED LEADS '!$H:$H,$B68,'ACTIVATED LEADS '!$D:$D,'PARTNERS SUMMARY'!AL$3) -> 0 | AM68: =COUNTIFS('ACTIVATED LEADS '!$H:$H,$B68,'ACTIVATED LEADS '!$D:$D,'PARTNERS SUMMARY'!AM$3) -> 0 | AN68: =COUNTIFS('ACTIVATED LEADS '!$H:$H,$B68,'ACTIVATED LEADS '!$D:$D,'PARTNERS SUMMARY'!AN$3) -> 0 | AO68: =COUNTIFS('ACTIVATED LEADS '!$H:$H,$B68,'ACTIVATED LEADS '!$D:$D,'PARTNERS SUMMARY'!AO$3) -> 0 | ... DO68: =COUNTIFS('ACTIVATED LEADS '!$H:$H,$B68,'ACTIVATED LEADS '!$D:$D,'PARTNERS SUMMARY'!DO$3) -> 0
A69: Betreace Chebet | B69: JOSEM COMMUNICATION | C69: 783690773 | E69: Nakuru Town | F69: Rift | G69: =COUNTIF('SEPT DUMP '!$C:$C,'PARTNERS SUMMARY'!$B69) -> 0 | H69: =COUNTIFS('SEPT DUMP '!$C:$C,'PARTNERS SUMMARY'!$B69,'SEPT DUMP '!$O:$O,"Confirmed") -> 0 | I69: =COUNTIFS('SEPT DUMP '!$C:$C,'PARTNERS SUMMARY'!$B69,'SEPT DUMP '!$O:$O,"Rejected") -> 0 | J69: =COUNTIFS('SEPT DUMP '!$C:$C,'PARTNERS SUMMARY'!$B69,'SEPT DUMP '!$O:$O,"Unreachable") -> 0 | K69: =COUNTIFS('SEPT DUMP '!$C:$C,'PARTNERS SUMMARY'!$B69,'SEPT DUMP '!$O:$O,"Postponed(Update Y)") -> 0 | L69: =SUM(AH69:BK69) -> 0 | M69: =IFERROR(L69/G69,0) -> 0 | O69: =COUNTIF('OCT DUMP'!$D:$D,'PARTNERS SUMMARY'!$B69) -> 0 | P69: =COUNTIFS('OCT DUMP'!$D:$D,'PARTNERS SUMMARY'!$B69,'OCT DUMP'!Q:Q,"Prospect") -> 0 | Q69: =COUNTIFS('OCT DUMP'!$D:$D,'PARTNERS SUMMARY'!$B69,'OCT DUMP'!$Q:$Q,"Confirmed") -> 0 | R69: =COUNTIFS('OCT DUMP'!$D:$D,'PARTNERS SUMMARY'!$B69,'OCT DUMP'!$Q:$Q,"Rejected") -> 0 | S69: =COUNTIFS('OCT DUMP'!$D:$D,'PARTNERS SUMMARY'!$B69,'OCT DUMP'!$Q:$Q,"Unreachable") -> 0 | T69: =COUNTIFS('OCT DUMP'!$D:$D,'PARTNERS SUMMARY'!$B69,'OCT DUMP'!$Q:$Q,"Postponed(Update Y)") -> 0 | U69: =SUM(BL69:CP69) -> 0 | V69: =IFERROR(U69/O69,0) -> 0 | X69: =COUNTIF('NOV DUMP'!C:C,'PARTNERS SUMMARY'!$B69) -> 0 | Y69: =COUNTIFS('NOV DUMP'!$C:$C,'PARTNERS SUMMARY'!$B69,'NOV DUMP'!$S:$S,"Prospect") -> 0 | Z69: =COUNTIFS('NOV DUMP'!$C:$C,'PARTNERS SUMMARY'!$B69,'NOV DUMP'!$S:$S,"Confirmed") -> 0 | AA69: =COUNTIFS('NOV DUMP'!$C:$C,'PARTNERS SUMMARY'!$B69,'NOV DUMP'!$S:$S,"Rejected") -> 0 | AB69: =COUNTIFS('NOV DUMP'!$C:$C,'PARTNERS SUMMARY'!$B69,'NOV DUMP'!$S:$S,"Unreachable") -> 0 | AC69: =COUNTIFS('NOV DUMP'!$C:$C,'PARTNERS SUMMARY'!$B69,'NOV DUMP'!$S:$S,"Postponed(Update Y)") -> 0 | AD69: =SUM(CQ69:DT69) -> 0 | AE69: =COUNTIFS('ACTIVATED LEADS '!$H:$H,'PARTNERS SUMMARY'!$B69,'ACTIVATED LEADS '!$K:$K,'PARTNERS SUMMARY'!$AE$2,'ACTIVATED LEADS '!$C:$C,"16") -> 0 | AF69: =IFERROR(AD69/X69,0) -> 0 | AH69: =COUNTIFS('ACTIVATED LEADS '!$H:$H,$B69,'ACTIVATED LEADS '!$D:$D,'PARTNERS SUMMARY'!AH$3) -> 0 | AI69: =COUNTIFS('ACTIVATED LEADS '!$H:$H,$B69,'ACTIVATED LEADS '!$D:$D,'PARTNERS SUMMARY'!AI$3) -> 0 | AJ69: =COUNTIFS('ACTIVATED LEADS '!$H:$H,$B69,'ACTIVATED LEADS '!$D:$D,'PARTNERS SUMMARY'!AJ$3) -> 0 | AK69: =COUNTIFS('ACTIVATED LEADS '!$H:$H,$B69,'ACTIVATED LEADS '!$D:$D,'PARTNERS SUMMARY'!AK$3) -> 0 | AL69: =COUNTIFS('ACTIVATED LEADS '!$H:$H,$B69,'ACTIVATED LEADS '!$D:$D,'PARTNERS SUMMARY'!AL$3) -> 0 | AM69: =COUNTIFS('ACTIVATED LEADS '!$H:$H,$B69,'ACTIVATED LEADS '!$D:$D,'PARTNERS SUMMARY'!AM$3) -> 0 | AN69: =COUNTIFS('ACTIVATED LEADS '!$H:$H,$B69,'ACTIVATED LEADS '!$D:$D,'PARTNERS SUMMARY'!AN$3) -> 0 | AO69: =COUNTIFS('ACTIVATED LEADS '!$H:$H,$B69,'ACTIVATED LEADS '!$D:$D,'PARTNERS SUMMARY'!AO$3) -> 0 | ... DO69: =COUNTIFS('ACTIVATED LEADS '!$H:$H,$B69,'ACTIVATED LEADS '!$D:$D,'PARTNERS SUMMARY'!DO$3) -> 0
A70: Daniel Kiragu | B70: REEF TECHNOLOGIES LIMITED | C70: 788390629 | E70: Nyeri | F70: Mountain | G70: =COUNTIF('SEPT DUMP '!$C:$C,'PARTNERS SUMMARY'!$B70) -> 0 | H70: =COUNTIFS('SEPT DUMP '!$C:$C,'PARTNERS SUMMARY'!$B70,'SEPT DUMP '!$O:$O,"Confirmed") -> 0 | I70: =COUNTIFS('SEPT DUMP '!$C:$C,'PARTNERS SUMMARY'!$B70,'SEPT DUMP '!$O:$O,"Rejected") -> 0 | J70: =COUNTIFS('SEPT DUMP '!$C:$C,'PARTNERS SUMMARY'!$B70,'SEPT DUMP '!$O:$O,"Unreachable") -> 0 | K70: =COUNTIFS('SEPT DUMP '!$C:$C,'PARTNERS SUMMARY'!$B70,'SEPT DUMP '!$O:$O,"Postponed(Update Y)") -> 0 | L70: =SUM(AH70:BK70) -> 0 | M70: =IFERROR(L70/G70,0) -> 0 | O70: =COUNTIF('OCT DUMP'!$D:$D,'PARTNERS SUMMARY'!$B70) -> 1 | P70: =COUNTIFS('OCT DUMP'!$D:$D,'PARTNERS SUMMARY'!$B70,'OCT DUMP'!Q:Q,"Prospect") -> 0 | Q70: =COUNTIFS('OCT DUMP'!$D:$D,'PARTNERS SUMMARY'!$B70,'OCT DUMP'!$Q:$Q,"Confirmed") -> 1 | R70: =COUNTIFS('OCT DUMP'!$D:$D,'PARTNERS SUMMARY'!$B70,'OCT DUMP'!$Q:$Q,"Rejected") -> 0 | S70: =COUNTIFS('OCT DUMP'!$D:$D,'PARTNERS SUMMARY'!$B70,'OCT DUMP'!$Q:$Q,"Unreachable") -> 0 | T70: =COUNTIFS('OCT DUMP'!$D:$D,'PARTNERS SUMMARY'!$B70,'OCT DUMP'!$Q:$Q,"Postponed(Update Y)") -> 0 | U70: =SUM(BL70:CP70) -> 0 | V70: =IFERROR(U70/O70,0) -> 0 | X70: =COUNTIF('NOV DUMP'!C:C,'PARTNERS SUMMARY'!$B70) -> 0 | Y70: =COUNTIFS('NOV DUMP'!$C:$C,'PARTNERS SUMMARY'!$B70,'NOV DUMP'!$S:$S,"Prospect") -> 0 | Z70: =COUNTIFS('NOV DUMP'!$C:$C,'PARTNERS SUMMARY'!$B70,'NOV DUMP'!$S:$S,"Confirmed") -> 0 | AA70: =COUNTIFS('NOV DUMP'!$C:$C,'PARTNERS SUMMARY'!$B70,'NOV DUMP'!$S:$S,"Rejected") -> 0 | AB70: =COUNTIFS('NOV DUMP'!$C:$C,'PARTNERS SUMMARY'!$B70,'NOV DUMP'!$S:$S,"Unreachable") -> 0 | AC70: =COUNTIFS('NOV DUMP'!$C:$C,'PARTNERS SUMMARY'!$B70,'NOV DUMP'!$S:$S,"Postponed(Update Y)") -> 0 | AD70: =SUM(CQ70:DT70) -> 0 | AE70: =COUNTIFS('ACTIVATED LEADS '!$H:$H,'PARTNERS SUMMARY'!$B70,'ACTIVATED LEADS '!$K:$K,'PARTNERS SUMMARY'!$AE$2,'ACTIVATED LEADS '!$C:$C,"16") -> 0 | AF70: =IFERROR(AD70/X70,0) -> 0 | AH70: =COUNTIFS('ACTIVATED LEADS '!$H:$H,$B70,'ACTIVATED LEADS '!$D:$D,'PARTNERS SUMMARY'!AH$3) -> 0 | AI70: =COUNTIFS('ACTIVATED LEADS '!$H:$H,$B70,'ACTIVATED LEADS '!$D:$D,'PARTNERS SUMMARY'!AI$3) -> 0 | AJ70: =COUNTIFS('ACTIVATED LEADS '!$H:$H,$B70,'ACTIVATED LEADS '!$D:$D,'PARTNERS SUMMARY'!AJ$3) -> 0 | AK70: =COUNTIFS('ACTIVATED LEADS '!$H:$H,$B70,'ACTIVATED LEADS '!$D:$D,'PARTNERS SUMMARY'!AK$3) -> 0 | AL70: =COUNTIFS('ACTIVATED LEADS '!$H:$H,$B70,'ACTIVATED LEADS '!$D:$D,'PARTNERS SUMMARY'!AL$3) -> 0 | AM70: =COUNTIFS('ACTIVATED LEADS '!$H:$H,$B70,'ACTIVATED LEADS '!$D:$D,'PARTNERS SUMMARY'!AM$3) -> 0 | AN70: =COUNTIFS('ACTIVATED LEADS '!$H:$H,$B70,'ACTIVATED LEADS '!$D:$D,'PARTNERS SUMMARY'!AN$3) -> 0 | AO70: =COUNTIFS('ACTIVATED LEADS '!$H:$H,$B70,'ACTIVATED LEADS '!$D:$D,'PARTNERS SUMMARY'!AO$3) -> 0 | ... DO70: =COUNTIFS('ACTIVATED LEADS '!$H:$H,$B70,'ACTIVATED LEADS '!$D:$D,'PARTNERS SUMMARY'!DO$3) -> 0
A71: Damaris Mainga | B71: BOSIMA ENTERPRISE | C71: 782722896 | E71: Nairobi CBD | F71: Nairobi | G71: =COUNTIF('SEPT DUMP '!$C:$C,'PARTNERS SUMMARY'!$B71) -> 0 | H71: =COUNTIFS('SEPT DUMP '!$C:$C,'PARTNERS SUMMARY'!$B71,'SEPT DUMP '!$O:$O,"Confirmed") -> 0 | I71: =COUNTIFS('SEPT DUMP '!$C:$C,'PARTNERS SUMMARY'!$B71,'SEPT DUMP '!$O:$O,"Rejected") -> 0 | J71: =COUNTIFS('SEPT DUMP '!$C:$C,'PARTNERS SUMMARY'!$B71,'SEPT DUMP '!$O:$O,"Unreachable") -> 0 | K71: =COUNTIFS('SEPT DUMP '!$C:$C,'PARTNERS SUMMARY'!$B71,'SEPT DUMP '!$O:$O,"Postponed(Update Y)") -> 0 | L71: =SUM(AH71:BK71) -> 0 | M71: =IFERROR(L71/G71,0) -> 0 | O71: =COUNTIF('OCT DUMP'!$D:$D,'PARTNERS SUMMARY'!$B71) -> 0 | P71: =COUNTIFS('OCT DUMP'!$D:$D,'PARTNERS SUMMARY'!$B71,'OCT DUMP'!Q:Q,"Prospect") -> 0 | Q71: =COUNTIFS('OCT DUMP'!$D:$D,'PARTNERS SUMMARY'!$B71,'OCT DUMP'!$Q:$Q,"Confirmed") -> 0 | R71: =COUNTIFS('OCT DUMP'!$D:$D,'PARTNERS SUMMARY'!$B71,'OCT DUMP'!$Q:$Q,"Rejected") -> 0 | S71: =COUNTIFS('OCT DUMP'!$D:$D,'PARTNERS SUMMARY'!$B71,'OCT DUMP'!$Q:$Q,"Unreachable") -> 0 | T71: =COUNTIFS('OCT DUMP'!$D:$D,'PARTNERS SUMMARY'!$B71,'OCT DUMP'!$Q:$Q,"Postponed(Update Y)") -> 0 | U71: =SUM(BL71:CP71) -> 0 | V71: =IFERROR(U71/O71,0) -> 0 | X71: =COUNTIF('NOV DUMP'!C:C,'PARTNERS SUMMARY'!$B71) -> 0 | Y71: =COUNTIFS('NOV DUMP'!$C:$C,'PARTNERS SUMMARY'!$B71,'NOV DUMP'!$S:$S,"Prospect") -> 0 | Z71: =COUNTIFS('NOV DUMP'!$C:$C,'PARTNERS SUMMARY'!$B71,'NOV DUMP'!$S:$S,"Confirmed") -> 0 | AA71: =COUNTIFS('NOV DUMP'!$C:$C,'PARTNERS SUMMARY'!$B71,'NOV DUMP'!$S:$S,"Rejected") -> 0 | AB71: =COUNTIFS('NOV DUMP'!$C:$C,'PARTNERS SUMMARY'!$B71,'NOV DUMP'!$S:$S,"Unreachable") -> 0 | AC71: =COUNTIFS('NOV DUMP'!$C:$C,'PARTNERS SUMMARY'!$B71,'NOV DUMP'!$S:$S,"Postponed(Update Y)") -> 0 | AD71: =SUM(CQ71:DT71) -> 0 | AE71: =COUNTIFS('ACTIVATED LEADS '!$H:$H,'PARTNERS SUMMARY'!$B71,'ACTIVATED LEADS '!$K:$K,'PARTNERS SUMMARY'!$AE$2,'ACTIVATED LEADS '!$C:$C,"16") -> 0 | AF71: =IFERROR(AD71/X71,0) -> 0 | AH71: =COUNTIFS('ACTIVATED LEADS '!$H:$H,$B71,'ACTIVATED LEADS '!$D:$D,'PARTNERS SUMMARY'!AH$3) -> 0 | AI71: =COUNTIFS('ACTIVATED LEADS '!$H:$H,$B71,'ACTIVATED LEADS '!$D:$D,'PARTNERS SUMMARY'!AI$3) -> 0 | AJ71: =COUNTIFS('ACTIVATED LEADS '!$H:$H,$B71,'ACTIVATED LEADS '!$D:$D,'PARTNERS SUMMARY'!AJ$3) -> 0 | AK71: =COUNTIFS('ACTIVATED LEADS '!$H:$H,$B71,'ACTIVATED LEADS '!$D:$D,'PARTNERS SUMMARY'!AK$3) -> 0 | AL71: =COUNTIFS('ACTIVATED LEADS '!$H:$H,$B71,'ACTIVATED LEADS '!$D:$D,'PARTNERS SUMMARY'!AL$3) -> 0 | AM71: =COUNTIFS('ACTIVATED LEADS '!$H:$H,$B71,'ACTIVATED LEADS '!$D:$D,'PARTNERS SUMMARY'!AM$3) -> 0 | AN71: =COUNTIFS('ACTIVATED LEADS '!$H:$H,$B71,'ACTIVATED LEADS '!$D:$D,'PARTNERS SUMMARY'!AN$3) -> 0 | AO71: =COUNTIFS('ACTIVATED LEADS '!$H:$H,$B71,'ACTIVATED LEADS '!$D:$D,'PARTNERS SUMMARY'!AO$3) -> 0 | ... DO71: =COUNTIFS('ACTIVATED LEADS '!$H:$H,$B71,'ACTIVATED LEADS '!$D:$D,'PARTNERS SUMMARY'!DO$3) -> 0
